Workbook

Sheet Graphs
A1: Painel - Terras agrícolas: preços, retornos e índice (estilo NCREIF)
A2: Todos os gráficos leem as fórmulas das abas Asset Value, Rent e Returns. Dados auxiliares dos gráficos estão abaixo (linha 84 em diante).
A84: DADOS DOS GRÁFICOS (fórmulas)
A86: Ano | B86: 2008 | C86: =B86+1 -> 2009 | D86: =C86+1 -> 2010 | E86: =D86+1 -> 2011 | F86: =E86+1 -> 2012 | G86: =F86+1 -> 2013 | H86: =G86+1 -> 2014 | I86: =H86+1 -> 2015
A87: Preço médio da terra (R$/ha) | B87: =SUMIFS('Asset Value'!$F$4:$F$500,'Asset Value'!$B$4:$B$500,B$86)/SUMIFS('Asset Value'!$D$4:$D$500,'Asset Value'!$B$4:$B$500,B$86) -> 6546.9425 | C87: =SUMIFS('Asset Value'!$F$4:$F$500,'Asset Value'!$B$4:$B$500,C$86)/SUMIFS('Asset Value'!$D$4:$D$500,'Asset Value'!$B$4:$B$500,C$86) -> 6865.2147 | D87: =SUMIFS('Asset Value'!$F$4:$F$500,'Asset Value'!$B$4:$B$500,D$86)/SUMIFS('Asset Value'!$D$4:$D$500,'Asset Value'!$B$4:$B$500,D$86) -> 6530.6176 | E87: =SUMIFS('Asset Value'!$F$4:$F$500,'Asset Value'!$B$4:$B$500,E$86)/SUMIFS('Asset Value'!$D$4:$D$500,'Asset Value'!$B$4:$B$500,E$86) -> 7875.1827 | F87: =SUMIFS('Asset Value'!$F$4:$F$500,'Asset Value'!$B$4:$B$500,F$86)/SUMIFS('Asset Value'!$D$4:$D$500,'Asset Value'!$B$4:$B$500,F$86) -> 7836.6341 | G87: =SUMIFS('Asset Value'!$F$4:$F$500,'Asset Value'!$B$4:$B$500,G$86)/SUMIFS('Asset Value'!$D$4:$D$500,'Asset Value'!$B$4:$B$500,G$86) -> 9206.3811 | H87: =SUMIFS('Asset Value'!$F$4:$F$500,'Asset Value'!$B$4:$B$500,H$86)/SUMIFS('Asset Value'!$D$4:$D$500,'Asset Value'!$B$4:$B$500,H$86) -> 10488.376 | I87: =SUMIFS('Asset Value'!$F$4:$F$500,'Asset Value'!$B$4:$B$500,I$86)/SUMIFS('Asset Value'!$D$4:$D$500,'Asset Value'!$B$4:$B$500,I$86) -> 11019.247
A88: Preço médio da terra (US$/ha) | B88: =SUMIFS('Asset Value'!$I$4:$I$500,'Asset Value'!$B$4:$B$500,B$86)/SUMIFS('Asset Value'!$D$4:$D$500,'Asset Value'!$B$4:$B$500,B$86) -> 3882.2003 | C88: =SUMIFS('Asset Value'!$I$4:$I$500,'Asset Value'!$B$4:$B$500,C$86)/SUMIFS('Asset Value'!$D$4:$D$500,'Asset Value'!$B$4:$B$500,C$86) -> 3409.4233 | D88: =SUMIFS('Asset Value'!$I$4:$I$500,'Asset Value'!$B$4:$B$500,D$86)/SUMIFS('Asset Value'!$D$4:$D$500,'Asset Value'!$B$4:$B$500,D$86) -> 3775.3599 | E88: =SUMIFS('Asset Value'!$I$4:$I$500,'Asset Value'!$B$4:$B$500,E$86)/SUMIFS('Asset Value'!$D$4:$D$500,'Asset Value'!$B$4:$B$500,E$86) -> 4890.5066 | F88: =SUMIFS('Asset Value'!$I$4:$I$500,'Asset Value'!$B$4:$B$500,F$86)/SUMIFS('Asset Value'!$D$4:$D$500,'Asset Value'!$B$4:$B$500,F$86) -> 3858.8902 | G88: =SUMIFS('Asset Value'!$I$4:$I$500,'Asset Value'!$B$4:$B$500,G$86)/SUMIFS('Asset Value'!$D$4:$D$500,'Asset Value'!$B$4:$B$500,G$86) -> 4050.4999 | H88: =SUMIFS('Asset Value'!$I$4:$I$500,'Asset Value'!$B$4:$B$500,H$86)/SUMIFS('Asset Value'!$D$4:$D$500,'Asset Value'!$B$4:$B$500,H$86) -> 4626.9526 | I88: =SUMIFS('Asset Value'!$I$4:$I$500,'Asset Value'!$B$4:$B$500,I$86)/SUMIFS('Asset Value'!$D$4:$D$500,'Asset Value'!$B$4:$B$500,I$86) -> 3247.2586
A89: Valor de mercado do portfólio (R$ mm) | B89: =SUMIFS(Returns!$E$120:$E$239,Returns!$B$120:$B$239,B$86)/1000 -> 1096.77 | C89: =SUMIFS(Returns!$E$120:$E$239,Returns!$B$120:$B$239,C$86)/1000 -> 1495.69 | D89: =SUMIFS(Returns!$E$120:$E$239,Returns!$B$120:$B$239,D$86)/1000 -> 1500.93 | E89: =SUMIFS(Returns!$E$120:$E$239,Returns!$B$120:$B$239,E$86)/1000 -> 1756.15 | F89: =SUMIFS(Returns!$E$120:$E$239,Returns!$B$120:$B$239,F$86)/1000 -> 2315.6 | G89: =SUMIFS(Returns!$E$120:$E$239,Returns!$B$120:$B$239,G$86)/1000 -> 2678.615 | H89: =SUMIFS(Returns!$E$120:$E$239,Returns!$B$120:$B$239,H$86)/1000 -> 3188.76 | I89: =SUMIFS(Returns!$E$120:$E$239,Returns!$B$120:$B$239,I$86)/1000 -> 3401.84
A90: Valor de mercado do portfólio (US$ mm) | B90: =SUMIFS(Returns!$E$244:$E$363,Returns!$B$244:$B$363,B$86)/1000 -> 650.36172 | C90: =SUMIFS(Returns!$E$244:$E$363,Returns!$B$244:$B$363,C$86)/1000 -> 742.794 | D90: =SUMIFS(Returns!$E$244:$E$363,Returns!$B$244:$B$363,D$86)/1000 -> 867.86057 | E90: =SUMIFS(Returns!$E$244:$E$363,Returns!$B$244:$B$363,E$86)/1000 -> 1090.5732 | F90: =SUMIFS(Returns!$E$244:$E$363,Returns!$B$244:$B$363,F$86)/1000 -> 1140.2403 | G90: =SUMIFS(Returns!$E$244:$E$363,Returns!$B$244:$B$363,G$86)/1000 -> 1178.501 | H90: =SUMIFS(Returns!$E$244:$E$363,Returns!$B$244:$B$363,H$86)/1000 -> 1406.7231 | I90: =SUMIFS(Returns!$E$244:$E$363,Returns!$B$244:$B$363,I$86)/1000 -> 1002.4872
A91: Nº de fazendas avaliadas | B91: =COUNTIFS(Returns!$B$120:$B$239,B$86,Returns!$E$120:$E$239,">0") -> 9 | C91: =COUNTIFS(Returns!$B$120:$B$239,C$86,Returns!$E$120:$E$239,">0") -> 11 | D91: =COUNTIFS(Returns!$B$120:$B$239,D$86,Returns!$E$120:$E$239,">0") -> 11 | E91: =COUNTIFS(Returns!$B$120:$B$239,E$86,Returns!$E$120:$E$239,">0") -> 10 | F91: =COUNTIFS(Returns!$B$120:$B$239,F$86,Returns!$E$120:$E$239,">0") -> 14 | G91: =COUNTIFS(Returns!$B$120:$B$239,G$86,Returns!$E$120:$E$239,">0") -> 14 | H91: =COUNTIFS(Returns!$B$120:$B$239,H$86,Returns!$E$120:$E$239,">0") -> 13 | I91: =COUNTIFS(Returns!$B$120:$B$239,I$86,Returns!$E$120:$E$239,">0") -> 13
A92: PTAX na data da avaliação (R$/US$) | B92: =IFERROR(AVERAGEIFS('Asset Value'!$H$4:$H$500,'Asset Value'!$B$4:$B$500,B$86),0) -> 1.6864 | C92: =IFERROR(AVERAGEIFS('Asset Value'!$H$4:$H$500,'Asset Value'!$B$4:$B$500,C$86),0) -> 2.0136 | D92: =IFERROR(AVERAGEIFS('Asset Value'!$H$4:$H$500,'Asset Value'!$B$4:$B$500,D$86),0) -> 1.7298 | E92: =IFERROR(AVERAGEIFS('Asset Value'!$H$4:$H$500,'Asset Value'!$B$4:$B$500,E$86),0) -> 1.6103 | F92: =IFERROR(AVERAGEIFS('Asset Value'!$H$4:$H$500,'Asset Value'!$B$4:$B$500,F$86),0) -> 2.0308 | G92: =IFERROR(AVERAGEIFS('Asset Value'!$H$4:$H$500,'Asset Value'!$B$4:$B$500,G$86),0) -> 2.2729 | H92: =IFERROR(AVERAGEIFS('Asset Value'!$H$4:$H$500,'Asset Value'!$B$4:$B$500,H$86),0) -> 2.2668 | I92: =IFERROR(AVERAGEIFS('Asset Value'!$H$4:$H$500,'Asset Value'!$B$4:$B$500,I$86),0) -> 3.3934
A93: PTAX em 31/dez (data do rent) (R$/US$) | B93: =IFERROR(AVERAGEIFS(Rent!$F$3:$F$500,Rent!$C$3:$C$500,B$86),0) -> 2.3362 | C93: =IFERROR(AVERAGEIFS(Rent!$F$3:$F$500,Rent!$C$3:$C$500,C$86),0) -> 1.7404 | D93: =IFERROR(AVERAGEIFS(Rent!$F$3:$F$500,Rent!$C$3:$C$500,D$86),0) -> 1.6654 | E93: =IFERROR(AVERAGEIFS(Rent!$F$3:$F$500,Rent!$C$3:$C$500,E$86),0) -> 1.8751 | F93: =IFERROR(AVERAGEIFS(Rent!$F$3:$F$500,Rent!$C$3:$C$500,F$86),0) -> 2.0429 | G93: =IFERROR(AVERAGEIFS(Rent!$F$3:$F$500,Rent!$C$3:$C$500,G$86),0) -> 2.342 | H93: =IFERROR(AVERAGEIFS(Rent!$F$3:$F$500,Rent!$C$3:$C$500,H$86),0) -> 2.6556 | I93: =IFERROR(AVERAGEIFS(Rent!$F$3:$F$500,Rent!$C$3:$C$500,I$86),0) -> 3.9042
A95: Preço da terra por fazenda (R$/ha) = Valor / Área
A96: Farm | B96: =B86 -> 2008 | C96: =C86 -> 2009 | D96: =D86 -> 2010 | E96: =E86 -> 2011 | F96: =F86 -> 2012 | G96: =G86 -> 2013 | H96: =H86 -> 2014 | I96: =I86 -> 2015 | J96: 1º ano | K96: Último ano | L96: R$/ha 1º | M96: R$/ha último | N96: Valorização total | O96: CAGR a.a.
A97: Fazenda Pamplona | B97: =IFERROR(SUMIFS('Asset Value'!$F$4:$F$500,'Asset Value'!$C$4:$C$500,$A97,'Asset Value'!$B$4:$B$500,B$96)/SUMIFS('Asset Value'!$D$4:$D$500,'Asset Value'!$C$4:$C$500,$A97,'Asset Value'!$B$4:$B$500,B$96),0) -> 8401.1934 | C97: =IFERROR(SUMIFS('Asset Value'!$F$4:$F$500,'Asset Value'!$C$4:$C$500,$A97,'Asset Value'!$B$4:$B$500,C$96)/SUMIFS('Asset Value'!$D$4:$D$500,'Asset Value'!$C$4:$C$500,$A97,'Asset Value'!$B$4:$B$500,C$96),0) -> 9255.8793 | D97: =IFERROR(SUMIFS('Asset Value'!$F$4:$F$500,'Asset Value'!$C$4:$C$500,$A97,'Asset Value'!$B$4:$B$500,D$96)/SUMIFS('Asset Value'!$D$4:$D$500,'Asset Value'!$C$4:$C$500,$A97,'Asset Value'!$B$4:$B$500,D$96),0) -> 9608.0496 | E97: =IFERROR(SUMIFS('Asset Value'!$F$4:$F$500,'Asset Value'!$C$4:$C$500,$A97,'Asset Value'!$B$4:$B$500,E$96)/SUMIFS('Asset Value'!$D$4:$D$500,'Asset Value'!$C$4:$C$500,$A97,'Asset Value'!$B$4:$B$500,E$96),0) -> 10504.856 | F97: =IFERROR(SUMIFS('Asset Value'!$F$4:$F$500,'Asset Value'!$C$4:$C$500,$A97,'Asset Value'!$B$4:$B$500,F$96)/SUMIFS('Asset Value'!$D$4:$D$500,'Asset Value'!$C$4:$C$500,$A97,'Asset Value'!$B$4:$B$500,F$96),0) -> 12403.221 | G97: =IFERROR(SUMIFS('Asset Value'!$F$4:$F$500,'Asset Value'!$C$4:$C$500,$A97,'Asset Value'!$B$4:$B$500,G$96)/SUMIFS('Asset Value'!$D$4:$D$500,'Asset Value'!$C$4:$C$500,$A97,'Asset Value'!$B$4:$B$500,G$96),0) -> 12904.343 | H97: =IFERROR(SUMIFS('Asset Value'!$F$4:$F$500,'Asset Value'!$C$4:$C$500,$A97,'Asset Value'!$B$4:$B$500,H$96)/SUMIFS('Asset Value'!$D$4:$D$500,'Asset Value'!$C$4:$C$500,$A97,'Asset Value'!$B$4:$B$500,H$96),0) -> 15526.086 | I97: =IFERROR(SUMIFS('Asset Value'!$F$4:$F$500,'Asset Value'!$C$4:$C$500,$A97,'Asset Value'!$B$4:$B$500,I$96)/SUMIFS('Asset Value'!$D$4:$D$500,'Asset Value'!$C$4:$C$500,$A97,'Asset Value'!$B$4:$B$500,I$96),0) -> 15994.062 | J97: =_xlfn.MINIFS($B$86:$I$86,$B97:$I97,">0") -> 2008 | K97: =_xlfn.MAXIFS($B$86:$I$86,$B97:$I97,">0") -> 2015 | L97: =INDEX($B97:$I97,MATCH(J97,$B$86:$I$86,0)) -> 8401.1934 | M97: =INDEX($B97:$I97,MATCH(K97,$B$86:$I$86,0)) -> 15994.062 | N97: =M97/L97-1 -> 0.90378453 | O97: =IF(K97>J97,(M97/L97)^(1/(K97-J97))-1,"") -> 0.096340352
A98: Fazenda Planalto | B98: =IFERROR(SUMIFS('Asset Value'!$F$4:$F$500,'Asset Value'!$C$4:$C$500,$A98,'Asset Value'!$B$4:$B$500,B$96)/SUMIFS('Asset Value'!$D$4:$D$500,'Asset Value'!$C$4:$C$500,$A98,'Asset Value'!$B$4:$B$500,B$96),0) -> 11876.608 | C98: =IFERROR(SUMIFS('Asset Value'!$F$4:$F$500,'Asset Value'!$C$4:$C$500,$A98,'Asset Value'!$B$4:$B$500,C$96)/SUMIFS('Asset Value'!$D$4:$D$500,'Asset Value'!$C$4:$C$500,$A98,'Asset Value'!$B$4:$B$500,C$96),0) -> 13426.154 | D98: =IFERROR(SUMIFS('Asset Value'!$F$4:$F$500,'Asset Value'!$C$4:$C$500,$A98,'Asset Value'!$B$4:$B$500,D$96)/SUMIFS('Asset Value'!$D$4:$D$500,'Asset Value'!$C$4:$C$500,$A98,'Asset Value'!$B$4:$B$500,D$96),0) -> 13825.615 | E98: =IFERROR(SUMIFS('Asset Value'!$F$4:$F$500,'Asset Value'!$C$4:$C$500,$A98,'Asset Value'!$B$4:$B$500,E$96)/SUMIFS('Asset Value'!$D$4:$D$500,'Asset Value'!$C$4:$C$500,$A98,'Asset Value'!$B$4:$B$500,E$96),0) -> 15709.124 | F98: =IFERROR(SUMIFS('Asset Value'!$F$4:$F$500,'Asset Value'!$C$4:$C$500,$A98,'Asset Value'!$B$4:$B$500,F$96)/SUMIFS('Asset Value'!$D$4:$D$500,'Asset Value'!$C$4:$C$500,$A98,'Asset Value'!$B$4:$B$500,F$96),0) -> 18485.978 | G98: =IFERROR(SUMIFS('Asset Value'!$F$4:$F$500,'Asset Value'!$C$4:$C$500,$A98,'Asset Value'!$B$4:$B$500,G$96)/SUMIFS('Asset Value'!$D$4:$D$500,'Asset Value'!$C$4:$C$500,$A98,'Asset Value'!$B$4:$B$500,G$96),0) -> 19023.456 | H98: =IFERROR(SUMIFS('Asset Value'!$F$4:$F$500,'Asset Value'!$C$4:$C$500,$A98,'Asset Value'!$B$4:$B$500,H$96)/SUMIFS('Asset Value'!$D$4:$D$500,'Asset Value'!$C$4:$C$500,$A98,'Asset Value'!$B$4:$B$500,H$96),0) -> 25994.036 | I98: =IFERROR(SUMIFS('Asset Value'!$F$4:$F$500,'Asset Value'!$C$4:$C$500,$A98,'Asset Value'!$B$4:$B$500,I$96)/SUMIFS('Asset Value'!$D$4:$D$500,'Asset Value'!$C$4:$C$500,$A98,'Asset Value'!$B$4:$B$500,I$96),0) -> 27157.768 | J98: =_xlfn.MINIFS($B$86:$I$86,$B98:$I98,">0") -> 2008 | K98: =_xlfn.MAXIFS($B$86:$I$86,$B98:$I98,">0") -> 2015 | L98: =INDEX($B98:$I98,MATCH(J98,$B$86:$I$86,0)) -> 11876.608 | M98: =INDEX($B98:$I98,MATCH(K98,$B$86:$I$86,0)) -> 27157.768 | N98: =M98/L98-1 -> 1.2866603 | O98: =IF(K98>J98,(M98/L98)^(1/(K98-J98))-1,"") -> 0.12541972
A99: Fazenda Planeste | B99: =IFERROR(SUMIFS('Asset Value'!$F$4:$F$500,'Asset Value'!$C$4:$C$500,$A99,'Asset Value'!$B$4:$B$500,B$96)/SUMIFS('Asset Value'!$D$4:$D$500,'Asset Value'!$C$4:$C$500,$A99,'Asset Value'!$B$4:$B$500,B$96),0) -> 5857.8002 | C99: =IFERROR(SUMIFS('Asset Value'!$F$4:$F$500,'Asset Value'!$C$4:$C$500,$A99,'Asset Value'!$B$4:$B$500,C$96)/SUMIFS('Asset Value'!$D$4:$D$500,'Asset Value'!$C$4:$C$500,$A99,'Asset Value'!$B$4:$B$500,C$96),0) -> 6465.8195 | D99: =IFERROR(SUMIFS('Asset Value'!$F$4:$F$500,'Asset Value'!$C$4:$C$500,$A99,'Asset Value'!$B$4:$B$500,D$96)/SUMIFS('Asset Value'!$D$4:$D$500,'Asset Value'!$C$4:$C$500,$A99,'Asset Value'!$B$4:$B$500,D$96),0) -> 6239.0837 | E99: =IFERROR(SUMIFS('Asset Value'!$F$4:$F$500,'Asset Value'!$C$4:$C$500,$A99,'Asset Value'!$B$4:$B$500,E$96)/SUMIFS('Asset Value'!$D$4:$D$500,'Asset Value'!$C$4:$C$500,$A99,'Asset Value'!$B$4:$B$500,E$96),0) -> 7590.7316 | F99: =IFERROR(SUMIFS('Asset Value'!$F$4:$F$500,'Asset Value'!$C$4:$C$500,$A99,'Asset Value'!$B$4:$B$500,F$96)/SUMIFS('Asset Value'!$D$4:$D$500,'Asset Value'!$C$4:$C$500,$A99,'Asset Value'!$B$4:$B$500,F$96),0) -> 8466.0665 | G99: =IFERROR(SUMIFS('Asset Value'!$F$4:$F$500,'Asset Value'!$C$4:$C$500,$A99,'Asset Value'!$B$4:$B$500,G$96)/SUMIFS('Asset Value'!$D$4:$D$500,'Asset Value'!$C$4:$C$500,$A99,'Asset Value'!$B$4:$B$500,G$96),0) -> 9440.6431 | H99: =IFERROR(SUMIFS('Asset Value'!$F$4:$F$500,'Asset Value'!$C$4:$C$500,$A99,'Asset Value'!$B$4:$B$500,H$96)/SUMIFS('Asset Value'!$D$4:$D$500,'Asset Value'!$C$4:$C$500,$A99,'Asset Value'!$B$4:$B$500,H$96),0) -> 9846.6881 | I99: =IFERROR(SUMIFS('Asset Value'!$F$4:$F$500,'Asset Value'!$C$4:$C$500,$A99,'Asset Value'!$B$4:$B$500,I$96)/SUMIFS('Asset Value'!$D$4:$D$500,'Asset Value'!$C$4:$C$500,$A99,'Asset Value'!$B$4:$B$500,I$96),0) -> 10055.303 | J99: =_xlfn.MINIFS($B$86:$I$86,$B99:$I99,">0") -> 2008 | K99: =_xlfn.MAXIFS($B$86:$I$86,$B99:$I99,">0") -> 2015 | L99: =INDEX($B99:$I99,MATCH(J99,$B$86:$I$86,0)) -> 5857.8002 | M99: =INDEX($B99:$I99,MATCH(K99,$B$86:$I$86,0)) -> 10055.303 | N99: =M99/L99-1 -> 0.71656642 | O99: =IF(K99>J99,(M99/L99)^(1/(K99-J99))-1,"") -> 0.080246691
A100: Fazenda Panorama | B100: =IFERROR(SUMIFS('Asset Value'!$F$4:$F$500,'Asset Value'!$C$4:$C$500,$A100,'Asset Value'!$B$4:$B$500,B$96)/SUMIFS('Asset Value'!$D$4:$D$500,'Asset Value'!$C$4:$C$500,$A100,'Asset Value'!$B$4:$B$500,B$96),0) -> 8144.2516 | C100: =IFERROR(SUMIFS('Asset Value'!$F$4:$F$500,'Asset Value'!$C$4:$C$500,$A100,'Asset Value'!$B$4:$B$500,C$96)/SUMIFS('Asset Value'!$D$4:$D$500,'Asset Value'!$C$4:$C$500,$A100,'Asset Value'!$B$4:$B$500,C$96),0) -> 9366.5944 | D100: =IFERROR(SUMIFS('Asset Value'!$F$4:$F$500,'Asset Value'!$C$4:$C$500,$A100,'Asset Value'!$B$4:$B$500,D$96)/SUMIFS('Asset Value'!$D$4:$D$500,'Asset Value'!$C$4:$C$500,$A100,'Asset Value'!$B$4:$B$500,D$96),0) -> 9910.3528 | E100: =IFERROR(SUMIFS('Asset Value'!$F$4:$F$500,'Asset Value'!$C$4:$C$500,$A100,'Asset Value'!$B$4:$B$500,E$96)/SUMIFS('Asset Value'!$D$4:$D$500,'Asset Value'!$C$4:$C$500,$A100,'Asset Value'!$B$4:$B$500,E$96),0) -> 11301.032 | F100: =IFERROR(SUMIFS('Asset Value'!$F$4:$F$500,'Asset Value'!$C$4:$C$500,$A100,'Asset Value'!$B$4:$B$500,F$96)/SUMIFS('Asset Value'!$D$4:$D$500,'Asset Value'!$C$4:$C$500,$A100,'Asset Value'!$B$4:$B$500,F$96),0) -> 12899.176 | G100: =IFERROR(SUMIFS('Asset Value'!$F$4:$F$500,'Asset Value'!$C$4:$C$500,$A100,'Asset Value'!$B$4:$B$500,G$96)/SUMIFS('Asset Value'!$D$4:$D$500,'Asset Value'!$C$4:$C$500,$A100,'Asset Value'!$B$4:$B$500,G$96),0) -> 14021.207 | H100: =IFERROR(SUMIFS('Asset Value'!$F$4:$F$500,'Asset Value'!$C$4:$C$500,$A100,'Asset Value'!$B$4:$B$500,H$96)/SUMIFS('Asset Value'!$D$4:$D$500,'Asset Value'!$C$4:$C$500,$A100,'Asset Value'!$B$4:$B$500,H$96),0) -> 15071.332 | I100: =IFERROR(SUMIFS('Asset Value'!$F$4:$F$500,'Asset Value'!$C$4:$C$500,$A100,'Asset Value'!$B$4:$B$500,I$96)/SUMIFS('Asset Value'!$D$4:$D$500,'Asset Value'!$C$4:$C$500,$A100,'Asset Value'!$B$4:$B$500,I$96),0) -> 16042.992 | J100: =_xlfn.MINIFS($B$86:$I$86,$B100:$I100,">0") -> 2008 | K100: =_xlfn.MAXIFS($B$86:$I$86,$B100:$I100,">0") -> 2015 | L100: =INDEX($B100:$I100,MATCH(J100,$B$86:$I$86,0)) -> 8144.2516 | M100: =INDEX($B100:$I100,MATCH(K100,$B$86:$I$86,0)) -> 16042.992 | N100: =M100/L100-1 -> 0.96985467 | O100: =IF(K100>J100,(M100/L100)^(1/(K100-J100))-1,"") -> 0.10169664
A101: Fazenda Piratini | B101: =IFERROR(SUMIFS('Asset Value'!$F$4:$F$500,'Asset Value'!$C$4:$C$500,$A101,'Asset Value'!$B$4:$B$500,B$96)/SUMIFS('Asset Value'!$D$4:$D$500,'Asset Value'!$C$4:$C$500,$A101,'Asset Value'!$B$4:$B$500,B$96),0) -> 2356.6115 | C101: =IFERROR(SUMIFS('Asset Value'!$F$4:$F$500,'Asset Value'!$C$4:$C$500,$A101,'Asset Value'!$B$4:$B$500,C$96)/SUMIFS('Asset Value'!$D$4:$D$500,'Asset Value'!$C$4:$C$500,$A101,'Asset Value'!$B$4:$B$500,C$96),0) -> 3793.2965 | D101: =IFERROR(SUMIFS('Asset Value'!$F$4:$F$500,'Asset Value'!$C$4:$C$500,$A101,'Asset Value'!$B$4:$B$500,D$96)/SUMIFS('Asset Value'!$D$4:$D$500,'Asset Value'!$C$4:$C$500,$A101,'Asset Value'!$B$4:$B$500,D$96),0) -> 3226.5825 | E101: =IFERROR(SUMIFS('Asset Value'!$F$4:$F$500,'Asset Value'!$C$4:$C$500,$A101,'Asset Value'!$B$4:$B$500,E$96)/SUMIFS('Asset Value'!$D$4:$D$500,'Asset Value'!$C$4:$C$500,$A101,'Asset Value'!$B$4:$B$500,E$96),0) -> 4615.2633 | F101: =IFERROR(SUMIFS('Asset Value'!$F$4:$F$500,'Asset Value'!$C$4:$C$500,$A101,'Asset Value'!$B$4:$B$500,F$96)/SUMIFS('Asset Value'!$D$4:$D$500,'Asset Value'!$C$4:$C$500,$A101,'Asset Value'!$B$4:$B$500,F$96),0) -> 5268.5072 | G101: =IFERROR(SUMIFS('Asset Value'!$F$4:$F$500,'Asset Value'!$C$4:$C$500,$A101,'Asset Value'!$B$4:$B$500,G$96)/SUMIFS('Asset Value'!$D$4:$D$500,'Asset Value'!$C$4:$C$500,$A101,'Asset Value'!$B$4:$B$500,G$96),0) -> 6957.3654 | H101: =IFERROR(SUMIFS('Asset Value'!$F$4:$F$500,'Asset Value'!$C$4:$C$500,$A101,'Asset Value'!$B$4:$B$500,H$96)/SUMIFS('Asset Value'!$D$4:$D$500,'Asset Value'!$C$4:$C$500,$A101,'Asset Value'!$B$4:$B$500,H$96),0) -> 7817.393 | I101: =IFERROR(SUMIFS('Asset Value'!$F$4:$F$500,'Asset Value'!$C$4:$C$500,$A101,'Asset Value'!$B$4:$B$500,I$96)/SUMIFS('Asset Value'!$D$4:$D$500,'Asset Value'!$C$4:$C$500,$A101,'Asset Value'!$B$4:$B$500,I$96),0) -> 8789.2412 | J101: =_xlfn.MINIFS($B$86:$I$86,$B101:$I101,">0") -> 2008 | K101: =_xlfn.MAXIFS($B$86:$I$86,$B101:$I101,">0") -> 2015 | L101: =INDEX($B101:$I101,MATCH(J101,$B$86:$I$86,0)) -> 2356.6115 | M101: =INDEX($B101:$I101,MATCH(K101,$B$86:$I$86,0)) -> 8789.2412 | N101: =M101/L101-1 -> 2.7296098 | O101: =IF(K101>J101,(M101/L101)^(1/(K101-J101))-1,"") -> 0.20688586
A102: Fazenda Palmares | B102: =IFERROR(SUMIFS('Asset Value'!$F$4:$F$500,'Asset Value'!$C$4:$C$500,$A102,'Asset Value'!$B$4:$B$500,B$96)/SUMIFS('Asset Value'!$D$4:$D$500,'Asset Value'!$C$4:$C$500,$A102,'Asset Value'!$B$4:$B$500,B$96),0) -> 0 | C102: =IFERROR(SUMIFS('Asset Value'!$F$4:$F$500,'Asset Value'!$C$4:$C$500,$A102,'Asset Value'!$B$4:$B$500,C$96)/SUMIFS('Asset Value'!$D$4:$D$500,'Asset Value'!$C$4:$C$500,$A102,'Asset Value'!$B$4:$B$500,C$96),0) -> 4314.3939 | D102: =IFERROR(SUMIFS('Asset Value'!$F$4:$F$500,'Asset Value'!$C$4:$C$500,$A102,'Asset Value'!$B$4:$B$500,D$96)/SUMIFS('Asset Value'!$D$4:$D$500,'Asset Value'!$C$4:$C$500,$A102,'Asset Value'!$B$4:$B$500,D$96),0) -> 4078.901 | E102: =IFERROR(SUMIFS('Asset Value'!$F$4:$F$500,'Asset Value'!$C$4:$C$500,$A102,'Asset Value'!$B$4:$B$500,E$96)/SUMIFS('Asset Value'!$D$4:$D$500,'Asset Value'!$C$4:$C$500,$A102,'Asset Value'!$B$4:$B$500,E$96),0) -> 4955.747 | F102: =IFERROR(SUMIFS('Asset Value'!$F$4:$F$500,'Asset Value'!$C$4:$C$500,$A102,'Asset Value'!$B$4:$B$500,F$96)/SUMIFS('Asset Value'!$D$4:$D$500,'Asset Value'!$C$4:$C$500,$A102,'Asset Value'!$B$4:$B$500,F$96),0) -> 6033.7503 | G102: =IFERROR(SUMIFS('Asset Value'!$F$4:$F$500,'Asset Value'!$C$4:$C$500,$A102,'Asset Value'!$B$4:$B$500,G$96)/SUMIFS('Asset Value'!$D$4:$D$500,'Asset Value'!$C$4:$C$500,$A102,'Asset Value'!$B$4:$B$500,G$96),0) -> 10218.61 | H102: =IFERROR(SUMIFS('Asset Value'!$F$4:$F$500,'Asset Value'!$C$4:$C$500,$A102,'Asset Value'!$B$4:$B$500,H$96)/SUMIFS('Asset Value'!$D$4:$D$500,'Asset Value'!$C$4:$C$500,$A102,'Asset Value'!$B$4:$B$500,H$96),0) -> 11324.592 | I102: =IFERROR(SUMIFS('Asset Value'!$F$4:$F$500,'Asset Value'!$C$4:$C$500,$A102,'Asset Value'!$B$4:$B$500,I$96)/SUMIFS('Asset Value'!$D$4:$D$500,'Asset Value'!$C$4:$C$500,$A102,'Asset Value'!$B$4:$B$500,I$96),0) -> 11603.884 | J102: =_xlfn.MINIFS($B$86:$I$86,$B102:$I102,">0") -> 2009 | K102: =_xlfn.MAXIFS($B$86:$I$86,$B102:$I102,">0") -> 2015 | L102: =INDEX($B102:$I102,MATCH(J102,$B$86:$I$86,0)) -> 4314.3939 | M102: =INDEX($B102:$I102,MATCH(K102,$B$86:$I$86,0)) -> 11603.884 | N102: =M102/L102-1 -> 1.6895746 | O102: =IF(K102>J102,(M102/L102)^(1/(K102-J102))-1,"") -> 0.17927185
A103: Fazenda Parnaíba | B103: =IFERROR(SUMIFS('Asset Value'!$F$4:$F$500,'Asset Value'!$C$4:$C$500,$A103,'Asset Value'!$B$4:$B$500,B$96)/SUMIFS('Asset Value'!$D$4:$D$500,'Asset Value'!$C$4:$C$500,$A103,'Asset Value'!$B$4:$B$500,B$96),0) -> 6005.9807 | C103: =IFERROR(SUMIFS('Asset Value'!$F$4:$F$500,'Asset Value'!$C$4:$C$500,$A103,'Asset Value'!$B$4:$B$500,C$96)/SUMIFS('Asset Value'!$D$4:$D$500,'Asset Value'!$C$4:$C$500,$A103,'Asset Value'!$B$4:$B$500,C$96),0) -> 6134.9784 | D103: =IFERROR(SUMIFS('Asset Value'!$F$4:$F$500,'Asset Value'!$C$4:$C$500,$A103,'Asset Value'!$B$4:$B$500,D$96)/SUMIFS('Asset Value'!$D$4:$D$500,'Asset Value'!$C$4:$C$500,$A103,'Asset Value'!$B$4:$B$500,D$96),0) -> 5924.29 | E103: =IFERROR(SUMIFS('Asset Value'!$F$4:$F$500,'Asset Value'!$C$4:$C$500,$A103,'Asset Value'!$B$4:$B$500,E$96)/SUMIFS('Asset Value'!$D$4:$D$500,'Asset Value'!$C$4:$C$500,$A103,'Asset Value'!$B$4:$B$500,E$96),0) -> 6597.7945 | F103: =IFERROR(SUMIFS('Asset Value'!$F$4:$F$500,'Asset Value'!$C$4:$C$500,$A103,'Asset Value'!$B$4:$B$500,F$96)/SUMIFS('Asset Value'!$D$4:$D$500,'Asset Value'!$C$4:$C$500,$A103,'Asset Value'!$B$4:$B$500,F$96),0) -> 7770.795 | G103: =IFERROR(SUMIFS('Asset Value'!$F$4:$F$500,'Asset Value'!$C$4:$C$500,$A103,'Asset Value'!$B$4:$B$500,G$96)/SUMIFS('Asset Value'!$D$4:$D$500,'Asset Value'!$C$4:$C$500,$A103,'Asset Value'!$B$4:$B$500,G$96),0) -> 9304.7718 | H103: =IFERROR(SUMIFS('Asset Value'!$F$4:$F$500,'Asset Value'!$C$4:$C$500,$A103,'Asset Value'!$B$4:$B$500,H$96)/SUMIFS('Asset Value'!$D$4:$D$500,'Asset Value'!$C$4:$C$500,$A103,'Asset Value'!$B$4:$B$500,H$96),0) -> 8305.1699 | I103: =IFERROR(SUMIFS('Asset Value'!$F$4:$F$500,'Asset Value'!$C$4:$C$500,$A103,'Asset Value'!$B$4:$B$500,I$96)/SUMIFS('Asset Value'!$D$4:$D$500,'Asset Value'!$C$4:$C$500,$A103,'Asset Value'!$B$4:$B$500,I$96),0) -> 8728.3164 | J103: =_xlfn.MINIFS($B$86:$I$86,$B103:$I103,">0") -> 2008 | K103: =_xlfn.MAXIFS($B$86:$I$86,$B103:$I103,">0") -> 2015 | L103: =INDEX($B103:$I103,MATCH(J103,$B$86:$I$86,0)) -> 6005.9807 | M103: =INDEX($B103:$I103,MATCH(K103,$B$86:$I$86,0)) -> 8728.3164 | N103: =M103/L103-1 -> 0.4532708 | O103: =IF(K103>J103,(M103/L103)^(1/(K103-J103))-1,"") -> 0.054854024
A104: Fazenda Paiaguás | B104: =IFERROR(SUMIFS('Asset Value'!$F$4:$F$500,'Asset Value'!$C$4:$C$500,$A104,'Asset Value'!$B$4:$B$500,B$96)/SUMIFS('Asset Value'!$D$4:$D$500,'Asset Value'!$C$4:$C$500,$A104,'Asset Value'!$B$4:$B$500,B$96),0) -> 8334.5394 | C104: =IFERROR(SUMIFS('Asset Value'!$F$4:$F$500,'Asset Value'!$C$4:$C$500,$A104,'Asset Value'!$B$4:$B$500,C$96)/SUMIFS('Asset Value'!$D$4:$D$500,'Asset Value'!$C$4:$C$500,$A104,'Asset Value'!$B$4:$B$500,C$96),0) -> 10094.451 | D104: =IFERROR(SUMIFS('Asset Value'!$F$4:$F$500,'Asset Value'!$C$4:$C$500,$A104,'Asset Value'!$B$4:$B$500,D$96)/SUMIFS('Asset Value'!$D$4:$D$500,'Asset Value'!$C$4:$C$500,$A104,'Asset Value'!$B$4:$B$500,D$96),0) -> 9290.8558 | E104: =IFERROR(SUMIFS('Asset Value'!$F$4:$F$500,'Asset Value'!$C$4:$C$500,$A104,'Asset Value'!$B$4:$B$500,E$96)/SUMIFS('Asset Value'!$D$4:$D$500,'Asset Value'!$C$4:$C$500,$A104,'Asset Value'!$B$4:$B$500,E$96),0) -> 10647.446 | F104: =IFERROR(SUMIFS('Asset Value'!$F$4:$F$500,'Asset Value'!$C$4:$C$500,$A104,'Asset Value'!$B$4:$B$500,F$96)/SUMIFS('Asset Value'!$D$4:$D$500,'Asset Value'!$C$4:$C$500,$A104,'Asset Value'!$B$4:$B$500,F$96),0) -> 12701.285 | G104: =IFERROR(SUMIFS('Asset Value'!$F$4:$F$500,'Asset Value'!$C$4:$C$500,$A104,'Asset Value'!$B$4:$B$500,G$96)/SUMIFS('Asset Value'!$D$4:$D$500,'Asset Value'!$C$4:$C$500,$A104,'Asset Value'!$B$4:$B$500,G$96),0) -> 13052.059 | H104: =IFERROR(SUMIFS('Asset Value'!$F$4:$F$500,'Asset Value'!$C$4:$C$500,$A104,'Asset Value'!$B$4:$B$500,H$96)/SUMIFS('Asset Value'!$D$4:$D$500,'Asset Value'!$C$4:$C$500,$A104,'Asset Value'!$B$4:$B$500,H$96),0) -> 16016.872 | I104: =IFERROR(SUMIFS('Asset Value'!$F$4:$F$500,'Asset Value'!$C$4:$C$500,$A104,'Asset Value'!$B$4:$B$500,I$96)/SUMIFS('Asset Value'!$D$4:$D$500,'Asset Value'!$C$4:$C$500,$A104,'Asset Value'!$B$4:$B$500,I$96),0) -> 17172.944 | J104: =_xlfn.MINIFS($B$86:$I$86,$B104:$I104,">0") -> 2008 | K104: =_xlfn.MAXIFS($B$86:$I$86,$B104:$I104,">0") -> 2015 | L104: =INDEX($B104:$I104,MATCH(J104,$B$86:$I$86,0)) -> 8334.5394 | M104: =INDEX($B104:$I104,MATCH(K104,$B$86:$I$86,0)) -> 17172.944 | N104: =M104/L104-1 -> 1.0604551 | O104: =IF(K104>J104,(M104/L104)^(1/(K104-J104))-1,"") -> 0.10879659
A105: Fazenda Pejuçara | B105: =IFERROR(SUMIFS('Asset Value'!$F$4:$F$500,'Asset Value'!$C$4:$C$500,$A105,'Asset Value'!$B$4:$B$500,B$96)/SUMIFS('Asset Value'!$D$4:$D$500,'Asset Value'!$C$4:$C$500,$A105,'Asset Value'!$B$4:$B$500,B$96),0) -> 0 | C105: =IFERROR(SUMIFS('Asset Value'!$F$4:$F$500,'Asset Value'!$C$4:$C$500,$A105,'Asset Value'!$B$4:$B$500,C$96)/SUMIFS('Asset Value'!$D$4:$D$500,'Asset Value'!$C$4:$C$500,$A105,'Asset Value'!$B$4:$B$500,C$96),0) -> 0 | D105: =IFERROR(SUMIFS('Asset Value'!$F$4:$F$500,'Asset Value'!$C$4:$C$500,$A105,'Asset Value'!$B$4:$B$500,D$96)/SUMIFS('Asset Value'!$D$4:$D$500,'Asset Value'!$C$4:$C$500,$A105,'Asset Value'!$B$4:$B$500,D$96),0) -> 0 | E105: =IFERROR(SUMIFS('Asset Value'!$F$4:$F$500,'Asset Value'!$C$4:$C$500,$A105,'Asset Value'!$B$4:$B$500,E$96)/SUMIFS('Asset Value'!$D$4:$D$500,'Asset Value'!$C$4:$C$500,$A105,'Asset Value'!$B$4:$B$500,E$96),0) -> 0 | F105: =IFERROR(SUMIFS('Asset Value'!$F$4:$F$500,'Asset Value'!$C$4:$C$500,$A105,'Asset Value'!$B$4:$B$500,F$96)/SUMIFS('Asset Value'!$D$4:$D$500,'Asset Value'!$C$4:$C$500,$A105,'Asset Value'!$B$4:$B$500,F$96),0) -> 12311.335 | G105: =IFERROR(SUMIFS('Asset Value'!$F$4:$F$500,'Asset Value'!$C$4:$C$500,$A105,'Asset Value'!$B$4:$B$500,G$96)/SUMIFS('Asset Value'!$D$4:$D$500,'Asset Value'!$C$4:$C$500,$A105,'Asset Value'!$B$4:$B$500,G$96),0) -> 12615.271 | H105: =IFERROR(SUMIFS('Asset Value'!$F$4:$F$500,'Asset Value'!$C$4:$C$500,$A105,'Asset Value'!$B$4:$B$500,H$96)/SUMIFS('Asset Value'!$D$4:$D$500,'Asset Value'!$C$4:$C$500,$A105,'Asset Value'!$B$4:$B$500,H$96),0) -> 0 | I105: =IFERROR(SUMIFS('Asset Value'!$F$4:$F$500,'Asset Value'!$C$4:$C$500,$A105,'Asset Value'!$B$4:$B$500,I$96)/SUMIFS('Asset Value'!$D$4:$D$500,'Asset Value'!$C$4:$C$500,$A105,'Asset Value'!$B$4:$B$500,I$96),0) -> 0 | J105: =_xlfn.MINIFS($B$86:$I$86,$B105:$I105,">0") -> 2012 | K105: =_xlfn.MAXIFS($B$86:$I$86,$B105:$I105,">0") -> 2013 | L105: =INDEX($B105:$I105,MATCH(J105,$B$86:$I$86,0)) -> 12311.335 | M105: =INDEX($B105:$I105,MATCH(K105,$B$86:$I$86,0)) -> 12615.271 | N105: =M105/L105-1 -> 0.0246875 | O105: =IF(K105>J105,(M105/L105)^(1/(K105-J105))-1,"") -> 0.0246875
A106: Fazenda Parceiro | B106: =IFERROR(SUMIFS('Asset Value'!$F$4:$F$500,'Asset Value'!$C$4:$C$500,$A106,'Asset Value'!$B$4:$B$500,B$96)/SUMIFS('Asset Value'!$D$4:$D$500,'Asset Value'!$C$4:$C$500,$A106,'Asset Value'!$B$4:$B$500,B$96),0) -> 0 | C106: =IFERROR(SUMIFS('Asset Value'!$F$4:$F$500,'Asset Value'!$C$4:$C$500,$A106,'Asset Value'!$B$4:$B$500,C$96)/SUMIFS('Asset Value'!$D$4:$D$500,'Asset Value'!$C$4:$C$500,$A106,'Asset Value'!$B$4:$B$500,C$96),0) -> 0 | D106: =IFERROR(SUMIFS('Asset Value'!$F$4:$F$500,'Asset Value'!$C$4:$C$500,$A106,'Asset Value'!$B$4:$B$500,D$96)/SUMIFS('Asset Value'!$D$4:$D$500,'Asset Value'!$C$4:$C$500,$A106,'Asset Value'!$B$4:$B$500,D$96),0) -> 0 | E106: =IFERROR(SUMIFS('Asset Value'!$F$4:$F$500,'Asset Value'!$C$4:$C$500,$A106,'Asset Value'!$B$4:$B$500,E$96)/SUMIFS('Asset Value'!$D$4:$D$500,'Asset Value'!$C$4:$C$500,$A106,'Asset Value'!$B$4:$B$500,E$96),0) -> 0 | F106: =IFERROR(SUMIFS('Asset Value'!$F$4:$F$500,'Asset Value'!$C$4:$C$500,$A106,'Asset Value'!$B$4:$B$500,F$96)/SUMIFS('Asset Value'!$D$4:$D$500,'Asset Value'!$C$4:$C$500,$A106,'Asset Value'!$B$4:$B$500,F$96),0) -> 3485.0683 | G106: =IFERROR(SUMIFS('Asset Value'!$F$4:$F$500,'Asset Value'!$C$4:$C$500,$A106,'Asset Value'!$B$4:$B$500,G$96)/SUMIFS('Asset Value'!$D$4:$D$500,'Asset Value'!$C$4:$C$500,$A106,'Asset Value'!$B$4:$B$500,G$96),0) -> 5333.8093 | H106: =IFERROR(SUMIFS('Asset Value'!$F$4:$F$500,'Asset Value'!$C$4:$C$500,$A106,'Asset Value'!$B$4:$B$500,H$96)/SUMIFS('Asset Value'!$D$4:$D$500,'Asset Value'!$C$4:$C$500,$A106,'Asset Value'!$B$4:$B$500,H$96),0) -> 6182.391 | I106: =IFERROR(SUMIFS('Asset Value'!$F$4:$F$500,'Asset Value'!$C$4:$C$500,$A106,'Asset Value'!$B$4:$B$500,I$96)/SUMIFS('Asset Value'!$D$4:$D$500,'Asset Value'!$C$4:$C$500,$A106,'Asset Value'!$B$4:$B$500,I$96),0) -> 6409.2843 | J106: =_xlfn.MINIFS($B$86:$I$86,$B106:$I106,">0") -> 2012 | K106: =_xlfn.MAXIFS($B$86:$I$86,$B106:$I106,">0") -> 2015 | L106: =INDEX($B106:$I106,MATCH(J106,$B$86:$I$86,0)) -> 3485.0683 | M106: =INDEX($B106:$I106,MATCH(K106,$B$86:$I$86,0)) -> 6409.2843 | N106: =M106/L106-1 -> 0.83906995 | O106: =IF(K106>J106,(M106/L106)^(1/(K106-J106))-1,"") -> 0.22517864
A107: Fazenda Perdizes | B107: =IFERROR(SUMIFS('Asset Value'!$F$4:$F$500,'Asset Value'!$C$4:$C$500,$A107,'Asset Value'!$B$4:$B$500,B$96)/SUMIFS('Asset Value'!$D$4:$D$500,'Asset Value'!$C$4:$C$500,$A107,'Asset Value'!$B$4:$B$500,B$96),0) -> 0 | C107: =IFERROR(SUMIFS('Asset Value'!$F$4:$F$500,'Asset Value'!$C$4:$C$500,$A107,'Asset Value'!$B$4:$B$500,C$96)/SUMIFS('Asset Value'!$D$4:$D$500,'Asset Value'!$C$4:$C$500,$A107,'Asset Value'!$B$4:$B$500,C$96),0) -> 0 | D107: =IFERROR(SUMIFS('Asset Value'!$F$4:$F$500,'Asset Value'!$C$4:$C$500,$A107,'Asset Value'!$B$4:$B$500,D$96)/SUMIFS('Asset Value'!$D$4:$D$500,'Asset Value'!$C$4:$C$500,$A107,'Asset Value'!$B$4:$B$500,D$96),0) -> 0 | E107: =IFERROR(SUMIFS('Asset Value'!$F$4:$F$500,'Asset Value'!$C$4:$C$500,$A107,'Asset Value'!$B$4:$B$500,E$96)/SUMIFS('Asset Value'!$D$4:$D$500,'Asset Value'!$C$4:$C$500,$A107,'Asset Value'!$B$4:$B$500,E$96),0) -> 0 | F107: =IFERROR(SUMIFS('Asset Value'!$F$4:$F$500,'Asset Value'!$C$4:$C$500,$A107,'Asset Value'!$B$4:$B$500,F$96)/SUMIFS('Asset Value'!$D$4:$D$500,'Asset Value'!$C$4:$C$500,$A107,'Asset Value'!$B$4:$B$500,F$96),0) -> 2919.3397 | G107: =IFERROR(SUMIFS('Asset Value'!$F$4:$F$500,'Asset Value'!$C$4:$C$500,$A107,'Asset Value'!$B$4:$B$500,G$96)/SUMIFS('Asset Value'!$D$4:$D$500,'Asset Value'!$C$4:$C$500,$A107,'Asset Value'!$B$4:$B$500,G$96),0) -> 5747.1651 | H107: =IFERROR(SUMIFS('Asset Value'!$F$4:$F$500,'Asset Value'!$C$4:$C$500,$A107,'Asset Value'!$B$4:$B$500,H$96)/SUMIFS('Asset Value'!$D$4:$D$500,'Asset Value'!$C$4:$C$500,$A107,'Asset Value'!$B$4:$B$500,H$96),0) -> 5923.3808 | I107: =IFERROR(SUMIFS('Asset Value'!$F$4:$F$500,'Asset Value'!$C$4:$C$500,$A107,'Asset Value'!$B$4:$B$500,I$96)/SUMIFS('Asset Value'!$D$4:$D$500,'Asset Value'!$C$4:$C$500,$A107,'Asset Value'!$B$4:$B$500,I$96),0) -> 6069.6328 | J107: =_xlfn.MINIFS($B$86:$I$86,$B107:$I107,">0") -> 2012 | K107: =_xlfn.MAXIFS($B$86:$I$86,$B107:$I107,">0") -> 2015 | L107: =INDEX($B107:$I107,MATCH(J107,$B$86:$I$86,0)) -> 2919.3397 | M107: =INDEX($B107:$I107,MATCH(K107,$B$86:$I$86,0)) -> 6069.6328 | N107: =M107/L107-1 -> 1.0791115 | O107: =IF(K107>J107,(M107/L107)^(1/(K107-J107))-1,"") -> 0.27631907
A108: Fazenda Planorte | B108: =IFERROR(SUMIFS('Asset Value'!$F$4:$F$500,'Asset Value'!$C$4:$C$500,$A108,'Asset Value'!$B$4:$B$500,B$96)/SUMIFS('Asset Value'!$D$4:$D$500,'Asset Value'!$C$4:$C$500,$A108,'Asset Value'!$B$4:$B$500,B$96),0) -> 8243.7875 | C108: =IFERROR(SUMIFS('Asset Value'!$F$4:$F$500,'Asset Value'!$C$4:$C$500,$A108,'Asset Value'!$B$4:$B$500,C$96)/SUMIFS('Asset Value'!$D$4:$D$500,'Asset Value'!$C$4:$C$500,$A108,'Asset Value'!$B$4:$B$500,C$96),0) -> 9791.9644 | D108: =IFERROR(SUMIFS('Asset Value'!$F$4:$F$500,'Asset Value'!$C$4:$C$500,$A108,'Asset Value'!$B$4:$B$500,D$96)/SUMIFS('Asset Value'!$D$4:$D$500,'Asset Value'!$C$4:$C$500,$A108,'Asset Value'!$B$4:$B$500,D$96),0) -> 8407.9351 | E108: =IFERROR(SUMIFS('Asset Value'!$F$4:$F$500,'Asset Value'!$C$4:$C$500,$A108,'Asset Value'!$B$4:$B$500,E$96)/SUMIFS('Asset Value'!$D$4:$D$500,'Asset Value'!$C$4:$C$500,$A108,'Asset Value'!$B$4:$B$500,E$96),0) -> 9216.5763 | F108: =IFERROR(SUMIFS('Asset Value'!$F$4:$F$500,'Asset Value'!$C$4:$C$500,$A108,'Asset Value'!$B$4:$B$500,F$96)/SUMIFS('Asset Value'!$D$4:$D$500,'Asset Value'!$C$4:$C$500,$A108,'Asset Value'!$B$4:$B$500,F$96),0) -> 10718.278 | G108: =IFERROR(SUMIFS('Asset Value'!$F$4:$F$500,'Asset Value'!$C$4:$C$500,$A108,'Asset Value'!$B$4:$B$500,G$96)/SUMIFS('Asset Value'!$D$4:$D$500,'Asset Value'!$C$4:$C$500,$A108,'Asset Value'!$B$4:$B$500,G$96),0) -> 10794.147 | H108: =IFERROR(SUMIFS('Asset Value'!$F$4:$F$500,'Asset Value'!$C$4:$C$500,$A108,'Asset Value'!$B$4:$B$500,H$96)/SUMIFS('Asset Value'!$D$4:$D$500,'Asset Value'!$C$4:$C$500,$A108,'Asset Value'!$B$4:$B$500,H$96),0) -> 12960.099 | I108: =IFERROR(SUMIFS('Asset Value'!$F$4:$F$500,'Asset Value'!$C$4:$C$500,$A108,'Asset Value'!$B$4:$B$500,I$96)/SUMIFS('Asset Value'!$D$4:$D$500,'Asset Value'!$C$4:$C$500,$A108,'Asset Value'!$B$4:$B$500,I$96),0) -> 13476.258 | J108: =_xlfn.MINIFS($B$86:$I$86,$B108:$I108,">0") -> 2008 | K108: =_xlfn.MAXIFS($B$86:$I$86,$B108:$I108,">0") -> 2015 | L108: =INDEX($B108:$I108,MATCH(J108,$B$86:$I$86,0)) -> 8243.7875 | M108: =INDEX($B108:$I108,MATCH(K108,$B$86:$I$86,0)) -> 13476.258 | N108: =M108/L108-1 -> 0.63471675 | O108: =IF(K108>J108,(M108/L108)^(1/(K108-J108))-1,"") -> 0.072733362
... A111: Fazenda Palmeira | B111: =IFERROR(SUMIFS('Asset Value'!$F$4:$F$500,'Asset Value'!$C$4:$C$500,$A111,'Asset Value'!$B$4:$B$500,B$96)/SUMIFS('Asset Value'!$D$4:$D$500,'Asset Value'!$C$4:$C$500,$A111,'Asset Value'!$B$4:$B$500,B$96),0) -> 1371.3827 | C111: =IFERROR(SUMIFS('Asset Value'!$F$4:$F$500,'Asset Value'!$C$4:$C$500,$A111,'Asset Value'!$B$4:$B$500,C$96)/SUMIFS('Asset Value'!$D$4:$D$500,'Asset Value'!$C$4:$C$500,$A111,'Asset Value'!$B$4:$B$500,C$96),0) -> 1688.1641 | D111: =IFERROR(SUMIFS('Asset Value'!$F$4:$F$500,'Asset Value'!$C$4:$C$500,$A111,'Asset Value'!$B$4:$B$500,D$96)/SUMIFS('Asset Value'!$D$4:$D$500,'Asset Value'!$C$4:$C$500,$A111,'Asset Value'!$B$4:$B$500,D$96),0) -> 1699.1453 | E111: =IFERROR(SUMIFS('Asset Value'!$F$4:$F$500,'Asset Value'!$C$4:$C$500,$A111,'Asset Value'!$B$4:$B$500,E$96)/SUMIFS('Asset Value'!$D$4:$D$500,'Asset Value'!$C$4:$C$500,$A111,'Asset Value'!$B$4:$B$500,E$96),0) -> 0 | F111: =IFERROR(SUMIFS('Asset Value'!$F$4:$F$500,'Asset Value'!$C$4:$C$500,$A111,'Asset Value'!$B$4:$B$500,F$96)/SUMIFS('Asset Value'!$D$4:$D$500,'Asset Value'!$C$4:$C$500,$A111,'Asset Value'!$B$4:$B$500,F$96),0) -> 0 | G111: =IFERROR(SUMIFS('Asset Value'!$F$4:$F$500,'Asset Value'!$C$4:$C$500,$A111,'Asset Value'!$B$4:$B$500,G$96)/SUMIFS('Asset Value'!$D$4:$D$500,'Asset Value'!$C$4:$C$500,$A111,'Asset Value'!$B$4:$B$500,G$96),0) -> 0 | H111: =IFERROR(SUMIFS('Asset Value'!$F$4:$F$500,'Asset Value'!$C$4:$C$500,$A111,'Asset Value'!$B$4:$B$500,H$96)/SUMIFS('Asset Value'!$D$4:$D$500,'Asset Value'!$C$4:$C$500,$A111,'Asset Value'!$B$4:$B$500,H$96),0) -> 0 | I111: =IFERROR(SUMIFS('Asset Value'!$F$4:$F$500,'Asset Value'!$C$4:$C$500,$A111,'Asset Value'!$B$4:$B$500,I$96)/SUMIFS('Asset Value'!$D$4:$D$500,'Asset Value'!$C$4:$C$500,$A111,'Asset Value'!$B$4:$B$500,I$96),0) -> 0 | J111: =_xlfn.MINIFS($B$86:$I$86,$B111:$I111,">0") -> 2008 | K111: =_xlfn.MAXIFS($B$86:$I$86,$B111:$I111,">0") -> 2010 | L111: =INDEX($B111:$I111,MATCH(J111,$B$86:$I$86,0)) -> 1371.3827 | M111: =INDEX($B111:$I111,MATCH(K111,$B$86:$I$86,0)) -> 1699.1453 | N111: =M111/L111-1 -> 0.23900152 | O111: =IF(K111>J111,(M111/L111)^(1/(K111-J111))-1,"") -> 0.11310445
A112: Obs.: o preço médio do portfólio muda também com a composição (entrada/saída de fazendas); use o gráfico por fazenda para comparar like-for-like.
A113: Obs.: CAGR de fazendas com poucos anos (Pejuçara 2012-13, Palmeira 2008-10) é só indicativo.

Sheet Register
B3: FNP | C3: Farm Name | D3: State | E3: County | F3: (R$ 000) | G3: 2008 | H3: 2009 | I3: 2010 | J3: 2011 | K3: =J3+1 -> 2012 | L3: =K3+1 -> 2013 | M3: =L3+1 -> 2014 | N3: =M3+1 -> 2015
B4: 73 | C4: Fazenda Pamplona | D4: Goias | E4: Cristalina | F4: Asset Value | G4: =SUMIFS('Asset Value'!$F$4:$F$102,'Asset Value'!$B$4:$B$102,Register!G$3,'Asset Value'!$C$4:$C$102,Register!$C4)/1000 -> 143610 | H4: =SUMIFS('Asset Value'!$F$4:$F$102,'Asset Value'!$B$4:$B$102,Register!H$3,'Asset Value'!$C$4:$C$102,Register!$C4)/1000 -> 158220 | I4: =SUMIFS('Asset Value'!$F$4:$F$102,'Asset Value'!$B$4:$B$102,Register!I$3,'Asset Value'!$C$4:$C$102,Register!$C4)/1000 -> 164240 | J4: =SUMIFS('Asset Value'!$F$4:$F$102,'Asset Value'!$B$4:$B$102,Register!J$3,'Asset Value'!$C$4:$C$102,Register!$C4)/1000 -> 179570 | K4: =SUMIFS('Asset Value'!$F$4:$F$102,'Asset Value'!$B$4:$B$102,Register!K$3,'Asset Value'!$C$4:$C$102,Register!$C4)/1000 -> 215630 | L4: =SUMIFS('Asset Value'!$F$4:$F$102,'Asset Value'!$B$4:$B$102,Register!L$3,'Asset Value'!$C$4:$C$102,Register!$C4)/1000 -> 224342 | M4: =SUMIFS('Asset Value'!$F$4:$F$102,'Asset Value'!$B$4:$B$102,Register!M$3,'Asset Value'!$C$4:$C$102,Register!$C4)/1000 -> 269921 | N4: =SUMIFS('Asset Value'!$F$4:$F$102,'Asset Value'!$B$4:$B$102,Register!N$3,'Asset Value'!$C$4:$C$102,Register!$C4)/1000 -> 290900
F5: %YoY | H5: =H4/G4-1 -> 0.10173386 | I5: =I4/H4-1 -> 0.038048287 | J5: =J4/I4-1 -> 0.093339016 | K5: =K4/J4-1 -> 0.20081305 | L5: =L4/K4-1 -> 0.040402541 | M5: =M4/L4-1 -> 0.20316749 | N5: =N4/M4-1 -> 0.077722741
F6: Rent | G6: =SUMIFS(Rent!$E$3:$E$110,Rent!$C$3:$C$110,Register!G$3,Rent!$D$3:$D$110,Register!$C4)/1000 -> 5764.1165 | H6: =SUMIFS(Rent!$E$3:$E$110,Rent!$C$3:$C$110,Register!H$3,Rent!$D$3:$D$110,Register!$C4)/1000 -> 5432.8454 | I6: =SUMIFS(Rent!$E$3:$E$110,Rent!$C$3:$C$110,Register!I$3,Rent!$D$3:$D$110,Register!$C4)/1000 -> 5962.8791 | J6: =SUMIFS(Rent!$E$3:$E$110,Rent!$C$3:$C$110,Register!J$3,Rent!$D$3:$D$110,Register!$C4)/1000 -> 4000.309 | K6: =SUMIFS(Rent!$E$3:$E$110,Rent!$C$3:$C$110,Register!K$3,Rent!$D$3:$D$110,Register!$C4)/1000 -> 6522 | L6: =SUMIFS(Rent!$E$3:$E$110,Rent!$C$3:$C$110,Register!L$3,Rent!$D$3:$D$110,Register!$C4)/1000 -> 5902 | M6: =SUMIFS(Rent!$E$3:$E$110,Rent!$C$3:$C$110,Register!M$3,Rent!$D$3:$D$110,Register!$C4)/1000 -> 6567 | N6: =SUMIFS(Rent!$E$3:$E$110,Rent!$C$3:$C$110,Register!N$3,Rent!$D$3:$D$110,Register!$C4)/1000 -> 8312
F7: %YoY | H7: =H6/G6-1 -> -0.057471264 | I7: =I6/H6-1 -> 0.097560976 | J7: =J6/I6-1 -> -0.32913129 | K7: =K6/J6-1 -> 0.63037404 | L7: =L6/K6-1 -> -0.095062864 | M7: =M6/L6-1 -> 0.11267367 | N7: =N6/M6-1 -> 0.26572255
F8: %Yield | G8: =G6/G4 -> 0.040137292 | H8: =H6/H4 -> 0.034337286 | I8: =I6/I4 -> 0.036305888 | J8: =J6/J4 -> 0.022277157 | K8: =K6/K4 -> 0.030246255 | L8: =L6/L4 -> 0.026308048 | M8: =M6/M4 -> 0.024329341 | N8: =N6/N4 -> 0.028573393
B9: 41 | C9: Fazenda Planalto | D9: Mato Grosso Sul | E9: Costa Rica | F9: Asset Value | G9: =SUMIFS('Asset Value'!$F$4:$F$102,'Asset Value'!$B$4:$B$102,Register!G$3,'Asset Value'!$C$4:$C$102,Register!$C9)/1000 -> 207710 | H9: =SUMIFS('Asset Value'!$F$4:$F$102,'Asset Value'!$B$4:$B$102,Register!H$3,'Asset Value'!$C$4:$C$102,Register!$C9)/1000 -> 234810 | I9: =SUMIFS('Asset Value'!$F$4:$F$102,'Asset Value'!$B$4:$B$102,Register!I$3,'Asset Value'!$C$4:$C$102,Register!$C9)/1000 -> 241810 | J9: =SUMIFS('Asset Value'!$F$4:$F$102,'Asset Value'!$B$4:$B$102,Register!J$3,'Asset Value'!$C$4:$C$102,Register!$C9)/1000 -> 273920 | K9: =SUMIFS('Asset Value'!$F$4:$F$102,'Asset Value'!$B$4:$B$102,Register!K$3,'Asset Value'!$C$4:$C$102,Register!$C9)/1000 -> 322340 | L9: =SUMIFS('Asset Value'!$F$4:$F$102,'Asset Value'!$B$4:$B$102,Register!L$3,'Asset Value'!$C$4:$C$102,Register!$C9)/1000 -> 331712 | M9: =SUMIFS('Asset Value'!$F$4:$F$102,'Asset Value'!$B$4:$B$102,Register!M$3,'Asset Value'!$C$4:$C$102,Register!$C9)/1000 -> 453258 | N9: =SUMIFS('Asset Value'!$F$4:$F$102,'Asset Value'!$B$4:$B$102,Register!N$3,'Asset Value'!$C$4:$C$102,Register!$C9)/1000 -> 473550
F10: %YoY | H10: =H9/G9-1 -> 0.13047037 | I10: =I9/H9-1 -> 0.029811337 | J10: =J9/I9-1 -> 0.13279021 | K10: =K9/J9-1 -> 0.17676694 | L10: =L9/K9-1 -> 0.02907489 | M10: =M9/L9-1 -> 0.36642027 | N10: =N9/M9-1 -> 0.044769204
F11: Rent | G11: =SUMIFS(Rent!$E$3:$E$110,Rent!$C$3:$C$110,Register!G$3,Rent!$D$3:$D$110,Register!$C9)/1000 -> 6078.8944 | H11: =SUMIFS(Rent!$E$3:$E$110,Rent!$C$3:$C$110,Register!H$3,Rent!$D$3:$D$110,Register!$C9)/1000 -> 5934.1588 | I11: =SUMIFS(Rent!$E$3:$E$110,Rent!$C$3:$C$110,Register!I$3,Rent!$D$3:$D$110,Register!$C9)/1000 -> 6802.5723 | J11: =SUMIFS(Rent!$E$3:$E$110,Rent!$C$3:$C$110,Register!J$3,Rent!$D$3:$D$110,Register!$C9)/1000 -> 4563.6752 | K11: =SUMIFS(Rent!$E$3:$E$110,Rent!$C$3:$C$110,Register!K$3,Rent!$D$3:$D$110,Register!$C9)/1000 -> 7795 | L11: =SUMIFS(Rent!$E$3:$E$110,Rent!$C$3:$C$110,Register!L$3,Rent!$D$3:$D$110,Register!$C9)/1000 -> 7483 | M11: =SUMIFS(Rent!$E$3:$E$110,Rent!$C$3:$C$110,Register!M$3,Rent!$D$3:$D$110,Register!$C9)/1000 -> 10660 | N11: =SUMIFS(Rent!$E$3:$E$110,Rent!$C$3:$C$110,Register!N$3,Rent!$D$3:$D$110,Register!$C9)/1000 -> 13057
F12: %YoY | H12: =H11/G11-1 -> -0.023809524 | I12: =I11/H11-1 -> 0.14634146 | J12: =J11/I11-1 -> -0.32912507 | K12: =K11/J11-1 -> 0.70805319 | L12: =L11/K11-1 -> -0.040025657 | M12: =M11/L11-1 -> 0.42456234 | N12: =N11/M11-1 -> 0.22485929
F13: %Yield | G13: =G11/G9 -> 0.029266258 | H13: =H11/H9 -> 0.025272172 | I13: =I11/I9 -> 0.02813189 | J13: =J11/J9 -> 0.016660613 | K13: =K11/K9 -> 0.02418254 | L13: =L11/L9 -> 0.022558726 | M13: =M11/M9 -> 0.023518614 | N13: =N11/N9 -> 0.02757259
B14: 114 | C14: Fazenda Planeste | D14: Maranhao | E14: Balsas | F14: Asset Value | G14: =SUMIFS('Asset Value'!$F$4:$F$102,'Asset Value'!$B$4:$B$102,Register!G$3,'Asset Value'!$C$4:$C$102,Register!$C14)/1000 -> 106940 | H14: =SUMIFS('Asset Value'!$F$4:$F$102,'Asset Value'!$B$4:$B$102,Register!H$3,'Asset Value'!$C$4:$C$102,Register!$C14)/1000 -> 118040 | I14: =SUMIFS('Asset Value'!$F$4:$F$102,'Asset Value'!$B$4:$B$102,Register!I$3,'Asset Value'!$C$4:$C$102,Register!$C14)/1000 -> 142170 | J14: =SUMIFS('Asset Value'!$F$4:$F$102,'Asset Value'!$B$4:$B$102,Register!J$3,'Asset Value'!$C$4:$C$102,Register!$C14)/1000 -> 172970 | K14: =SUMIFS('Asset Value'!$F$4:$F$102,'Asset Value'!$B$4:$B$102,Register!K$3,'Asset Value'!$C$4:$C$102,Register!$C14)/1000 -> 197471 | L14: =SUMIFS('Asset Value'!$F$4:$F$102,'Asset Value'!$B$4:$B$102,Register!L$3,'Asset Value'!$C$4:$C$102,Register!$C14)/1000 -> 220203 | M14: =SUMIFS('Asset Value'!$F$4:$F$102,'Asset Value'!$B$4:$B$102,Register!M$3,'Asset Value'!$C$4:$C$102,Register!$C14)/1000 -> 229674 | N14: =SUMIFS('Asset Value'!$F$4:$F$102,'Asset Value'!$B$4:$B$102,Register!N$3,'Asset Value'!$C$4:$C$102,Register!$C14)/1000 -> 234550
F15: %YoY | H15: =H14/G14-1 -> 0.10379652 | I15: =I14/H14-1 -> 0.20442223 | J15: =J14/I14-1 -> 0.21664205 | K15: =K14/J14-1 -> 0.14164884 | L15: =L14/K14-1 -> 0.11511564 | M15: =M14/L14-1 -> 0.043010313 | N15: =N14/M14-1 -> 0.021230091
F16: Rent | G16: =SUMIFS(Rent!$E$3:$E$110,Rent!$C$3:$C$110,Register!G$3,Rent!$D$3:$D$110,Register!$C14)/1000 -> 3727.4927 | H16: =SUMIFS(Rent!$E$3:$E$110,Rent!$C$3:$C$110,Register!H$3,Rent!$D$3:$D$110,Register!$C14)/1000 -> 3502.9449 | I16: =SUMIFS(Rent!$E$3:$E$110,Rent!$C$3:$C$110,Register!I$3,Rent!$D$3:$D$110,Register!$C14)/1000 -> 3907.1309 | J16: =SUMIFS(Rent!$E$3:$E$110,Rent!$C$3:$C$110,Register!J$3,Rent!$D$3:$D$110,Register!$C14)/1000 -> 4417.4492 | K16: =SUMIFS(Rent!$E$3:$E$110,Rent!$C$3:$C$110,Register!K$3,Rent!$D$3:$D$110,Register!$C14)/1000 -> 9821 | L16: =SUMIFS(Rent!$E$3:$E$110,Rent!$C$3:$C$110,Register!L$3,Rent!$D$3:$D$110,Register!$C14)/1000 -> 7371 | M16: =SUMIFS(Rent!$E$3:$E$110,Rent!$C$3:$C$110,Register!M$3,Rent!$D$3:$D$110,Register!$C14)/1000 -> 8241 | N16: =SUMIFS(Rent!$E$3:$E$110,Rent!$C$3:$C$110,Register!N$3,Rent!$D$3:$D$110,Register!$C14)/1000 -> 8398
F17: %YoY | H17: =H16/G16-1 -> -0.060240964 | I17: =I16/H16-1 -> 0.11538462 | J17: =J16/I16-1 -> 0.13061206 | K17: =K16/J16-1 -> 1.2232287 | L17: =L16/K16-1 -> -0.24946543 | M17: =M16/L16-1 -> 0.11803012 | N17: =N16/M16-1 -> 0.019051086
F18: %Yield | G18: =G16/G14 -> 0.034855925 | H18: =H16/H14 -> 0.029675914 | I18: =I16/I14 -> 0.027482105 | J18: =J16/J14 -> 0.025538817 | K18: =K16/K14 -> 0.049733885 | L18: =L16/L14 -> 0.033473658 | M18: =M16/M14 -> 0.035881293 | N18: =N16/N14 -> 0.035804732
B19: 82 | C19: Fazenda Panorama | D19: Bahia | E19: Correntina | F19: Asset Value | G19: =SUMIFS('Asset Value'!$F$4:$F$102,'Asset Value'!$B$4:$B$102,Register!G$3,'Asset Value'!$C$4:$C$102,Register!$C19)/1000 -> 75090 | H19: =SUMIFS('Asset Value'!$F$4:$F$102,'Asset Value'!$B$4:$B$102,Register!H$3,'Asset Value'!$C$4:$C$102,Register!$C19)/1000 -> 86360 | I19: =SUMIFS('Asset Value'!$F$4:$F$102,'Asset Value'!$B$4:$B$102,Register!I$3,'Asset Value'!$C$4:$C$102,Register!$C19)/1000 -> 102810 | J19: =SUMIFS('Asset Value'!$F$4:$F$102,'Asset Value'!$B$4:$B$102,Register!J$3,'Asset Value'!$C$4:$C$102,Register!$C19)/1000 -> 146710 | K19: =SUMIFS('Asset Value'!$F$4:$F$102,'Asset Value'!$B$4:$B$102,Register!K$3,'Asset Value'!$C$4:$C$102,Register!$C19)/1000 -> 167470 | L19: =SUMIFS('Asset Value'!$F$4:$F$102,'Asset Value'!$B$4:$B$102,Register!L$3,'Asset Value'!$C$4:$C$102,Register!$C19)/1000 -> 145456 | M19: =SUMIFS('Asset Value'!$F$4:$F$102,'Asset Value'!$B$4:$B$102,Register!M$3,'Asset Value'!$C$4:$C$102,Register!$C19)/1000 -> 156350 | N19: =SUMIFS('Asset Value'!$F$4:$F$102,'Asset Value'!$B$4:$B$102,Register!N$3,'Asset Value'!$C$4:$C$102,Register!$C19)/1000 -> 166430
F20: %YoY | H20: =H19/G19-1 -> 0.15008656 | I20: =I19/H19-1 -> 0.1904817 | J20: =J19/I19-1 -> 0.42700126 | K20: =K19/J19-1 -> 0.14150365 | L20: =L19/K19-1 -> -0.13145041 | M20: =M19/L19-1 -> 0.074895501 | N20: =N19/M19-1 -> 0.064470739
F21: Rent | G21: =SUMIFS(Rent!$E$3:$E$110,Rent!$C$3:$C$110,Register!G$3,Rent!$D$3:$D$110,Register!$C19)/1000 -> 2181.24 | H21: =SUMIFS(Rent!$E$3:$E$110,Rent!$C$3:$C$110,Register!H$3,Rent!$D$3:$D$110,Register!$C19)/1000 -> 2049.84 | I21: =SUMIFS(Rent!$E$3:$E$110,Rent!$C$3:$C$110,Register!I$3,Rent!$D$3:$D$110,Register!$C19)/1000 -> 2897.28 | J21: =SUMIFS(Rent!$E$3:$E$110,Rent!$C$3:$C$110,Register!J$3,Rent!$D$3:$D$110,Register!$C19)/1000 -> 3924.8869 | K21: =SUMIFS(Rent!$E$3:$E$110,Rent!$C$3:$C$110,Register!K$3,Rent!$D$3:$D$110,Register!$C19)/1000 -> 7989 | L21: =SUMIFS(Rent!$E$3:$E$110,Rent!$C$3:$C$110,Register!L$3,Rent!$D$3:$D$110,Register!$C19)/1000 -> 5372 | M21: =SUMIFS(Rent!$E$3:$E$110,Rent!$C$3:$C$110,Register!M$3,Rent!$D$3:$D$110,Register!$C19)/1000 -> 5792 | N21: =SUMIFS(Rent!$E$3:$E$110,Rent!$C$3:$C$110,Register!N$3,Rent!$D$3:$D$110,Register!$C19)/1000 -> 6119
F22: %YoY | H22: =H21/G21-1 -> -0.060240964 | I22: =I21/H21-1 -> 0.41341763 | J22: =J21/I21-1 -> 0.35467986 | K22: =K21/J21-1 -> 1.0354727 | L22: =L21/K21-1 -> -0.32757542 | M22: =M21/L21-1 -> 0.078183172 | N22: =N21/M21-1 -> 0.056457182
F23: %Yield | G23: =G21/G19 -> 0.029048342 | H23: =H21/H19 -> 0.023735989 | I23: =I21/I19 -> 0.028180916 | J23: =J21/J19 -> 0.026752688 | K23: =K21/K19 -> 0.047704066 | L23: =L21/L19 -> 0.036932131 | M23: =M21/M19 -> 0.037045091 | N23: =N21/N19 -> 0.036766208
B24: 82 | C24: Fazenda Piratini | D24: Bahia | E24: Jaborandi | F24: Asset Value | G24: =SUMIFS('Asset Value'!$F$4:$F$102,'Asset Value'!$B$4:$B$102,Register!G$3,'Asset Value'!$C$4:$C$102,Register!$C24)/1000 -> 58920 | H24: =SUMIFS('Asset Value'!$F$4:$F$102,'Asset Value'!$B$4:$B$102,Register!H$3,'Asset Value'!$C$4:$C$102,Register!$C24)/1000 -> 94840 | I24: =SUMIFS('Asset Value'!$F$4:$F$102,'Asset Value'!$B$4:$B$102,Register!I$3,'Asset Value'!$C$4:$C$102,Register!$C24)/1000 -> 81810 | J24: =SUMIFS('Asset Value'!$F$4:$F$102,'Asset Value'!$B$4:$B$102,Register!J$3,'Asset Value'!$C$4:$C$102,Register!$C24)/1000 -> 117020 | K24: =SUMIFS('Asset Value'!$F$4:$F$102,'Asset Value'!$B$4:$B$102,Register!K$3,'Asset Value'!$C$4:$C$102,Register!$C24)/1000 -> 133583 | L24: =SUMIFS('Asset Value'!$F$4:$F$102,'Asset Value'!$B$4:$B$102,Register!L$3,'Asset Value'!$C$4:$C$102,Register!$C24)/1000 -> 176404 | M24: =SUMIFS('Asset Value'!$F$4:$F$102,'Asset Value'!$B$4:$B$102,Register!M$3,'Asset Value'!$C$4:$C$102,Register!$C24)/1000 -> 198210 | N24: =SUMIFS('Asset Value'!$F$4:$F$102,'Asset Value'!$B$4:$B$102,Register!N$3,'Asset Value'!$C$4:$C$102,Register!$C24)/1000 -> 222860
F25: %YoY | H25: =H24/G24-1 -> 0.60964019 | I25: =I24/H24-1 -> -0.13738929 | J25: =J24/I24-1 -> 0.43038748 | K25: =K24/J24-1 -> 0.14153991 | L25: =L24/K24-1 -> 0.32055726 | M25: =M24/L24-1 -> 0.12361398 | N25: =N24/M24-1 -> 0.12436305
F26: Rent | G26: =SUMIFS(Rent!$E$3:$E$110,Rent!$C$3:$C$110,Register!G$3,Rent!$D$3:$D$110,Register!$C24)/1000 -> 0 | H26: =SUMIFS(Rent!$E$3:$E$110,Rent!$C$3:$C$110,Register!H$3,Rent!$D$3:$D$110,Register!$C24)/1000 -> 0 | I26: =SUMIFS(Rent!$E$3:$E$110,Rent!$C$3:$C$110,Register!I$3,Rent!$D$3:$D$110,Register!$C24)/1000 -> 455 | J26: =SUMIFS(Rent!$E$3:$E$110,Rent!$C$3:$C$110,Register!J$3,Rent!$D$3:$D$110,Register!$C24)/1000 -> 2193.4205 | K26: =SUMIFS(Rent!$E$3:$E$110,Rent!$C$3:$C$110,Register!K$3,Rent!$D$3:$D$110,Register!$C24)/1000 -> 3466 | L26: =SUMIFS(Rent!$E$3:$E$110,Rent!$C$3:$C$110,Register!L$3,Rent!$D$3:$D$110,Register!$C24)/1000 -> 2818 | M26: =SUMIFS(Rent!$E$3:$E$110,Rent!$C$3:$C$110,Register!M$3,Rent!$D$3:$D$110,Register!$C24)/1000 -> 3235 | N26: =SUMIFS(Rent!$E$3:$E$110,Rent!$C$3:$C$110,Register!N$3,Rent!$D$3:$D$110,Register!$C24)/1000 -> 3602
F27: %YoY | H27: =H26/G26-1 -> #DIV/0! | I27: =I26/H26-1 -> #DIV/0! | J27: =J26/I26-1 -> 3.8207044 | K27: =K26/J26-1 -> 0.58018038 | L27: =L26/K26-1 -> -0.18695903 | M27: =M26/L26-1 -> 0.14797729 | N27: =N26/M26-1 -> 0.11344668
F28: %Yield | G28: =G26/G24 -> 0 | H28: =H26/H24 -> 0 | I28: =I26/I24 -> 0.0055616673 | J28: =J26/J24 -> 0.018743979 | K28: =K26/K24 -> 0.025946415 | L28: =L26/L24 -> 0.015974694 | M28: =M26/M24 -> 0.016321074 | N28: =N26/N24 -> 0.016162613
B29: 82 | C29: Fazenda Palmares | D29: Bahia | E29: Barreiras | F29: Asset Value | G29: =SUMIFS('Asset Value'!$F$4:$F$102,'Asset Value'!$B$4:$B$102,Register!G$3,'Asset Value'!$C$4:$C$102,Register!$C29)/1000 -> 0 | H29: =SUMIFS('Asset Value'!$F$4:$F$102,'Asset Value'!$B$4:$B$102,Register!H$3,'Asset Value'!$C$4:$C$102,Register!$C29)/1000 -> 22780 | I29: =SUMIFS('Asset Value'!$F$4:$F$102,'Asset Value'!$B$4:$B$102,Register!I$3,'Asset Value'!$C$4:$C$102,Register!$C29)/1000 -> 46320 | J29: =SUMIFS('Asset Value'!$F$4:$F$102,'Asset Value'!$B$4:$B$102,Register!J$3,'Asset Value'!$C$4:$C$102,Register!$C29)/1000 -> 83990 | K29: =SUMIFS('Asset Value'!$F$4:$F$102,'Asset Value'!$B$4:$B$102,Register!K$3,'Asset Value'!$C$4:$C$102,Register!$C29)/1000 -> 102260 | L29: =SUMIFS('Asset Value'!$F$4:$F$102,'Asset Value'!$B$4:$B$102,Register!L$3,'Asset Value'!$C$4:$C$102,Register!$C29)/1000 -> 173185 | M29: =SUMIFS('Asset Value'!$F$4:$F$102,'Asset Value'!$B$4:$B$102,Register!M$3,'Asset Value'!$C$4:$C$102,Register!$C29)/1000 -> 183096 | N29: =SUMIFS('Asset Value'!$F$4:$F$102,'Asset Value'!$B$4:$B$102,Register!N$3,'Asset Value'!$C$4:$C$102,Register!$C29)/1000 -> 187600
F30: %YoY | H30: =H29/G29-1 -> #DIV/0! | I30: =I29/H29-1 -> 1.0333626 | J30: =J29/I29-1 -> 0.81325561 | K30: =K29/J29-1 -> 0.2175259 | L30: =L29/K29-1 -> 0.6935752 | M30: =M29/L29-1 -> 0.05722782 | N30: =N29/M29-1 -> 0.024599117
F31: Rent | G31: =SUMIFS(Rent!$E$3:$E$110,Rent!$C$3:$C$110,Register!G$3,Rent!$D$3:$D$110,Register!$C29)/1000 -> 565.677 | H31: =SUMIFS(Rent!$E$3:$E$110,Rent!$C$3:$C$110,Register!H$3,Rent!$D$3:$D$110,Register!$C29)/1000 -> 1155.0427 | I31: =SUMIFS(Rent!$E$3:$E$110,Rent!$C$3:$C$110,Register!I$3,Rent!$D$3:$D$110,Register!$C29)/1000 -> 2568.87 | J31: =SUMIFS(Rent!$E$3:$E$110,Rent!$C$3:$C$110,Register!J$3,Rent!$D$3:$D$110,Register!$C29)/1000 -> 4695.2925 | K31: =SUMIFS(Rent!$E$3:$E$110,Rent!$C$3:$C$110,Register!K$3,Rent!$D$3:$D$110,Register!$C29)/1000 -> 7902 | L31: =SUMIFS(Rent!$E$3:$E$110,Rent!$C$3:$C$110,Register!L$3,Rent!$D$3:$D$110,Register!$C29)/1000 -> 7315 | M31: =SUMIFS(Rent!$E$3:$E$110,Rent!$C$3:$C$110,Register!M$3,Rent!$D$3:$D$110,Register!$C29)/1000 -> 7608 | N31: =SUMIFS(Rent!$E$3:$E$110,Rent!$C$3:$C$110,Register!N$3,Rent!$D$3:$D$110,Register!$C29)/1000 -> 10130
F32: %YoY | H32: =H31/G31-1 -> 1.0418768 | I32: =I31/H31-1 -> 1.2240476 | J32: =J31/I31-1 -> 0.8277657 | K32: =K31/J31-1 -> 0.68296225 | L32: =L31/K31-1 -> -0.074284991 | M32: =M31/L31-1 -> 0.040054682 | N32: =N31/M31-1 -> 0.33149317
F33: %Yield | G33: =G31/G29 -> #DIV/0! | H33: =H31/H29 -> 0.050704246 | I33: =I31/I29 -> 0.055459197 | J33: =J31/J29 -> 0.055902994 | K33: =K31/K29 -> 0.077273616 | L33: =L31/L29 -> 0.042238069 | M33: =M31/M29 -> 0.041551973 | N33: =N31/N29 -> 0.053997868
B34: 114 | C34: Fazenda Parnaíba | D34: Maranhao | E34: Tasso Fragoso | F34: Asset Value | G34: =SUMIFS('Asset Value'!$F$4:$F$102,'Asset Value'!$B$4:$B$102,Register!G$3,'Asset Value'!$C$4:$C$102,Register!$C34)/1000 -> 156660 | H34: =SUMIFS('Asset Value'!$F$4:$F$102,'Asset Value'!$B$4:$B$102,Register!H$3,'Asset Value'!$C$4:$C$102,Register!$C34)/1000 -> 207350 | I34: =SUMIFS('Asset Value'!$F$4:$F$102,'Asset Value'!$B$4:$B$102,Register!I$3,'Asset Value'!$C$4:$C$102,Register!$C34)/1000 -> 199850 | J34: =SUMIFS('Asset Value'!$F$4:$F$102,'Asset Value'!$B$4:$B$102,Register!J$3,'Asset Value'!$C$4:$C$102,Register!$C34)/1000 -> 222570 | K34: =SUMIFS('Asset Value'!$F$4:$F$102,'Asset Value'!$B$4:$B$102,Register!K$3,'Asset Value'!$C$4:$C$102,Register!$C34)/1000 -> 262140 | L34: =SUMIFS('Asset Value'!$F$4:$F$102,'Asset Value'!$B$4:$B$102,Register!L$3,'Asset Value'!$C$4:$C$102,Register!$C34)/1000 -> 305364 | M34: =SUMIFS('Asset Value'!$F$4:$F$102,'Asset Value'!$B$4:$B$102,Register!M$3,'Asset Value'!$C$4:$C$102,Register!$C34)/1000 -> 346990 | N34: =SUMIFS('Asset Value'!$F$4:$F$102,'Asset Value'!$B$4:$B$102,Register!N$3,'Asset Value'!$C$4:$C$102,Register!$C34)/1000 -> 412090
F35: %YoY | H35: =H34/G34-1 -> 0.32356696 | I35: =I34/H34-1 -> -0.036170726 | J35: =J34/I34-1 -> 0.11368526 | K35: =K34/J34-1 -> 0.17778676 | L35: =L34/K34-1 -> 0.16488899 | M35: =M34/L34-1 -> 0.136316 | N35: =N34/M34-1 -> 0.18761348
F36: Rent | G36: =SUMIFS(Rent!$E$3:$E$110,Rent!$C$3:$C$110,Register!G$3,Rent!$D$3:$D$110,Register!$C34)/1000 -> 0 | H36: =SUMIFS(Rent!$E$3:$E$110,Rent!$C$3:$C$110,Register!H$3,Rent!$D$3:$D$110,Register!$C34)/1000 -> 0 | I36: =SUMIFS(Rent!$E$3:$E$110,Rent!$C$3:$C$110,Register!I$3,Rent!$D$3:$D$110,Register!$C34)/1000 -> 0 | J36: =SUMIFS(Rent!$E$3:$E$110,Rent!$C$3:$C$110,Register!J$3,Rent!$D$3:$D$110,Register!$C34)/1000 -> 0 | K36: =SUMIFS(Rent!$E$3:$E$110,Rent!$C$3:$C$110,Register!K$3,Rent!$D$3:$D$110,Register!$C34)/1000 -> 0 | L36: =SUMIFS(Rent!$E$3:$E$110,Rent!$C$3:$C$110,Register!L$3,Rent!$D$3:$D$110,Register!$C34)/1000 -> 0 | M36: =SUMIFS(Rent!$E$3:$E$110,Rent!$C$3:$C$110,Register!M$3,Rent!$D$3:$D$110,Register!$C34)/1000 -> 151 | N36: =SUMIFS(Rent!$E$3:$E$110,Rent!$C$3:$C$110,Register!N$3,Rent!$D$3:$D$110,Register!$C34)/1000 -> 159
F37: %YoY | H37: =H36/G36-1 -> #DIV/0! | I37: =I36/H36-1 -> #DIV/0! | J37: =J36/I36-1 -> #DIV/0! | K37: =K36/J36-1 -> #DIV/0! | L37: =L36/K36-1 -> #DIV/0! | M37: =M36/L36-1 -> #DIV/0! | N37: =N36/M36-1 -> 0.052980132
F38: %Yield | G38: =G36/G34 -> 0 | H38: =H36/H34 -> 0 | I38: =I36/I34 -> 0 | J38: =J36/J34 -> 0 | K38: =K36/K34 -> 0 | L38: =L36/L34 -> 0 | M38: =M36/M34 -> 0.00043517104 | N38: =N36/N34 -> 0.00038583805
B39: 64 | C39: Fazenda Paiaguás | D39: Mato Grosso | E39: Diamantino | F39: Asset Value | G39: =(SUMIFS('Asset Value'!$F$4:$F$102,'Asset Value'!$B$4:$B$102,Register!G$3,'Asset Value'!$C$4:$C$102,Register!$C39)/1000)+(G44) -> 218840 | H39: =(SUMIFS('Asset Value'!$F$4:$F$102,'Asset Value'!$B$4:$B$102,Register!H$3,'Asset Value'!$C$4:$C$102,Register!$C39)/1000)+(H44) -> 265050 | I39: =(SUMIFS('Asset Value'!$F$4:$F$102,'Asset Value'!$B$4:$B$102,Register!I$3,'Asset Value'!$C$4:$C$102,Register!$C39)/1000)+(I44) -> 243950 | J39: =(SUMIFS('Asset Value'!$F$4:$F$102,'Asset Value'!$B$4:$B$102,Register!J$3,'Asset Value'!$C$4:$C$102,Register!$C39)/1000)+(J44) -> 279570 | K39: =(SUMIFS('Asset Value'!$F$4:$F$102,'Asset Value'!$B$4:$B$102,Register!K$3,'Asset Value'!$C$4:$C$102,Register!$C39)/1000)+(K44) -> 332180 | L39: =(SUMIFS('Asset Value'!$F$4:$F$102,'Asset Value'!$B$4:$B$102,Register!L$3,'Asset Value'!$C$4:$C$102,Register!$C39)/1000)+(L44) -> 341232 | M39: =(SUMIFS('Asset Value'!$F$4:$F$102,'Asset Value'!$B$4:$B$102,Register!M$3,'Asset Value'!$C$4:$C$102,Register!$C39)/1000)+(M44) -> 420555 | N39: =(SUMIFS('Asset Value'!$F$4:$F$102,'Asset Value'!$B$4:$B$102,Register!N$3,'Asset Value'!$C$4:$C$102,Register!$C39)/1000)+(N44) -> 450910
F40: %YoY | H40: =H39/G39-1 -> 0.21115884 | I40: =I39/H39-1 -> -0.079607621 | J40: =J39/I39-1 -> 0.14601353 | K40: =K39/J39-1 -> 0.18818185 | L40: =L39/K39-1 -> 0.027250286 | M40: =M39/L39-1 -> 0.23246061 | N40: =N39/M39-1 -> 0.072178431
F41: Rent | G41: =(SUMIFS(Rent!$E$3:$E$110,Rent!$C$3:$C$110,Register!G$3,Rent!$D$3:$D$110,Register!$C39)/1000)+(G46) -> 7507.2496 | H41: =(SUMIFS(Rent!$E$3:$E$110,Rent!$C$3:$C$110,Register!H$3,Rent!$D$3:$D$110,Register!$C39)/1000)+(H46) -> 7007.6113 | I41: =(SUMIFS(Rent!$E$3:$E$110,Rent!$C$3:$C$110,Register!I$3,Rent!$D$3:$D$110,Register!$C39)/1000)+(I46) -> 8841.9566 | J41: =(SUMIFS(Rent!$E$3:$E$110,Rent!$C$3:$C$110,Register!J$3,Rent!$D$3:$D$110,Register!$C39)/1000)+(J46) -> 4976.6418 | K41: =(SUMIFS(Rent!$E$3:$E$110,Rent!$C$3:$C$110,Register!K$3,Rent!$D$3:$D$110,Register!$C39)/1000)+(K46) -> 10538 | L41: =(SUMIFS(Rent!$E$3:$E$110,Rent!$C$3:$C$110,Register!L$3,Rent!$D$3:$D$110,Register!$C39)/1000)+(L46) -> 9884 | M41: =(SUMIFS(Rent!$E$3:$E$110,Rent!$C$3:$C$110,Register!M$3,Rent!$D$3:$D$110,Register!$C39)/1000)+(M46) -> 15146 | N41: =(SUMIFS(Rent!$E$3:$E$110,Rent!$C$3:$C$110,Register!N$3,Rent!$D$3:$D$110,Register!$C39)/1000)+(N46) -> 17733
F42: %YoY | H42: =H41/G41-1 -> -0.066554101 | I42: =I41/H41-1 -> 0.26176471 | J42: =J41/I41-1 -> -0.43715605 | K42: =K41/J41-1 -> 1.1174922 | L42: =L41/K41-1 -> -0.062061112 | M42: =M41/L41-1 -> 0.53237556 | N42: =N41/M41-1 -> 0.17080417
F43: %Yield | G43: =G41/G39 -> 0.034304741 | H43: =H41/H39 -> 0.026438828 | I43: =I41/I39 -> 0.036244954 | J43: =J41/J39 -> 0.017801058 | K43: =K41/K39 -> 0.031723764 | L43: =L41/L39 -> 0.02896563 | M43: =M41/M39 -> 0.036014314 | N43: =N41/N39 -> 0.039327138
B44: 64 | C44: Fazenda Pejuçara | D44: Mato Grosso | E44: Diamantino | F44: Asset Value | G44: =SUMIFS('Asset Value'!$F$4:$F$102,'Asset Value'!$B$4:$B$102,Register!G$3,'Asset Value'!$C$4:$C$102,Register!$C44)/1000 -> 0 | H44: =SUMIFS('Asset Value'!$F$4:$F$102,'Asset Value'!$B$4:$B$102,Register!H$3,'Asset Value'!$C$4:$C$102,Register!$C44)/1000 -> 0 | I44: =SUMIFS('Asset Value'!$F$4:$F$102,'Asset Value'!$B$4:$B$102,Register!I$3,'Asset Value'!$C$4:$C$102,Register!$C44)/1000 -> 0 | J44: =SUMIFS('Asset Value'!$F$4:$F$102,'Asset Value'!$B$4:$B$102,Register!J$3,'Asset Value'!$C$4:$C$102,Register!$C44)/1000 -> 0 | K44: =SUMIFS('Asset Value'!$F$4:$F$102,'Asset Value'!$B$4:$B$102,Register!K$3,'Asset Value'!$C$4:$C$102,Register!$C44)/1000 -> 41600 | L44: =SUMIFS('Asset Value'!$F$4:$F$102,'Asset Value'!$B$4:$B$102,Register!L$3,'Asset Value'!$C$4:$C$102,Register!$C44)/1000 -> 42627 | M44: =SUMIFS('Asset Value'!$F$4:$F$102,'Asset Value'!$B$4:$B$102,Register!M$3,'Asset Value'!$C$4:$C$102,Register!$C44)/1000 -> 0 | N44: =SUMIFS('Asset Value'!$F$4:$F$102,'Asset Value'!$B$4:$B$102,Register!N$3,'Asset Value'!$C$4:$C$102,Register!$C44)/1000 -> 0
F45: %YoY | H45: =H44/G44-1 -> #DIV/0! | I45: =I44/H44-1 -> #DIV/0! | J45: =J44/I44-1 -> #DIV/0! | K45: =K44/J44-1 -> #DIV/0! | L45: =L44/K44-1 -> 0.0246875 | M45: =M44/L44-1 -> -1 | N45: =N44/M44-1 -> #DIV/0!
F46: Rent | G46: =SUMIFS(Rent!$E$3:$E$110,Rent!$C$3:$C$110,Register!G$3,Rent!$D$3:$D$110,Register!$C44)/1000 -> 0 | H46: =SUMIFS(Rent!$E$3:$E$110,Rent!$C$3:$C$110,Register!H$3,Rent!$D$3:$D$110,Register!$C44)/1000 -> 0 | I46: =SUMIFS(Rent!$E$3:$E$110,Rent!$C$3:$C$110,Register!I$3,Rent!$D$3:$D$110,Register!$C44)/1000 -> 0 | J46: =SUMIFS(Rent!$E$3:$E$110,Rent!$C$3:$C$110,Register!J$3,Rent!$D$3:$D$110,Register!$C44)/1000 -> 0 | K46: =SUMIFS(Rent!$E$3:$E$110,Rent!$C$3:$C$110,Register!K$3,Rent!$D$3:$D$110,Register!$C44)/1000 -> 1287 | L46: =SUMIFS(Rent!$E$3:$E$110,Rent!$C$3:$C$110,Register!L$3,Rent!$D$3:$D$110,Register!$C44)/1000 -> 1207 | M46: =SUMIFS(Rent!$E$3:$E$110,Rent!$C$3:$C$110,Register!M$3,Rent!$D$3:$D$110,Register!$C44)/1000 -> 0 | N46: =SUMIFS(Rent!$E$3:$E$110,Rent!$C$3:$C$110,Register!N$3,Rent!$D$3:$D$110,Register!$C44)/1000 -> 0
F47: %YoY | H47: =H46/G46-1 -> #DIV/0! | I47: =I46/H46-1 -> #DIV/0! | J47: =J46/I46-1 -> #DIV/0! | K47: =K46/J46-1 -> #DIV/0! | L47: =L46/K46-1 -> -0.062160062 | M47: =M46/L46-1 -> -1 | N47: =N46/M46-1 -> #DIV/0!
F48: %Yield | G48: =G46/G44 -> #DIV/0! | H48: =H46/H44 -> #DIV/0! | I48: =I46/I44 -> #DIV/0! | J48: =J46/J44 -> #DIV/0! | K48: =K46/K44 -> 0.0309375 | L48: =L46/L44 -> 0.028315387 | M48: =M46/M44 -> #DIV/0! | N48: =N46/N44 -> #DIV/0!
B49: 82 | C49: Fazenda Parceiro | D49: Bahia | E49: Formosa do Rio Preto | F49: Asset Value | G49: =SUMIFS('Asset Value'!$F$4:$F$102,'Asset Value'!$B$4:$B$102,Register!G$3,'Asset Value'!$C$4:$C$102,Register!$C49)/1000 -> 0 | H49: =SUMIFS('Asset Value'!$F$4:$F$102,'Asset Value'!$B$4:$B$102,Register!H$3,'Asset Value'!$C$4:$C$102,Register!$C49)/1000 -> 0 | I49: =SUMIFS('Asset Value'!$F$4:$F$102,'Asset Value'!$B$4:$B$102,Register!I$3,'Asset Value'!$C$4:$C$102,Register!$C49)/1000 -> 0 | J49: =SUMIFS('Asset Value'!$F$4:$F$102,'Asset Value'!$B$4:$B$102,Register!J$3,'Asset Value'!$C$4:$C$102,Register!$C49)/1000 -> 0 | K49: =SUMIFS('Asset Value'!$F$4:$F$102,'Asset Value'!$B$4:$B$102,Register!K$3,'Asset Value'!$C$4:$C$102,Register!$C49)/1000 -> 114366 | L49: =SUMIFS('Asset Value'!$F$4:$F$102,'Asset Value'!$B$4:$B$102,Register!L$3,'Asset Value'!$C$4:$C$102,Register!$C49)/1000 -> 168079 | M49: =SUMIFS('Asset Value'!$F$4:$F$102,'Asset Value'!$B$4:$B$102,Register!M$3,'Asset Value'!$C$4:$C$102,Register!$C49)/1000 -> 226665 | N49: =SUMIFS('Asset Value'!$F$4:$F$102,'Asset Value'!$B$4:$B$102,Register!N$3,'Asset Value'!$C$4:$C$102,Register!$C49)/1000 -> 234990
F50: %YoY | H50: =H49/G49-1 -> #DIV/0! | I50: =I49/H49-1 -> #DIV/0! | J50: =J49/I49-1 -> #DIV/0! | K50: =K49/J49-1 -> #DIV/0! | L50: =L49/K49-1 -> 0.46965881 | M50: =M49/L49-1 -> 0.34856228 | N50: =N49/M49-1 -> 0.036728211
F51: Rent | G51: =SUMIFS(Rent!$E$3:$E$110,Rent!$C$3:$C$110,Register!G$3,Rent!$D$3:$D$110,Register!$C49)/1000 -> 0 | H51: =SUMIFS(Rent!$E$3:$E$110,Rent!$C$3:$C$110,Register!H$3,Rent!$D$3:$D$110,Register!$C49)/1000 -> 0 | I51: =SUMIFS(Rent!$E$3:$E$110,Rent!$C$3:$C$110,Register!I$3,Rent!$D$3:$D$110,Register!$C49)/1000 -> 0 | J51: =SUMIFS(Rent!$E$3:$E$110,Rent!$C$3:$C$110,Register!J$3,Rent!$D$3:$D$110,Register!$C49)/1000 -> 0 | K51: =SUMIFS(Rent!$E$3:$E$110,Rent!$C$3:$C$110,Register!K$3,Rent!$D$3:$D$110,Register!$C49)/1000 -> 2962 | L51: =SUMIFS(Rent!$E$3:$E$110,Rent!$C$3:$C$110,Register!L$3,Rent!$D$3:$D$110,Register!$C49)/1000 -> 2245 | M51: =SUMIFS(Rent!$E$3:$E$110,Rent!$C$3:$C$110,Register!M$3,Rent!$D$3:$D$110,Register!$C49)/1000 -> 657 | N51: =SUMIFS(Rent!$E$3:$E$110,Rent!$C$3:$C$110,Register!N$3,Rent!$D$3:$D$110,Register!$C49)/1000 -> 1217
F52: %YoY | H52: =H51/G51-1 -> #DIV/0! | I52: =I51/H51-1 -> #DIV/0! | J52: =J51/I51-1 -> #DIV/0! | K52: =K51/J51-1 -> #DIV/0! | L52: =L51/K51-1 -> -0.24206617 | M52: =M51/L51-1 -> -0.70734967 | N52: =N51/M51-1 -> 0.85235921
F53: %Yield | G53: =G51/G49 -> #DIV/0! | H53: =H51/H49 -> #DIV/0! | I53: =I51/I49 -> #DIV/0! | J53: =J51/J49 -> #DIV/0! | K53: =K51/K49 -> 0.025899306 | L53: =L51/L49 -> 0.013356814 | M53: =M51/M49 -> 0.0028985507 | N53: =N51/N49 -> 0.0051789438
B54: 82 | C54: Fazenda Paladino | D54: Bahia | E54: Sao Desiderio | F54: Asset Value | G54: =SUMIFS('Asset Value'!$F$4:$F$102,'Asset Value'!$B$4:$B$102,Register!G$3,'Asset Value'!$C$4:$C$102,Register!$C54)/1000 -> 0 | H54: =SUMIFS('Asset Value'!$F$4:$F$102,'Asset Value'!$B$4:$B$102,Register!H$3,'Asset Value'!$C$4:$C$102,Register!$C54)/1000 -> 0 | I54: =SUMIFS('Asset Value'!$F$4:$F$102,'Asset Value'!$B$4:$B$102,Register!I$3,'Asset Value'!$C$4:$C$102,Register!$C54)/1000 -> 0 | J54: =SUMIFS('Asset Value'!$F$4:$F$102,'Asset Value'!$B$4:$B$102,Register!J$3,'Asset Value'!$C$4:$C$102,Register!$C54)/1000 -> 0 | K54: =SUMIFS('Asset Value'!$F$4:$F$102,'Asset Value'!$B$4:$B$102,Register!K$3,'Asset Value'!$C$4:$C$102,Register!$C54)/1000 -> 0 | L54: =SUMIFS('Asset Value'!$F$4:$F$102,'Asset Value'!$B$4:$B$102,Register!L$3,'Asset Value'!$C$4:$C$102,Register!$C54)/1000 -> 0 | M54: =SUMIFS('Asset Value'!$F$4:$F$102,'Asset Value'!$B$4:$B$102,Register!M$3,'Asset Value'!$C$4:$C$102,Register!$C54)/1000 -> 0 | N54: =SUMIFS('Asset Value'!$F$4:$F$102,'Asset Value'!$B$4:$B$102,Register!N$3,'Asset Value'!$C$4:$C$102,Register!$C54)/1000 -> 0
F55: %YoY | H55: =H54/G54-1 -> #DIV/0! | I55: =I54/H54-1 -> #DIV/0! | J55: =J54/I54-1 -> #DIV/0! | K55: =K54/J54-1 -> #DIV/0! | L55: =L54/K54-1 -> #DIV/0! | M55: =M54/L54-1 -> #DIV/0! | N55: =N54/M54-1 -> #DIV/0!
F56: Rent | G56: =SUMIFS(Rent!$E$3:$E$110,Rent!$C$3:$C$110,Register!G$3,Rent!$D$3:$D$110,Register!$C54)/1000 -> 0 | H56: =SUMIFS(Rent!$E$3:$E$110,Rent!$C$3:$C$110,Register!H$3,Rent!$D$3:$D$110,Register!$C54)/1000 -> 0 | I56: =SUMIFS(Rent!$E$3:$E$110,Rent!$C$3:$C$110,Register!I$3,Rent!$D$3:$D$110,Register!$C54)/1000 -> 0 | J56: =SUMIFS(Rent!$E$3:$E$110,Rent!$C$3:$C$110,Register!J$3,Rent!$D$3:$D$110,Register!$C54)/1000 -> 0 | K56: =SUMIFS(Rent!$E$3:$E$110,Rent!$C$3:$C$110,Register!K$3,Rent!$D$3:$D$110,Register!$C54)/1000 -> 0 | L56: =SUMIFS(Rent!$E$3:$E$110,Rent!$C$3:$C$110,Register!L$3,Rent!$D$3:$D$110,Register!$C54)/1000 -> 0 | M56: =SUMIFS(Rent!$E$3:$E$110,Rent!$C$3:$C$110,Register!M$3,Rent!$D$3:$D$110,Register!$C54)/1000 -> 0 | N56: =SUMIFS(Rent!$E$3:$E$110,Rent!$C$3:$C$110,Register!N$3,Rent!$D$3:$D$110,Register!$C54)/1000 -> 0
F57: %YoY | H57: =H56/G56-1 -> #DIV/0! | I57: =I56/H56-1 -> #DIV/0! | J57: =J56/I56-1 -> #DIV/0! | K57: =K56/J56-1 -> #DIV/0! | L57: =L56/K56-1 -> #DIV/0! | M57: =M56/L56-1 -> #DIV/0! | N57: =N56/M56-1 -> #DIV/0!
F58: %Yield | G58: =G56/G54 -> #DIV/0! | H58: =H56/H54 -> #DIV/0! | I58: =I56/I54 -> #DIV/0! | J58: =J56/J54 -> #DIV/0! | K58: =K56/K54 -> #DIV/0! | L58: =L56/L54 -> #DIV/0! | M58: =M56/M54 -> #DIV/0! | N58: =N56/N54 -> #DIV/0!
B59: 66 | C59: Fazenda Perdizes | D59: Mato Grosso | E59: Porto Dos Gauchos | F59: Asset Value | G59: =SUMIFS('Asset Value'!$F$4:$F$102,'Asset Value'!$B$4:$B$102,Register!G$3,'Asset Value'!$C$4:$C$102,Register!$C59)/1000 -> 0 | H59: =SUMIFS('Asset Value'!$F$4:$F$102,'Asset Value'!$B$4:$B$102,Register!H$3,'Asset Value'!$C$4:$C$102,Register!$C59)/1000 -> 0 | I59: =SUMIFS('Asset Value'!$F$4:$F$102,'Asset Value'!$B$4:$B$102,Register!I$3,'Asset Value'!$C$4:$C$102,Register!$C59)/1000 -> 0 | J59: =SUMIFS('Asset Value'!$F$4:$F$102,'Asset Value'!$B$4:$B$102,Register!J$3,'Asset Value'!$C$4:$C$102,Register!$C59)/1000 -> 0 | K59: =SUMIFS('Asset Value'!$F$4:$F$102,'Asset Value'!$B$4:$B$102,Register!K$3,'Asset Value'!$C$4:$C$102,Register!$C59)/1000 -> 84185 | L59: =SUMIFS('Asset Value'!$F$4:$F$102,'Asset Value'!$B$4:$B$102,Register!L$3,'Asset Value'!$C$4:$C$102,Register!$C59)/1000 -> 165731 | M59: =SUMIFS('Asset Value'!$F$4:$F$102,'Asset Value'!$B$4:$B$102,Register!M$3,'Asset Value'!$C$4:$C$102,Register!$C59)/1000 -> 170931 | N59: =SUMIFS('Asset Value'!$F$4:$F$102,'Asset Value'!$B$4:$B$102,Register!N$3,'Asset Value'!$C$4:$C$102,Register!$C59)/1000 -> 175030
F60: %YoY | H60: =H59/G59-1 -> #DIV/0! | I60: =I59/H59-1 -> #DIV/0! | J60: =J59/I59-1 -> #DIV/0! | K60: =K59/J59-1 -> #DIV/0! | L60: =L59/K59-1 -> 0.96865237 | M60: =M59/L59-1 -> 0.031376146 | N60: =N59/M59-1 -> 0.023980437
F61: Rent | G61: =SUMIFS(Rent!$E$3:$E$110,Rent!$C$3:$C$110,Register!G$3,Rent!$D$3:$D$110,Register!$C59)/1000 -> 0 | H61: =SUMIFS(Rent!$E$3:$E$110,Rent!$C$3:$C$110,Register!H$3,Rent!$D$3:$D$110,Register!$C59)/1000 -> 0 | I61: =SUMIFS(Rent!$E$3:$E$110,Rent!$C$3:$C$110,Register!I$3,Rent!$D$3:$D$110,Register!$C59)/1000 -> 0 | J61: =SUMIFS(Rent!$E$3:$E$110,Rent!$C$3:$C$110,Register!J$3,Rent!$D$3:$D$110,Register!$C59)/1000 -> 0 | K61: =SUMIFS(Rent!$E$3:$E$110,Rent!$C$3:$C$110,Register!K$3,Rent!$D$3:$D$110,Register!$C59)/1000 -> 5276 | L61: =SUMIFS(Rent!$E$3:$E$110,Rent!$C$3:$C$110,Register!L$3,Rent!$D$3:$D$110,Register!$C59)/1000 -> 4830 | M61: =SUMIFS(Rent!$E$3:$E$110,Rent!$C$3:$C$110,Register!M$3,Rent!$D$3:$D$110,Register!$C59)/1000 -> 5172 | N61: =SUMIFS(Rent!$E$3:$E$110,Rent!$C$3:$C$110,Register!N$3,Rent!$D$3:$D$110,Register!$C59)/1000 -> 5990
F62: %YoY | H62: =H61/G61-1 -> #DIV/0! | I62: =I61/H61-1 -> #DIV/0! | J62: =J61/I61-1 -> #DIV/0! | K62: =K61/J61-1 -> #DIV/0! | L62: =L61/K61-1 -> -0.084533738 | M62: =M61/L61-1 -> 0.070807453 | N62: =N61/M61-1 -> 0.15815932
F63: %Yield | G63: =G61/G59 -> #DIV/0! | H63: =H61/H59 -> #DIV/0! | I63: =I61/I59 -> #DIV/0! | J63: =J61/J59 -> #DIV/0! | K63: =K61/K59 -> 0.062671497 | L63: =L61/L59 -> 0.029143612 | M63: =M61/M59 -> 0.030257823 | N63: =N61/N59 -> 0.034222705
B64: 63 | C64: Fazenda Planorte | D64: Mato Grosso | E64: Sapezal | F64: Asset Value | G64: =SUMIFS('Asset Value'!$F$4:$F$102,'Asset Value'!$B$4:$B$102,Register!G$3,'Asset Value'!$C$4:$C$102,Register!$C64)/1000 -> 108480 | H64: =SUMIFS('Asset Value'!$F$4:$F$102,'Asset Value'!$B$4:$B$102,Register!H$3,'Asset Value'!$C$4:$C$102,Register!$C64)/1000 -> 232990 | I64: =SUMIFS('Asset Value'!$F$4:$F$102,'Asset Value'!$B$4:$B$102,Register!I$3,'Asset Value'!$C$4:$C$102,Register!$C64)/1000 -> 200050 | J64: =SUMIFS('Asset Value'!$F$4:$F$102,'Asset Value'!$B$4:$B$102,Register!J$3,'Asset Value'!$C$4:$C$102,Register!$C64)/1000 -> 219290 | K64: =SUMIFS('Asset Value'!$F$4:$F$102,'Asset Value'!$B$4:$B$102,Register!K$3,'Asset Value'!$C$4:$C$102,Register!$C64)/1000 -> 255020 | L64: =SUMIFS('Asset Value'!$F$4:$F$102,'Asset Value'!$B$4:$B$102,Register!L$3,'Asset Value'!$C$4:$C$102,Register!$C64)/1000 -> 256728 | M64: =SUMIFS('Asset Value'!$F$4:$F$102,'Asset Value'!$B$4:$B$102,Register!M$3,'Asset Value'!$C$4:$C$102,Register!$C64)/1000 -> 308243 | N64: =SUMIFS('Asset Value'!$F$4:$F$102,'Asset Value'!$B$4:$B$102,Register!N$3,'Asset Value'!$C$4:$C$102,Register!$C64)/1000 -> 315870
F65: %YoY | H65: =H64/G64-1 -> 1.1477692 | I65: =I64/H64-1 -> -0.14137946 | J65: =J64/I64-1 -> 0.096175956 | K65: =K64/J64-1 -> 0.16293493 | L65: =L64/K64-1 -> 0.0066975139 | M65: =M64/L64-1 -> 0.20065984 | N65: =N64/M64-1 -> 0.024743465
F66: Rent | G66: =SUMIFS(Rent!$E$3:$E$110,Rent!$C$3:$C$110,Register!G$3,Rent!$D$3:$D$110,Register!$C64)/1000 -> 0 | H66: =SUMIFS(Rent!$E$3:$E$110,Rent!$C$3:$C$110,Register!H$3,Rent!$D$3:$D$110,Register!$C64)/1000 -> 0 | I66: =SUMIFS(Rent!$E$3:$E$110,Rent!$C$3:$C$110,Register!I$3,Rent!$D$3:$D$110,Register!$C64)/1000 -> 0 | J66: =SUMIFS(Rent!$E$3:$E$110,Rent!$C$3:$C$110,Register!J$3,Rent!$D$3:$D$110,Register!$C64)/1000 -> 0 | K66: =SUMIFS(Rent!$E$3:$E$110,Rent!$C$3:$C$110,Register!K$3,Rent!$D$3:$D$110,Register!$C64)/1000 -> 0 | L66: =SUMIFS(Rent!$E$3:$E$110,Rent!$C$3:$C$110,Register!L$3,Rent!$D$3:$D$110,Register!$C64)/1000 -> 0 | M66: =SUMIFS(Rent!$E$3:$E$110,Rent!$C$3:$C$110,Register!M$3,Rent!$D$3:$D$110,Register!$C64)/1000 -> 0 | N66: =SUMIFS(Rent!$E$3:$E$110,Rent!$C$3:$C$110,Register!N$3,Rent!$D$3:$D$110,Register!$C64)/1000 -> 0
F67: %YoY | H67: =H66/G66-1 -> #DIV/0! | I67: =I66/H66-1 -> #DIV/0! | J67: =J66/I66-1 -> #DIV/0! | K67: =K66/J66-1 -> #DIV/0! | L67: =L66/K66-1 -> #DIV/0! | M67: =M66/L66-1 -> #DIV/0! | N67: =N66/M66-1 -> #DIV/0!
F68: %Yield | G68: =G66/G64 -> 0 | H68: =H66/H64 -> 0 | I68: =I66/I64 -> 0 | J68: =J66/J64 -> 0 | K68: =K66/K64 -> 0 | L68: =L66/L64 -> 0 | M68: =M66/M64 -> 0 | N68: =N66/N64 -> 0
B69: 110 | C69: Fazenda Parnaguá | D69: Piaui | E69: Santa Filomena | F69: Asset Value | G69: =SUMIFS('Asset Value'!$F$4:$F$102,'Asset Value'!$B$4:$B$102,Register!G$3,'Asset Value'!$C$4:$C$102,Register!$C69)/1000 -> 0 | H69: =SUMIFS('Asset Value'!$F$4:$F$102,'Asset Value'!$B$4:$B$102,Register!H$3,'Asset Value'!$C$4:$C$102,Register!$C69)/1000 -> 49990 | I69: =SUMIFS('Asset Value'!$F$4:$F$102,'Asset Value'!$B$4:$B$102,Register!I$3,'Asset Value'!$C$4:$C$102,Register!$C69)/1000 -> 50760 | J69: =SUMIFS('Asset Value'!$F$4:$F$102,'Asset Value'!$B$4:$B$102,Register!J$3,'Asset Value'!$C$4:$C$102,Register!$C69)/1000 -> 60540 | K69: =SUMIFS('Asset Value'!$F$4:$F$102,'Asset Value'!$B$4:$B$102,Register!K$3,'Asset Value'!$C$4:$C$102,Register!$C69)/1000 -> 63480 | L69: =SUMIFS('Asset Value'!$F$4:$F$102,'Asset Value'!$B$4:$B$102,Register!L$3,'Asset Value'!$C$4:$C$102,Register!$C69)/1000 -> 86708 | M69: =SUMIFS('Asset Value'!$F$4:$F$102,'Asset Value'!$B$4:$B$102,Register!M$3,'Asset Value'!$C$4:$C$102,Register!$C69)/1000 -> 137610 | N69: =SUMIFS('Asset Value'!$F$4:$F$102,'Asset Value'!$B$4:$B$102,Register!N$3,'Asset Value'!$C$4:$C$102,Register!$C69)/1000 -> 143710
F70: %YoY | H70: =H69/G69-1 -> #DIV/0! | I70: =I69/H69-1 -> 0.015403081 | J70: =J69/I69-1 -> 0.19267139 | K70: =K69/J69-1 -> 0.048562934 | L70: =L69/K69-1 -> 0.36591052 | M70: =M69/L69-1 -> 0.58705079 | N70: =N69/M69-1 -> 0.044328174
F71: Rent | G71: =SUMIFS(Rent!$E$3:$E$110,Rent!$C$3:$C$110,Register!G$3,Rent!$D$3:$D$110,Register!$C69)/1000 -> 0 | H71: =SUMIFS(Rent!$E$3:$E$110,Rent!$C$3:$C$110,Register!H$3,Rent!$D$3:$D$110,Register!$C69)/1000 -> 0 | I71: =SUMIFS(Rent!$E$3:$E$110,Rent!$C$3:$C$110,Register!I$3,Rent!$D$3:$D$110,Register!$C69)/1000 -> 0 | J71: =SUMIFS(Rent!$E$3:$E$110,Rent!$C$3:$C$110,Register!J$3,Rent!$D$3:$D$110,Register!$C69)/1000 -> 0 | K71: =SUMIFS(Rent!$E$3:$E$110,Rent!$C$3:$C$110,Register!K$3,Rent!$D$3:$D$110,Register!$C69)/1000 -> 0 | L71: =SUMIFS(Rent!$E$3:$E$110,Rent!$C$3:$C$110,Register!L$3,Rent!$D$3:$D$110,Register!$C69)/1000 -> 2100 | M71: =SUMIFS(Rent!$E$3:$E$110,Rent!$C$3:$C$110,Register!M$3,Rent!$D$3:$D$110,Register!$C69)/1000 -> 0 | N71: =SUMIFS(Rent!$E$3:$E$110,Rent!$C$3:$C$110,Register!N$3,Rent!$D$3:$D$110,Register!$C69)/1000 -> 586
F72: %YoY | H72: =H71/G71-1 -> #DIV/0! | I72: =I71/H71-1 -> #DIV/0! | J72: =J71/I71-1 -> #DIV/0! | K72: =K71/J71-1 -> #DIV/0! | L72: =L71/K71-1 -> #DIV/0! | M72: =M71/L71-1 -> -1 | N72: =N71/M71-1 -> #DIV/0!
F73: %Yield | G73: =G71/G69 -> #DIV/0! | H73: =H71/H69 -> 0 | I73: =I71/I69 -> 0 | J73: =J71/J69 -> 0 | K73: =K71/K69 -> 0 | L73: =L71/L69 -> 0.024219219 | M73: =M71/M69 -> 0 | N73: =N71/N69 -> 0.0040776564
B74: 110 | C74: Fazenda Paineira | D74: Piaui | E74: Monte Alegre | F74: Asset Value | G74: =SUMIFS('Asset Value'!$F$4:$F$102,'Asset Value'!$B$4:$B$102,Register!G$3,'Asset Value'!$C$4:$C$102,Register!$C74)/1000 -> 0 | H74: =SUMIFS('Asset Value'!$F$4:$F$102,'Asset Value'!$B$4:$B$102,Register!H$3,'Asset Value'!$C$4:$C$102,Register!$C74)/1000 -> 0 | I74: =SUMIFS('Asset Value'!$F$4:$F$102,'Asset Value'!$B$4:$B$102,Register!I$3,'Asset Value'!$C$4:$C$102,Register!$C74)/1000 -> 0 | J74: =SUMIFS('Asset Value'!$F$4:$F$102,'Asset Value'!$B$4:$B$102,Register!J$3,'Asset Value'!$C$4:$C$102,Register!$C74)/1000 -> 0 | K74: =SUMIFS('Asset Value'!$F$4:$F$102,'Asset Value'!$B$4:$B$102,Register!K$3,'Asset Value'!$C$4:$C$102,Register!$C74)/1000 -> 65475 | L74: =SUMIFS('Asset Value'!$F$4:$F$102,'Asset Value'!$B$4:$B$102,Register!L$3,'Asset Value'!$C$4:$C$102,Register!$C74)/1000 -> 83471 | M74: =SUMIFS('Asset Value'!$F$4:$F$102,'Asset Value'!$B$4:$B$102,Register!M$3,'Asset Value'!$C$4:$C$102,Register!$C74)/1000 -> 87257 | N74: =SUMIFS('Asset Value'!$F$4:$F$102,'Asset Value'!$B$4:$B$102,Register!N$3,'Asset Value'!$C$4:$C$102,Register!$C74)/1000 -> 93350
F75: %YoY | H75: =H74/G74-1 -> #DIV/0! | I75: =I74/H74-1 -> #DIV/0! | J75: =J74/I74-1 -> #DIV/0! | K75: =K74/J74-1 -> #DIV/0! | L75: =L74/K74-1 -> 0.274853 | M75: =M74/L74-1 -> 0.04535707 | N75: =N74/M74-1 -> 0.069828209
F76: Rent | G76: =SUMIFS(Rent!$E$3:$E$110,Rent!$C$3:$C$110,Register!G$3,Rent!$D$3:$D$110,Register!$C74)/1000 -> 0 | H76: =SUMIFS(Rent!$E$3:$E$110,Rent!$C$3:$C$110,Register!H$3,Rent!$D$3:$D$110,Register!$C74)/1000 -> 0 | I76: =SUMIFS(Rent!$E$3:$E$110,Rent!$C$3:$C$110,Register!I$3,Rent!$D$3:$D$110,Register!$C74)/1000 -> 0 | J76: =SUMIFS(Rent!$E$3:$E$110,Rent!$C$3:$C$110,Register!J$3,Rent!$D$3:$D$110,Register!$C74)/1000 -> 0 | K76: =SUMIFS(Rent!$E$3:$E$110,Rent!$C$3:$C$110,Register!K$3,Rent!$D$3:$D$110,Register!$C74)/1000 -> 2533 | L76: =SUMIFS(Rent!$E$3:$E$110,Rent!$C$3:$C$110,Register!L$3,Rent!$D$3:$D$110,Register!$C74)/1000 -> 1965 | M76: =SUMIFS(Rent!$E$3:$E$110,Rent!$C$3:$C$110,Register!M$3,Rent!$D$3:$D$110,Register!$C74)/1000 -> 2688 | N76: =SUMIFS(Rent!$E$3:$E$110,Rent!$C$3:$C$110,Register!N$3,Rent!$D$3:$D$110,Register!$C74)/1000 -> 0
F77: %YoY | H77: =H76/G76-1 -> #DIV/0! | I77: =I76/H76-1 -> #DIV/0! | J77: =J76/I76-1 -> #DIV/0! | K77: =K76/J76-1 -> #DIV/0! | L77: =L76/K76-1 -> -0.22424003 | M77: =M76/L76-1 -> 0.36793893 | N77: =N76/M76-1 -> -1
F78: %Yield | G78: =G76/G74 -> #DIV/0! | H78: =H76/H74 -> #DIV/0! | I78: =I76/I74 -> #DIV/0! | J78: =J76/J74 -> #DIV/0! | K78: =K76/K74 -> 0.038686522 | L78: =L76/L74 -> 0.02354111 | M78: =M76/M74 -> 0.030805551 | N78: =N76/N74 -> 0
B79: 117 | C79: Fazenda Palmeira | D79: Maranhao | E79: Buriti | F79: Asset Value | G79: =SUMIFS('Asset Value'!$F$4:$F$102,'Asset Value'!$B$4:$B$102,Register!G$3,'Asset Value'!$C$4:$C$102,Register!$C79)/1000 -> 20520 | H79: =SUMIFS('Asset Value'!$F$4:$F$102,'Asset Value'!$B$4:$B$102,Register!H$3,'Asset Value'!$C$4:$C$102,Register!$C79)/1000 -> 25260 | I79: =SUMIFS('Asset Value'!$F$4:$F$102,'Asset Value'!$B$4:$B$102,Register!I$3,'Asset Value'!$C$4:$C$102,Register!$C79)/1000 -> 24850 | J79: =SUMIFS('Asset Value'!$F$4:$F$102,'Asset Value'!$B$4:$B$102,Register!J$3,'Asset Value'!$C$4:$C$102,Register!$C79)/1000 -> 0 | K79: =SUMIFS('Asset Value'!$F$4:$F$102,'Asset Value'!$B$4:$B$102,Register!K$3,'Asset Value'!$C$4:$C$102,Register!$C79)/1000 -> 0 | L79: =SUMIFS('Asset Value'!$F$4:$F$102,'Asset Value'!$B$4:$B$102,Register!L$3,'Asset Value'!$C$4:$C$102,Register!$C79)/1000 -> 0 | M79: =SUMIFS('Asset Value'!$F$4:$F$102,'Asset Value'!$B$4:$B$102,Register!M$3,'Asset Value'!$C$4:$C$102,Register!$C79)/1000 -> 0 | N79: =SUMIFS('Asset Value'!$F$4:$F$102,'Asset Value'!$B$4:$B$102,Register!N$3,'Asset Value'!$C$4:$C$102,Register!$C79)/1000 -> 0
F80: %YoY | H80: =H79/G79-1 -> 0.23099415 | I80: =I79/H79-1 -> -0.016231196 | J80: =J79/I79-1 -> -1 | K80: =K79/J79-1 -> #DIV/0! | L80: =L79/K79-1 -> #DIV/0! | M80: =M79/L79-1 -> #DIV/0! | N80: =N79/M79-1 -> #DIV/0!
F81: Rent | G81: =SUMIFS(Rent!$E$3:$E$110,Rent!$C$3:$C$110,Register!G$3,Rent!$D$3:$D$110,Register!$C79)/1000 -> 1083.6 | H81: =SUMIFS(Rent!$E$3:$E$110,Rent!$C$3:$C$110,Register!H$3,Rent!$D$3:$D$110,Register!$C79)/1000 -> 948.15 | I81: =SUMIFS(Rent!$E$3:$E$110,Rent!$C$3:$C$110,Register!I$3,Rent!$D$3:$D$110,Register!$C79)/1000 -> 0 | J81: =SUMIFS(Rent!$E$3:$E$110,Rent!$C$3:$C$110,Register!J$3,Rent!$D$3:$D$110,Register!$C79)/1000 -> 0 | K81: =SUMIFS(Rent!$E$3:$E$110,Rent!$C$3:$C$110,Register!K$3,Rent!$D$3:$D$110,Register!$C79)/1000 -> 0 | L81: =SUMIFS(Rent!$E$3:$E$110,Rent!$C$3:$C$110,Register!L$3,Rent!$D$3:$D$110,Register!$C79)/1000 -> 0 | M81: =SUMIFS(Rent!$E$3:$E$110,Rent!$C$3:$C$110,Register!M$3,Rent!$D$3:$D$110,Register!$C79)/1000 -> 0 | N81: =SUMIFS(Rent!$E$3:$E$110,Rent!$C$3:$C$110,Register!N$3,Rent!$D$3:$D$110,Register!$C79)/1000 -> 0
F82: %YoY | H82: =H81/G81-1 -> -0.125 | I82: =I81/H81-1 -> -1 | J82: =J81/I81-1 -> #DIV/0! | K82: =K81/J81-1 -> #DIV/0! | L82: =L81/K81-1 -> #DIV/0! | M82: =M81/L81-1 -> #DIV/0! | N82: =N81/M81-1 -> #DIV/0!
F83: %Yield | G83: =G81/G79 -> 0.052807018 | H83: =H81/H79 -> 0.037535629 | I83: =I81/I79 -> 0 | J83: =J81/J79 -> #DIV/0! | K83: =K81/K79 -> #DIV/0! | L83: =L81/L79 -> #DIV/0! | M83: =M81/M79 -> #DIV/0! | N83: =N81/N79 -> #DIV/0!

Sheet Asset Value
A3: Date | B3: Ano | C3: Fazenda | D3: Area Agricultavel | E3: Valor (R$ 000) | F3: Valor (R$) | G3: (R$/ha) | H3: PTAX (R$/US$) | I3: Valor (US$) | J3: (US$/ha) | L3: PTAX = cotação de compra do Banco Central na data do Date (ou último dia útil anterior). Ver aba PTAX.
A4: 39568 | B4: 2008 | C4: Fazenda Pamplona | D4: 17094 | E4: 143610 | F4: =E4*1000 -> 143610000 | G4: =F4/D4 -> 8401.1934 | H4: =IFERROR(INDEX(PTAX!$C$5:$C$5000,MATCH($A4,PTAX!$B$5:$B$5000,1)),"") -> 1.6864 | I4: =IF(H4="","",F4/H4) -> 85157732 | J4: =IF(H4="","",I4/D4) -> 4981.7323
A5: 39568 | B5: 2008 | C5: Fazenda Planalto | D5: 17489 | E5: 207710 | F5: =E5*1000 -> 207710000 | G5: =F5/D5 -> 11876.608 | H5: =IFERROR(INDEX(PTAX!$C$5:$C$5000,MATCH($A5,PTAX!$B$5:$B$5000,1)),"") -> 1.6864 | I5: =IF(H5="","",F5/H5) -> 1.2316769e+08 | J5: =IF(H5="","",I5/D5) -> 7042.5807
A6: 39568 | B6: 2008 | C6: Fazenda Planeste | D6: 18256 | E6: 106940 | F6: =E6*1000 -> 106940000 | G6: =F6/D6 -> 5857.8002 | H6: =IFERROR(INDEX(PTAX!$C$5:$C$5000,MATCH($A6,PTAX!$B$5:$B$5000,1)),"") -> 1.6864 | I6: =IF(H6="","",F6/H6) -> 63413188 | J6: =IF(H6="","",I6/D6) -> 3473.5532
A7: 39568 | B7: 2008 | C7: Fazenda Parnaíba | D7: 26084 | E7: 156660 | F7: =E7*1000 -> 156660000 | G7: =F7/D7 -> 6005.9807 | H7: =IFERROR(INDEX(PTAX!$C$5:$C$5000,MATCH($A7,PTAX!$B$5:$B$5000,1)),"") -> 1.6864 | I7: =IF(H7="","",F7/H7) -> 92896110 | J7: =IF(H7="","",I7/D7) -> 3561.4212
A8: 39568 | B8: 2008 | C8: Fazenda Palmeira | D8: 14963 | E8: 20520 | F8: =E8*1000 -> 20520000 | G8: =F8/D8 -> 1371.3827 | H8: =IFERROR(INDEX(PTAX!$C$5:$C$5000,MATCH($A8,PTAX!$B$5:$B$5000,1)),"") -> 1.6864 | I8: =IF(H8="","",F8/H8) -> 12167932 | J8: =IF(H8="","",I8/D8) -> 813.20134
A9: 39568 | B9: 2008 | C9: Fazenda Planorte | D9: 13159 | E9: 108480 | F9: =E9*1000 -> 108480000 | G9: =F9/D9 -> 8243.7875 | H9: =IFERROR(INDEX(PTAX!$C$5:$C$5000,MATCH($A9,PTAX!$B$5:$B$5000,1)),"") -> 1.6864 | I9: =IF(H9="","",F9/H9) -> 64326376 | J9: =IF(H9="","",I9/D9) -> 4888.3939
A10: 39568 | B10: 2008 | C10: Fazenda Paiaguás | D10: 26257 | E10: 218840 | F10: =E10*1000 -> 218840000 | G10: =F10/D10 -> 8334.5394 | H10: =IFERROR(INDEX(PTAX!$C$5:$C$5000,MATCH($A10,PTAX!$B$5:$B$5000,1)),"") -> 1.6864 | I10: =IF(H10="","",F10/H10) -> 1.2976755e+08 | J10: =IF(H10="","",I10/D10) -> 4942.2079
A11: 39568 | B11: 2008 | C11: Fazenda Panorama | D11: 9220 | E11: 75090 | F11: =E11*1000 -> 75090000 | G11: =F11/D11 -> 8144.2516 | H11: =IFERROR(INDEX(PTAX!$C$5:$C$5000,MATCH($A11,PTAX!$B$5:$B$5000,1)),"") -> 1.6864 | I11: =IF(H11="","",F11/H11) -> 44526803 | J11: =IF(H11="","",I11/D11) -> 4829.3712
A12: 39568 | B12: 2008 | C12: Fazenda Piratini | D12: 25002 | E12: 58920 | F12: =E12*1000 -> 58920000 | G12: =F12/D12 -> 2356.6115 | H12: =IFERROR(INDEX(PTAX!$C$5:$C$5000,MATCH($A12,PTAX!$B$5:$B$5000,1)),"") -> 1.6864 | I12: =IF(H12="","",F12/H12) -> 34938330 | J12: =IF(H12="","",I12/D12) -> 1397.4214
A13: 39961 | B13: 2009 | C13: Fazenda Pamplona | D13: 17094 | E13: 158220 | F13: =E13*1000 -> 158220000 | G13: =F13/D13 -> 9255.8793 | H13: =IFERROR(INDEX(PTAX!$C$5:$C$5000,MATCH($A13,PTAX!$B$5:$B$5000,1)),"") -> 2.0136 | I13: =IF(H13="","",F13/H13) -> 78575685 | J13: =IF(H13="","",I13/D13) -> 4596.6822
A14: 39961 | B14: 2009 | C14: Fazenda Planalto | D14: 17489 | E14: 234810 | F14: =E14*1000 -> 234810000 | G14: =F14/D14 -> 13426.154 | H14: =IFERROR(INDEX(PTAX!$C$5:$C$5000,MATCH($A14,PTAX!$B$5:$B$5000,1)),"") -> 2.0136 | I14: =IF(H14="","",F14/H14) -> 1.1661204e+08 | J14: =IF(H14="","",I14/D14) -> 6667.7362
A15: 39961 | B15: 2009 | C15: Fazenda Planeste | D15: 18256 | E15: 118040 | F15: =E15*1000 -> 118040000 | G15: =F15/D15 -> 6465.8195 | H15: =IFERROR(INDEX(PTAX!$C$5:$C$5000,MATCH($A15,PTAX!$B$5:$B$5000,1)),"") -> 2.0136 | I15: =IF(H15="","",F15/H15) -> 58621375 | J15: =IF(H15="","",I15/D15) -> 3211.0744
... A102: 42216 | B102: 2015 | C102: Fazenda Piratini | D102: 25356 | E102: 222860 | F102: =E102*1000 -> 222860000 | G102: =F102/D102 -> 8789.2412 | H102: =IFERROR(INDEX(PTAX!$C$5:$C$5000,MATCH($A102,PTAX!$B$5:$B$5000,1)),"") -> 3.3934 | I102: =IF(H102="","",F102/H102) -> 65674545 | J102: =IF(H102="","",I102/D102) -> 2590.0988

Sheet Rent
B2: Date | C2: Year | D2: Farm | E2: R$/year | F2: PTAX (R$/US$) | G2: US$/year | I2: PTAX = cotação de compra do Banco Central em 31/dez (ou último dia útil anterior). Ver aba PTAX.
B3: 39447 | C3: 2007 | D3: Fazenda Planalto | E3: 6223629.9 | F3: =IFERROR(INDEX(PTAX!$C$5:$C$5000,MATCH($B3,PTAX!$B$5:$B$5000,1)),"") -> 1.7705 | G3: =IF(F3="","",E3/F3) -> 3515182.1
B4: 39447 | C4: 2007 | D4: Fazenda Pamplona | E4: 5489634.8 | F4: =IFERROR(INDEX(PTAX!$C$5:$C$5000,MATCH($B4,PTAX!$B$5:$B$5000,1)),"") -> 1.7705 | G4: =IF(F4="","",E4/F4) -> 3100612.7
B5: 39447 | C5: 2007 | D5: Fazenda Planeste | E5: 3727492.6 | F5: =IFERROR(INDEX(PTAX!$C$5:$C$5000,MATCH($B5,PTAX!$B$5:$B$5000,1)),"") -> 1.7705 | G5: =IF(F5="","",E5/F5) -> 2105333.3
B6: 39447 | C6: 2007 | D6: Fazenda Palmeira | E6: 936862.5 | F6: =IFERROR(INDEX(PTAX!$C$5:$C$5000,MATCH($B6,PTAX!$B$5:$B$5000,1)),"") -> 1.7705 | G6: =IF(F6="","",E6/F6) -> 529151.37
B7: 39447 | C7: 2007 | D7: Fazenda Panorama | E7: 2049840 | F7: =IFERROR(INDEX(PTAX!$C$5:$C$5000,MATCH($B7,PTAX!$B$5:$B$5000,1)),"") -> 1.7705 | G7: =IF(F7="","",E7/F7) -> 1157774.6
B8: 39447 | C8: 2007 | D8: Fazenda Paiaguás | E8: 7507249.6 | F8: =IFERROR(INDEX(PTAX!$C$5:$C$5000,MATCH($B8,PTAX!$B$5:$B$5000,1)),"") -> 1.7705 | G8: =IF(F8="","",E8/F8) -> 4240186.1
B9: 39813 | C9: 2008 | D9: Fazenda Planalto | E9: 6078894.4 | F9: =IFERROR(INDEX(PTAX!$C$5:$C$5000,MATCH($B9,PTAX!$B$5:$B$5000,1)),"") -> 2.3362 | G9: =IF(F9="","",E9/F9) -> 2602043.6
B10: 39813 | C10: 2008 | D10: Fazenda Pamplona | E10: 5764116.5 | F10: =IFERROR(INDEX(PTAX!$C$5:$C$5000,MATCH($B10,PTAX!$B$5:$B$5000,1)),"") -> 2.3362 | G10: =IF(F10="","",E10/F10) -> 2467304.4
B11: 39813 | C11: 2008 | D11: Fazenda Planeste | E11: 3727492.6 | F11: =IFERROR(INDEX(PTAX!$C$5:$C$5000,MATCH($B11,PTAX!$B$5:$B$5000,1)),"") -> 2.3362 | G11: =IF(F11="","",E11/F11) -> 1595536.6
B12: 39813 | C12: 2008 | D12: Fazenda Palmeira | E12: 1083600 | F12: =IFERROR(INDEX(PTAX!$C$5:$C$5000,MATCH($B12,PTAX!$B$5:$B$5000,1)),"") -> 2.3362 | G12: =IF(F12="","",E12/F12) -> 463830.15
B13: 39813 | C13: 2008 | D13: Fazenda Panorama | E13: 2181240 | F13: =IFERROR(INDEX(PTAX!$C$5:$C$5000,MATCH($B13,PTAX!$B$5:$B$5000,1)),"") -> 2.3362 | G13: =IF(F13="","",E13/F13) -> 933670.06
B14: 39813 | C14: 2008 | D14: Fazenda Paiaguás | E14: 7507249.6 | F14: =IFERROR(INDEX(PTAX!$C$5:$C$5000,MATCH($B14,PTAX!$B$5:$B$5000,1)),"") -> 2.3362 | G14: =IF(F14="","",E14/F14) -> 3213444.7
... B39: 40908 | C39: 2011 | D39: Fazenda Piratini | E39: 692094.78 | F39: =IFERROR(INDEX(PTAX!$C$5:$C$5000,MATCH($B39,PTAX!$B$5:$B$5000,1)),"") -> 1.8751 | G39: =IF(F39="","",E39/F39) -> 369097.53
B40: =DATE(C40,12,31) -> 41274 | C40: 2012 | D40: Fazenda Planalto | E40: 7795000 | F40: =IFERROR(INDEX(PTAX!$C$5:$C$5000,MATCH($B40,PTAX!$B$5:$B$5000,1)),"") -> 2.0429 | G40: =IF(F40="","",E40/F40) -> 3815654.2
B41: =DATE(C41,12,31) -> 41639 | C41: 2013 | D41: Fazenda Planalto | E41: 7483000 | F41: =IFERROR(INDEX(PTAX!$C$5:$C$5000,MATCH($B41,PTAX!$B$5:$B$5000,1)),"") -> 2.342 | G41: =IF(F41="","",E41/F41) -> 3195132.4
B42: =DATE(C42,12,31) -> 42004 | C42: 2014 | D42: Fazenda Planalto | E42: 10660000 | F42: =IFERROR(INDEX(PTAX!$C$5:$C$5000,MATCH($B42,PTAX!$B$5:$B$5000,1)),"") -> 2.6556 | G42: =IF(F42="","",E42/F42) -> 4014158.8
B43: =DATE(C43,12,31) -> 42369 | C43: 2015 | D43: Fazenda Planalto | E43: 13057000 | F43: =IFERROR(INDEX(PTAX!$C$5:$C$5000,MATCH($B43,PTAX!$B$5:$B$5000,1)),"") -> 3.9042 | G43: =IF(F43="","",E43/F43) -> 3344347.1
B44: =DATE(C44,12,31) -> 42735 | C44: 2016 | D44: Fazenda Planalto | E44: 12883000 | F44: =IFERROR(INDEX(PTAX!$C$5:$C$5000,MATCH($B44,PTAX!$B$5:$B$5000,1)),"") -> 3.2585 | G44: =IF(F44="","",E44/F44) -> 3953659.7
B45: =DATE(C45,12,31) -> 43100 | C45: 2017 | D45: Fazenda Planalto | E45: 13426000 | F45: =IFERROR(INDEX(PTAX!$C$5:$C$5000,MATCH($B45,PTAX!$B$5:$B$5000,1)),"") -> 3.3074 | G45: =IF(F45="","",E45/F45) -> 4059382
B46: =DATE(C46,12,31) -> 41274 | C46: 2012 | D46: Fazenda Pamplona | E46: 6522000 | F46: =IFERROR(INDEX(PTAX!$C$5:$C$5000,MATCH($B46,PTAX!$B$5:$B$5000,1)),"") -> 2.0429 | G46: =IF(F46="","",E46/F46) -> 3192520.4
B47: =DATE(C47,12,31) -> 41639 | C47: 2013 | D47: Fazenda Pamplona | E47: 5902000 | F47: =IFERROR(INDEX(PTAX!$C$5:$C$5000,MATCH($B47,PTAX!$B$5:$B$5000,1)),"") -> 2.342 | G47: =IF(F47="","",E47/F47) -> 2520068.3
B48: =DATE(C48,12,31) -> 42004 | C48: 2014 | D48: Fazenda Pamplona | E48: 6567000 | F48: =IFERROR(INDEX(PTAX!$C$5:$C$5000,MATCH($B48,PTAX!$B$5:$B$5000,1)),"") -> 2.6556 | G48: =IF(F48="","",E48/F48) -> 2472887.5
B49: =DATE(C49,12,31) -> 42369 | C49: 2015 | D49: Fazenda Pamplona | E49: 8312000 | F49: =IFERROR(INDEX(PTAX!$C$5:$C$5000,MATCH($B49,PTAX!$B$5:$B$5000,1)),"") -> 3.9042 | G49: =IF(F49="","",E49/F49) -> 2128989.3
B50: =DATE(C50,12,31) -> 42735 | C50: 2016 | D50: Fazenda Pamplona | E50: 7880000 | F50: =IFERROR(INDEX(PTAX!$C$5:$C$5000,MATCH($B50,PTAX!$B$5:$B$5000,1)),"") -> 3.2585 | G50: =IF(F50="","",E50/F50) -> 2418290.6
B51: =DATE(C51,12,31) -> 43100 | C51: 2017 | D51: Fazenda Pamplona | E51: 8082000 | F51: =IFERROR(INDEX(PTAX!$C$5:$C$5000,MATCH($B51,PTAX!$B$5:$B$5000,1)),"") -> 3.3074 | G51: =IF(F51="","",E51/F51) -> 2443611.3
... B110: =DATE(C110,12,31) -> 43100 | C110: 2017 | D110: Fazenda Planorte | E110: 12637000 | F110: =IFERROR(INDEX(PTAX!$C$5:$C$5000,MATCH($B110,PTAX!$B$5:$B$5000,1)),"") -> 3.3074 | G110: =IF(F110="","",E110/F110) -> 3820826

Sheet Sales
B2: Date | C2: Farm | D2: Value (R$) | E2: PTAX (R$/US$) | F2: Value (US$) | H2: Venda total da fazenda (R$). No ano da venda, o Ending MV da fazenda = preço de venda; no ano seguinte ela sai do índice.
B3: 40445 | C3: Fazenda Palmeira | D3: 27160000 | E3: =IFERROR(INDEX(PTAX!$C$5:$C$5000,MATCH($B3,PTAX!$B$5:$B$5000,1)),"") -> 1.7112 | F3: =IF(OR($B3="",E3=""),"",D3/E3) -> 15871903
E4: =IFERROR(INDEX(PTAX!$C$5:$C$5000,MATCH($B4,PTAX!$B$5:$B$5000,1)),"") | F4: =IF(OR($B4="",E4=""),"",D4/E4)
E5: =IFERROR(INDEX(PTAX!$C$5:$C$5000,MATCH($B5,PTAX!$B$5:$B$5000,1)),"") | F5: =IF(OR($B5="",E5=""),"",D5/E5)
E6: =IFERROR(INDEX(PTAX!$C$5:$C$5000,MATCH($B6,PTAX!$B$5:$B$5000,1)),"") | F6: =IF(OR($B6="",E6=""),"",D6/E6)
E7: =IFERROR(INDEX(PTAX!$C$5:$C$5000,MATCH($B7,PTAX!$B$5:$B$5000,1)),"") | F7: =IF(OR($B7="",E7=""),"",D7/E7)
E8: =IFERROR(INDEX(PTAX!$C$5:$C$5000,MATCH($B8,PTAX!$B$5:$B$5000,1)),"") | F8: =IF(OR($B8="",E8=""),"",D8/E8)
E9: =IFERROR(INDEX(PTAX!$C$5:$C$5000,MATCH($B9,PTAX!$B$5:$B$5000,1)),"") | F9: =IF(OR($B9="",E9=""),"",D9/E9)
E10: =IFERROR(INDEX(PTAX!$C$5:$C$5000,MATCH($B10,PTAX!$B$5:$B$5000,1)),"") | F10: =IF(OR($B10="",E10=""),"",D10/E10)
E11: =IFERROR(INDEX(PTAX!$C$5:$C$5000,MATCH($B11,PTAX!$B$5:$B$5000,1)),"") | F11: =IF(OR($B11="",E11=""),"",D11/E11)
E12: =IFERROR(INDEX(PTAX!$C$5:$C$5000,MATCH($B12,PTAX!$B$5:$B$5000,1)),"") | F12: =IF(OR($B12="",E12=""),"",D12/E12)
E13: =IFERROR(INDEX(PTAX!$C$5:$C$5000,MATCH($B13,PTAX!$B$5:$B$5000,1)),"") | F13: =IF(OR($B13="",E13=""),"",D13/E13)
E14: =IFERROR(INDEX(PTAX!$C$5:$C$5000,MATCH($B14,PTAX!$B$5:$B$5000,1)),"") | F14: =IF(OR($B14="",E14=""),"",D14/E14)
E15: =IFERROR(INDEX(PTAX!$C$5:$C$5000,MATCH($B15,PTAX!$B$5:$B$5000,1)),"") | F15: =IF(OR($B15="",E15=""),"",D15/E15)
... E60: =IFERROR(INDEX(PTAX!$C$5:$C$5000,MATCH($B60,PTAX!$B$5:$B$5000,1)),"") | F60: =IF(OR($B60="",E60=""),"",D60/E60)

Sheet Partial Sales
B2: Date | C2: Farm | D2: Value (R$) | E2: PTAX (R$/US$) | F2: Value (US$) | H2: Vendas parciais (R$). Aba vazia = 0. Preencher Date / Farm / Value (R$); PTAX e US$ são calculados.
E3: =IFERROR(INDEX(PTAX!$C$5:$C$5000,MATCH($B3,PTAX!$B$5:$B$5000,1)),"") | F3: =IF(OR($B3="",E3=""),"",D3/E3)
E4: =IFERROR(INDEX(PTAX!$C$5:$C$5000,MATCH($B4,PTAX!$B$5:$B$5000,1)),"") | F4: =IF(OR($B4="",E4=""),"",D4/E4)
E5: =IFERROR(INDEX(PTAX!$C$5:$C$5000,MATCH($B5,PTAX!$B$5:$B$5000,1)),"") | F5: =IF(OR($B5="",E5=""),"",D5/E5)
E6: =IFERROR(INDEX(PTAX!$C$5:$C$5000,MATCH($B6,PTAX!$B$5:$B$5000,1)),"") | F6: =IF(OR($B6="",E6=""),"",D6/E6)
E7: =IFERROR(INDEX(PTAX!$C$5:$C$5000,MATCH($B7,PTAX!$B$5:$B$5000,1)),"") | F7: =IF(OR($B7="",E7=""),"",D7/E7)
E8: =IFERROR(INDEX(PTAX!$C$5:$C$5000,MATCH($B8,PTAX!$B$5:$B$5000,1)),"") | F8: =IF(OR($B8="",E8=""),"",D8/E8)
E9: =IFERROR(INDEX(PTAX!$C$5:$C$5000,MATCH($B9,PTAX!$B$5:$B$5000,1)),"") | F9: =IF(OR($B9="",E9=""),"",D9/E9)
E10: =IFERROR(INDEX(PTAX!$C$5:$C$5000,MATCH($B10,PTAX!$B$5:$B$5000,1)),"") | F10: =IF(OR($B10="",E10=""),"",D10/E10)
E11: =IFERROR(INDEX(PTAX!$C$5:$C$5000,MATCH($B11,PTAX!$B$5:$B$5000,1)),"") | F11: =IF(OR($B11="",E11=""),"",D11/E11)
E12: =IFERROR(INDEX(PTAX!$C$5:$C$5000,MATCH($B12,PTAX!$B$5:$B$5000,1)),"") | F12: =IF(OR($B12="",E12=""),"",D12/E12)
E13: =IFERROR(INDEX(PTAX!$C$5:$C$5000,MATCH($B13,PTAX!$B$5:$B$5000,1)),"") | F13: =IF(OR($B13="",E13=""),"",D13/E13)
E14: =IFERROR(INDEX(PTAX!$C$5:$C$5000,MATCH($B14,PTAX!$B$5:$B$5000,1)),"") | F14: =IF(OR($B14="",E14=""),"",D14/E14)
... E60: =IFERROR(INDEX(PTAX!$C$5:$C$5000,MATCH($B60,PTAX!$B$5:$B$5000,1)),"") | F60: =IF(OR($B60="",E60=""),"",D60/E60)

Sheet Costs
B2: Date | C2: Farm | D2: Value (R$) | E2: PTAX (R$/US$) | F2: Value (US$) | H2: Capital Improvements (R$). Aba vazia = 0. Preencher Date / Farm / Value (R$); PTAX e US$ são calculados.
E3: =IFERROR(INDEX(PTAX!$C$5:$C$5000,MATCH($B3,PTAX!$B$5:$B$5000,1)),"") | F3: =IF(OR($B3="",E3=""),"",D3/E3)
E4: =IFERROR(INDEX(PTAX!$C$5:$C$5000,MATCH($B4,PTAX!$B$5:$B$5000,1)),"") | F4: =IF(OR($B4="",E4=""),"",D4/E4)
E5: =IFERROR(INDEX(PTAX!$C$5:$C$5000,MATCH($B5,PTAX!$B$5:$B$5000,1)),"") | F5: =IF(OR($B5="",E5=""),"",D5/E5)
E6: =IFERROR(INDEX(PTAX!$C$5:$C$5000,MATCH($B6,PTAX!$B$5:$B$5000,1)),"") | F6: =IF(OR($B6="",E6=""),"",D6/E6)
E7: =IFERROR(INDEX(PTAX!$C$5:$C$5000,MATCH($B7,PTAX!$B$5:$B$5000,1)),"") | F7: =IF(OR($B7="",E7=""),"",D7/E7)
E8: =IFERROR(INDEX(PTAX!$C$5:$C$5000,MATCH($B8,PTAX!$B$5:$B$5000,1)),"") | F8: =IF(OR($B8="",E8=""),"",D8/E8)
E9: =IFERROR(INDEX(PTAX!$C$5:$C$5000,MATCH($B9,PTAX!$B$5:$B$5000,1)),"") | F9: =IF(OR($B9="",E9=""),"",D9/E9)
E10: =IFERROR(INDEX(PTAX!$C$5:$C$5000,MATCH($B10,PTAX!$B$5:$B$5000,1)),"") | F10: =IF(OR($B10="",E10=""),"",D10/E10)
E11: =IFERROR(INDEX(PTAX!$C$5:$C$5000,MATCH($B11,PTAX!$B$5:$B$5000,1)),"") | F11: =IF(OR($B11="",E11=""),"",D11/E11)
E12: =IFERROR(INDEX(PTAX!$C$5:$C$5000,MATCH($B12,PTAX!$B$5:$B$5000,1)),"") | F12: =IF(OR($B12="",E12=""),"",D12/E12)
E13: =IFERROR(INDEX(PTAX!$C$5:$C$5000,MATCH($B13,PTAX!$B$5:$B$5000,1)),"") | F13: =IF(OR($B13="",E13=""),"",D13/E13)
E14: =IFERROR(INDEX(PTAX!$C$5:$C$5000,MATCH($B14,PTAX!$B$5:$B$5000,1)),"") | F14: =IF(OR($B14="",E14=""),"",D14/E14)
... E60: =IFERROR(INDEX(PTAX!$C$5:$C$5000,MATCH($B60,PTAX!$B$5:$B$5000,1)),"") | F60: =IF(OR($B60="",E60=""),"",D60/E60)

Sheet Partial Purchases
B2: Date | C2: Farm | D2: Value (R$) | E2: PTAX (R$/US$) | F2: Value (US$) | H2: Compras parciais / aquisições de área (R$). Aba vazia = 0. Preencher Date / Farm / Value (R$).
E3: =IFERROR(INDEX(PTAX!$C$5:$C$5000,MATCH($B3,PTAX!$B$5:$B$5000,1)),"") | F3: =IF(OR($B3="",E3=""),"",D3/E3)
E4: =IFERROR(INDEX(PTAX!$C$5:$C$5000,MATCH($B4,PTAX!$B$5:$B$5000,1)),"") | F4: =IF(OR($B4="",E4=""),"",D4/E4)
E5: =IFERROR(INDEX(PTAX!$C$5:$C$5000,MATCH($B5,PTAX!$B$5:$B$5000,1)),"") | F5: =IF(OR($B5="",E5=""),"",D5/E5)
E6: =IFERROR(INDEX(PTAX!$C$5:$C$5000,MATCH($B6,PTAX!$B$5:$B$5000,1)),"") | F6: =IF(OR($B6="",E6=""),"",D6/E6)
E7: =IFERROR(INDEX(PTAX!$C$5:$C$5000,MATCH($B7,PTAX!$B$5:$B$5000,1)),"") | F7: =IF(OR($B7="",E7=""),"",D7/E7)
E8: =IFERROR(INDEX(PTAX!$C$5:$C$5000,MATCH($B8,PTAX!$B$5:$B$5000,1)),"") | F8: =IF(OR($B8="",E8=""),"",D8/E8)
E9: =IFERROR(INDEX(PTAX!$C$5:$C$5000,MATCH($B9,PTAX!$B$5:$B$5000,1)),"") | F9: =IF(OR($B9="",E9=""),"",D9/E9)
E10: =IFERROR(INDEX(PTAX!$C$5:$C$5000,MATCH($B10,PTAX!$B$5:$B$5000,1)),"") | F10: =IF(OR($B10="",E10=""),"",D10/E10)
E11: =IFERROR(INDEX(PTAX!$C$5:$C$5000,MATCH($B11,PTAX!$B$5:$B$5000,1)),"") | F11: =IF(OR($B11="",E11=""),"",D11/E11)
E12: =IFERROR(INDEX(PTAX!$C$5:$C$5000,MATCH($B12,PTAX!$B$5:$B$5000,1)),"") | F12: =IF(OR($B12="",E12=""),"",D12/E12)
E13: =IFERROR(INDEX(PTAX!$C$5:$C$5000,MATCH($B13,PTAX!$B$5:$B$5000,1)),"") | F13: =IF(OR($B13="",E13=""),"",D13/E13)
E14: =IFERROR(INDEX(PTAX!$C$5:$C$5000,MATCH($B14,PTAX!$B$5:$B$5000,1)),"") | F14: =IF(OR($B14="",E14=""),"",D14/E14)
... E60: =IFERROR(INDEX(PTAX!$C$5:$C$5000,MATCH($B60,PTAX!$B$5:$B$5000,1)),"") | F60: =IF(OR($B60="",E60=""),"",D60/E60)

Sheet PTAX
B1: PTAX compra (R$ por US$) - Banco Central do Brasil
B2: Fonte: arquivo fornecido pelo usuário (BCB/Olinda PTAX, CotacaoDolarPeriodo), campo cotacaoCompra (taxa de compra), diário, 02/01/2007 a 31/12/2025. Em datas sem cotação (fim de semana/feriado) usa-se a última cotação anterior.
B4: Date | C4: PTAX (R$/US$)
B5: 39084 | C5: 2.1334
B6: 39085 | C6: 2.1364
B7: 39086 | C7: 2.1421
B8: 39087 | C8: 2.1466
B9: 39090 | C9: 2.1497
B10: 39091 | C10: 2.1498
B11: 39092 | C11: 2.1548
B12: 39093 | C12: 2.1457
B13: 39094 | C13: 2.1413
B14: 39097 | C14: 2.1399
B15: 39098 | C15: 2.1436
B16: 39099 | C16: 2.1342
... B4777: 46022 | C4777: 5.5018

Sheet Returns
A1: Farmland Returns Index (estilo NCREIF Farmland Property Index)
A2: Cada fazenda é um cluster. Retornos anuais 2009-2015 (base do índice = 100 em 2008). Valores em R$ mil / US$ mil nas tabelas de cálculo.
A3: Income Return = NOI / (Beginning MV + 1/2 x (Capital Improvements - Partial Sales + Partial Purchases - NOI))
A4: Capital (Appreciation) Return = (Ending MV - Beginning MV + Partial Sales - Capital Improvements - Partial Purchases) / (mesmo denominador)
A5: Total Return = Income Return + Capital Return. Índices: encadeados (chain-linked) a partir de 100. Total Farmland = soma dos numeradores / soma dos denominadores (ponderado por valor de mercado).
A6: Beginning MV = avaliação do ano anterior; Ending MV = avaliação do ano (preço de venda se a fazenda foi vendida no ano); NOI = Rent do ano. Fazenda só entra no índice a partir do ano seguinte à 1ª avaliação e sai no ano seguinte à venda.
A7: Abas Costs / Partial Sales / Partial Purchases vazias = 0. Venda total (aba Sales): Ending MV do ano da venda = preço de venda. US$: cada valor convertido pela PTAX da própria data (avaliação, 31/dez do rent, data da venda).
A10: FARMLAND INDEX - R$ (NCREIF style) | E10: Returns | O10: Index Values (Dec 2008 = 100)
A11: Farm | B11: Years | C11: Market Value (R$ mm, 2015) | E11: 2009 | F11: =E11+1 -> 2010 | G11: =F11+1 -> 2011 | H11: =G11+1 -> 2012 | I11: =H11+1 -> 2013 | J11: =I11+1 -> 2014 | K11: =J11+1 -> 2015 | L11: Cumulative | M11: Annualized | O11: =E11-1 -> 2008 | P11: =O11+1 -> 2009 | Q11: =P11+1 -> 2010 | R11: =Q11+1 -> 2011 | S11: =R11+1 -> 2012 | T11: =S11+1 -> 2013 | U11: =T11+1 -> 2014 | V11: =U11+1 -> 2015
A12: Total Farmland | B12: =COUNT(E12:K12) -> 7 | C12: =K16 -> 3401.84 | D12: Total: | E12: =IF(E14="","",E14+E13) -> 0.32372509 | F12: =IF(F14="","",F14+F13) -> 0.024781337 | G12: =IF(G14="","",G14+G13) -> 0.21320752 | H12: =IF(H14="","",H14+H13) -> 0.17723094 | I12: =IF(I14="","",I14+I13) -> 0.18378129 | J12: =IF(J14="","",J14+J13) -> 0.21773877 | K12: =IF(K14="","",K14+K13) -> 0.091517953 | L12: =V12/O12-1 -> 2.0484723 | M12: =IF($B12=0,"",(V12/O12)^(1/$B12)-1) -> 0.17261274 | O12: 100 | P12: =IF(E12="",O12,O12*(1+E12)) -> 132.37251 | Q12: =IF(F12="",P12,P12*(1+F12)) -> 135.65288 | R12: =IF(G12="",Q12,Q12*(1+G12)) -> 164.57509 | S12: =IF(H12="",R12,R12*(1+H12)) -> 193.74289 | T12: =IF(I12="",S12,S12*(1+I12)) -> 229.34921 | U12: =IF(J12="",T12,T12*(1+J12)) -> 279.28742 | V12: =IF(K12="",U12,U12*(1+K12)) -> 304.84723
D13: Appreciation: | E13: =IF(SUMIFS($J$120:$J$239,$B$120:$B$239,E$11)=0,"",SUMIFS($K$120:$K$239,$B$120:$B$239,E$11)/SUMIFS($J$120:$J$239,$B$120:$B$239,E$11)) -> 0.3007842 | F13: =IF(SUMIFS($J$120:$J$239,$B$120:$B$239,F$11)=0,"",SUMIFS($K$120:$K$239,$B$120:$B$239,F$11)/SUMIFS($J$120:$J$239,$B$120:$B$239,F$11)) -> 0.0035406072 | G13: =IF(SUMIFS($J$120:$J$239,$B$120:$B$239,G$11)=0,"",SUMIFS($K$120:$K$239,$B$120:$B$239,G$11)/SUMIFS($J$120:$J$239,$B$120:$B$239,G$11)) -> 0.19349258 | H13: =IF(SUMIFS($J$120:$J$239,$B$120:$B$239,H$11)=0,"",SUMIFS($K$120:$K$239,$B$120:$B$239,H$11)/SUMIFS($J$120:$J$239,$B$120:$B$239,H$11)) -> 0.14673799 | I13: =IF(SUMIFS($J$120:$J$239,$B$120:$B$239,I$11)=0,"",SUMIFS($K$120:$K$239,$B$120:$B$239,I$11)/SUMIFS($J$120:$J$239,$B$120:$B$239,I$11)) -> 0.15873273 | J13: =IF(SUMIFS($J$120:$J$239,$B$120:$B$239,J$11)=0,"",SUMIFS($K$120:$K$239,$B$120:$B$239,J$11)/SUMIFS($J$120:$J$239,$B$120:$B$239,J$11)) -> 0.1928236 | K13: =IF(SUMIFS($J$120:$J$239,$B$120:$B$239,K$11)=0,"",SUMIFS($K$120:$K$239,$B$120:$B$239,K$11)/SUMIFS($J$120:$J$239,$B$120:$B$239,K$11)) -> 0.067620648 | L13: =V13/O13-1 -> 1.6363349 | M13: =IF($B12=0,"",(V13/O13)^(1/$B12)-1) -> 0.14853158 | O13: 100 | P13: =IF(E13="",O13,O13*(1+E13)) -> 130.07842 | Q13: =IF(F13="",P13,P13*(1+F13)) -> 130.53898 | R13: =IF(G13="",Q13,Q13*(1+G13)) -> 155.7973 | S13: =IF(H13="",R13,R13*(1+H13)) -> 178.65868 | T13: =IF(I13="",S13,S13*(1+I13)) -> 207.01766 | U13: =IF(J13="",T13,T13*(1+J13)) -> 246.93555 | V13: =IF(K13="",U13,U13*(1+K13)) -> 263.63349
D14: Income: | E14: =IF(SUMIFS($J$120:$J$239,$B$120:$B$239,E$11)=0,"",SUMIFS($F$120:$F$239,$B$120:$B$239,E$11,$C$120:$C$239,1)/SUMIFS($J$120:$J$239,$B$120:$B$239,E$11)) -> 0.022940894 | F14: =IF(SUMIFS($J$120:$J$239,$B$120:$B$239,F$11)=0,"",SUMIFS($F$120:$F$239,$B$120:$B$239,F$11,$C$120:$C$239,1)/SUMIFS($J$120:$J$239,$B$120:$B$239,F$11)) -> 0.02124073 | G14: =IF(SUMIFS($J$120:$J$239,$B$120:$B$239,G$11)=0,"",SUMIFS($F$120:$F$239,$B$120:$B$239,G$11,$C$120:$C$239,1)/SUMIFS($J$120:$J$239,$B$120:$B$239,G$11)) -> 0.019714943 | H14: =IF(SUMIFS($J$120:$J$239,$B$120:$B$239,H$11)=0,"",SUMIFS($F$120:$F$239,$B$120:$B$239,H$11,$C$120:$C$239,1)/SUMIFS($J$120:$J$239,$B$120:$B$239,H$11)) -> 0.030492948 | I14: =IF(SUMIFS($J$120:$J$239,$B$120:$B$239,I$11)=0,"",SUMIFS($F$120:$F$239,$B$120:$B$239,I$11,$C$120:$C$239,1)/SUMIFS($J$120:$J$239,$B$120:$B$239,I$11)) -> 0.025048563 | J14: =IF(SUMIFS($J$120:$J$239,$B$120:$B$239,J$11)=0,"",SUMIFS($F$120:$F$239,$B$120:$B$239,J$11,$C$120:$C$239,1)/SUMIFS($J$120:$J$239,$B$120:$B$239,J$11)) -> 0.024915177 | K14: =IF(SUMIFS($J$120:$J$239,$B$120:$B$239,K$11)=0,"",SUMIFS($F$120:$F$239,$B$120:$B$239,K$11,$C$120:$C$239,1)/SUMIFS($J$120:$J$239,$B$120:$B$239,K$11)) -> 0.023897305 | L14: =V14/O14-1 -> 0.1808405 | M14: =IF($B12=0,"",(V14/O14)^(1/$B12)-1) -> 0.024030836 | O14: 100 | P14: =IF(E14="",O14,O14*(1+E14)) -> 102.29409 | Q14: =IF(F14="",P14,P14*(1+F14)) -> 104.46689 | R14: =IF(G14="",Q14,Q14*(1+G14)) -> 106.52645 | S14: =IF(H14="",R14,R14*(1+H14)) -> 109.77475 | T14: =IF(I14="",S14,S14*(1+I14)) -> 112.52445 | U14: =IF(J14="",T14,T14*(1+J14)) -> 115.32802 | V14: =IF(K14="",U14,U14*(1+K14)) -> 118.08405
D15: Props: | E15: =COUNTIFS($B$120:$B$239,E$11,$E$120:$E$239,">0") -> 11 | F15: =COUNTIFS($B$120:$B$239,F$11,$E$120:$E$239,">0") -> 11 | G15: =COUNTIFS($B$120:$B$239,G$11,$E$120:$E$239,">0") -> 10 | H15: =COUNTIFS($B$120:$B$239,H$11,$E$120:$E$239,">0") -> 14 | I15: =COUNTIFS($B$120:$B$239,I$11,$E$120:$E$239,">0") -> 14 | J15: =COUNTIFS($B$120:$B$239,J$11,$E$120:$E$239,">0") -> 13 | K15: =COUNTIFS($B$120:$B$239,K$11,$E$120:$E$239,">0") -> 13
D16: MV (R$ mm): | E16: =SUMIFS($E$120:$E$239,$B$120:$B$239,E$11)/1000 -> 1495.69 | F16: =SUMIFS($E$120:$E$239,$B$120:$B$239,F$11)/1000 -> 1500.93 | G16: =SUMIFS($E$120:$E$239,$B$120:$B$239,G$11)/1000 -> 1756.15 | H16: =SUMIFS($E$120:$E$239,$B$120:$B$239,H$11)/1000 -> 2315.6 | I16: =SUMIFS($E$120:$E$239,$B$120:$B$239,I$11)/1000 -> 2678.615 | J16: =SUMIFS($E$120:$E$239,$B$120:$B$239,J$11)/1000 -> 3188.76 | K16: =SUMIFS($E$120:$E$239,$B$120:$B$239,K$11)/1000 -> 3401.84
A17: Fazenda Pamplona | B17: =COUNT(E17:K17) -> 7 | C17: =SUMIFS($E$120:$E$239,$A$120:$A$239,$A17,$B$120:$B$239,K$11)/1000 -> 290.9 | D17: Total: | E17: =IF(SUMIFS($C$120:$C$239,$A$120:$A$239,$A$17,$B$120:$B$239,E$11)=0,"",SUMIFS($N$120:$N$239,$A$120:$A$239,$A$17,$B$120:$B$239,E$11)) -> 0.14225521 | F17: =IF(SUMIFS($C$120:$C$239,$A$120:$A$239,$A$17,$B$120:$B$239,F$11)=0,"",SUMIFS($N$120:$N$239,$A$120:$A$239,$A$17,$B$120:$B$239,F$11)) -> 0.077190094 | G17: =IF(SUMIFS($C$120:$C$239,$A$120:$A$239,$A$17,$B$120:$B$239,G$11)=0,"",SUMIFS($N$120:$N$239,$A$120:$A$239,$A$17,$B$120:$B$239,G$11)) -> 0.1191465 | H17: =IF(SUMIFS($C$120:$C$239,$A$120:$A$239,$A$17,$B$120:$B$239,H$11)=0,"",SUMIFS($N$120:$N$239,$A$120:$A$239,$A$17,$B$120:$B$239,H$11)) -> 0.24151915 | I17: =IF(SUMIFS($C$120:$C$239,$A$120:$A$239,$A$17,$B$120:$B$239,I$11)=0,"",SUMIFS($N$120:$N$239,$A$120:$A$239,$A$17,$B$120:$B$239,I$11)) -> 0.068713883 | J17: =IF(SUMIFS($C$120:$C$239,$A$120:$A$239,$A$17,$B$120:$B$239,J$11)=0,"",SUMIFS($N$120:$N$239,$A$120:$A$239,$A$17,$B$120:$B$239,J$11)) -> 0.23589231 | K17: =IF(SUMIFS($C$120:$C$239,$A$120:$A$239,$A$17,$B$120:$B$239,K$11)=0,"",SUMIFS($N$120:$N$239,$A$120:$A$239,$A$17,$B$120:$B$239,K$11)) -> 0.11021391 | L17: =V17/O17-1 -> 1.5069438 | M17: =IF($B17=0,"",(V17/O17)^(1/$B17)-1) -> 0.14030403 | O17: 100 | P17: =IF(E17="",O17,O17*(1+E17)) -> 114.22552 | Q17: =IF(F17="",P17,P17*(1+F17)) -> 123.0426 | R17: =IF(G17="",Q17,Q17*(1+G17)) -> 137.70269 | S17: =IF(H17="",R17,R17*(1+H17)) -> 170.96053 | T17: =IF(I17="",S17,S17*(1+I17)) -> 182.70789 | U17: =IF(J17="",T17,T17*(1+J17)) -> 225.80728 | V17: =IF(K17="",U17,U17*(1+K17)) -> 250.69438
D18: Appreciation: | E18: =IF(SUMIFS($C$120:$C$239,$A$120:$A$239,$A$17,$B$120:$B$239,E$11)=0,"",SUMIFS($M$120:$M$239,$A$120:$A$239,$A$17,$B$120:$B$239,E$11)) -> 0.10369529 | F18: =IF(SUMIFS($C$120:$C$239,$A$120:$A$239,$A$17,$B$120:$B$239,F$11)=0,"",SUMIFS($M$120:$M$239,$A$120:$A$239,$A$17,$B$120:$B$239,F$11)) -> 0.038779025 | G18: =IF(SUMIFS($C$120:$C$239,$A$120:$A$239,$A$17,$B$120:$B$239,G$11)=0,"",SUMIFS($M$120:$M$239,$A$120:$A$239,$A$17,$B$120:$B$239,G$11)) -> 0.094489735 | H18: =IF(SUMIFS($C$120:$C$239,$A$120:$A$239,$A$17,$B$120:$B$239,H$11)=0,"",SUMIFS($M$120:$M$239,$A$120:$A$239,$A$17,$B$120:$B$239,H$11)) -> 0.20452728 | I18: =IF(SUMIFS($C$120:$C$239,$A$120:$A$239,$A$17,$B$120:$B$239,I$11)=0,"",SUMIFS($M$120:$M$239,$A$120:$A$239,$A$17,$B$120:$B$239,I$11)) -> 0.040963142 | J18: =IF(SUMIFS($C$120:$C$239,$A$120:$A$239,$A$17,$B$120:$B$239,J$11)=0,"",SUMIFS($M$120:$M$239,$A$120:$A$239,$A$17,$B$120:$B$239,J$11)) -> 0.20618524 | K18: =IF(SUMIFS($C$120:$C$239,$A$120:$A$239,$A$17,$B$120:$B$239,K$11)=0,"",SUMIFS($M$120:$M$239,$A$120:$A$239,$A$17,$B$120:$B$239,K$11)) -> 0.07893816 | L18: =V18/O18-1 -> 1.047607 | M18: =IF($B17=0,"",(V18/O18)^(1/$B17)-1) -> 0.10780622 | O18: 100 | P18: =IF(E18="",O18,O18*(1+E18)) -> 110.36953 | Q18: =IF(F18="",P18,P18*(1+F18)) -> 114.64955 | R18: =IF(G18="",Q18,Q18*(1+G18)) -> 125.48276 | S18: =IF(H18="",R18,R18*(1+H18)) -> 151.1474 | T18: =IF(I18="",S18,S18*(1+I18)) -> 157.33888 | U18: =IF(J18="",T18,T18*(1+J18)) -> 189.77983 | V18: =IF(K18="",U18,U18*(1+K18)) -> 204.7607
D19: Income: | E19: =IF(SUMIFS($C$120:$C$239,$A$120:$A$239,$A$17,$B$120:$B$239,E$11)=0,"",SUMIFS($L$120:$L$239,$A$120:$A$239,$A$17,$B$120:$B$239,E$11)) -> 0.038559923 | F19: =IF(SUMIFS($C$120:$C$239,$A$120:$A$239,$A$17,$B$120:$B$239,F$11)=0,"",SUMIFS($L$120:$L$239,$A$120:$A$239,$A$17,$B$120:$B$239,F$11)) -> 0.038411069 | G19: =IF(SUMIFS($C$120:$C$239,$A$120:$A$239,$A$17,$B$120:$B$239,G$11)=0,"",SUMIFS($L$120:$L$239,$A$120:$A$239,$A$17,$B$120:$B$239,G$11)) -> 0.024656761 | H19: =IF(SUMIFS($C$120:$C$239,$A$120:$A$239,$A$17,$B$120:$B$239,H$11)=0,"",SUMIFS($L$120:$L$239,$A$120:$A$239,$A$17,$B$120:$B$239,H$11)) -> 0.036991872 | I19: =IF(SUMIFS($C$120:$C$239,$A$120:$A$239,$A$17,$B$120:$B$239,I$11)=0,"",SUMIFS($L$120:$L$239,$A$120:$A$239,$A$17,$B$120:$B$239,I$11)) -> 0.027750742 | J19: =IF(SUMIFS($C$120:$C$239,$A$120:$A$239,$A$17,$B$120:$B$239,J$11)=0,"",SUMIFS($L$120:$L$239,$A$120:$A$239,$A$17,$B$120:$B$239,J$11)) -> 0.029707068 | K19: =IF(SUMIFS($C$120:$C$239,$A$120:$A$239,$A$17,$B$120:$B$239,K$11)=0,"",SUMIFS($L$120:$L$239,$A$120:$A$239,$A$17,$B$120:$B$239,K$11)) -> 0.031275751 | L19: =V19/O19-1 -> 0.25063601 | M19: =IF($B17=0,"",(V19/O19)^(1/$B17)-1) -> 0.03246621 | O19: 100 | P19: =IF(E19="",O19,O19*(1+E19)) -> 103.85599 | Q19: =IF(F19="",P19,P19*(1+F19)) -> 107.84521 | R19: =IF(G19="",Q19,Q19*(1+G19)) -> 110.50433 | S19: =IF(H19="",R19,R19*(1+H19)) -> 114.59209 | T19: =IF(I19="",S19,S19*(1+I19)) -> 117.7721 | U19: =IF(J19="",T19,T19*(1+J19)) -> 121.27077 | V19: =IF(K19="",U19,U19*(1+K19)) -> 125.0636
A20: Fazenda Planalto | B20: =COUNT(E20:K20) -> 7 | C20: =SUMIFS($E$120:$E$239,$A$120:$A$239,$A20,$B$120:$B$239,K$11)/1000 -> 473.55 | D20: Total: | E20: =IF(SUMIFS($C$120:$C$239,$A$120:$A$239,$A$20,$B$120:$B$239,E$11)=0,"",SUMIFS($N$120:$N$239,$A$120:$A$239,$A$20,$B$120:$B$239,E$11)) -> 0.16134457 | F20: =IF(SUMIFS($C$120:$C$239,$A$120:$A$239,$A$20,$B$120:$B$239,F$11)=0,"",SUMIFS($N$120:$N$239,$A$120:$A$239,$A$20,$B$120:$B$239,F$11)) -> 0.059645862 | G20: =IF(SUMIFS($C$120:$C$239,$A$120:$A$239,$A$20,$B$120:$B$239,G$11)=0,"",SUMIFS($N$120:$N$239,$A$120:$A$239,$A$20,$B$120:$B$239,G$11)) -> 0.15310799 | H20: =IF(SUMIFS($C$120:$C$239,$A$120:$A$239,$A$20,$B$120:$B$239,H$11)=0,"",SUMIFS($N$120:$N$239,$A$120:$A$239,$A$20,$B$120:$B$239,H$11)) -> 0.20818635 | I20: =IF(SUMIFS($C$120:$C$239,$A$120:$A$239,$A$20,$B$120:$B$239,I$11)=0,"",SUMIFS($N$120:$N$239,$A$120:$A$239,$A$20,$B$120:$B$239,I$11)) -> 0.052903576 | J20: =IF(SUMIFS($C$120:$C$239,$A$120:$A$239,$A$20,$B$120:$B$239,J$11)=0,"",SUMIFS($N$120:$N$239,$A$120:$A$239,$A$20,$B$120:$B$239,J$11)) -> 0.40506523 | K20: =IF(SUMIFS($C$120:$C$239,$A$120:$A$239,$A$20,$B$120:$B$239,K$11)=0,"",SUMIFS($N$120:$N$239,$A$120:$A$239,$A$20,$B$120:$B$239,K$11)) -> 0.074651439 | L20: =V20/O20-1 -> 1.7257026 | M20: =IF($B20=0,"",(V20/O20)^(1/$B20)-1) -> 0.15401435 | O20: 100 | P20: =IF(E20="",O20,O20*(1+E20)) -> 116.13446 | Q20: =IF(F20="",P20,P20*(1+F20)) -> 123.0614 | R20: =IF(G20="",Q20,Q20*(1+G20)) -> 141.90308 | S20: =IF(H20="",R20,R20*(1+H20)) -> 171.44536 | T20: =IF(I20="",S20,S20*(1+I20)) -> 180.51544 | U20: =IF(J20="",T20,T20*(1+J20)) -> 253.63597 | V20: =IF(K20="",U20,U20*(1+K20)) -> 272.57026
D21: Appreciation: | E21: =IF(SUMIFS($C$120:$C$239,$A$120:$A$239,$A$20,$B$120:$B$239,E$11)=0,"",SUMIFS($M$120:$M$239,$A$120:$A$239,$A$20,$B$120:$B$239,E$11)) -> 0.13236111 | F21: =IF(SUMIFS($C$120:$C$239,$A$120:$A$239,$A$20,$B$120:$B$239,F$11)=0,"",SUMIFS($M$120:$M$239,$A$120:$A$239,$A$20,$B$120:$B$239,F$11)) -> 0.030249509 | G21: =IF(SUMIFS($C$120:$C$239,$A$120:$A$239,$A$20,$B$120:$B$239,G$11)=0,"",SUMIFS($M$120:$M$239,$A$120:$A$239,$A$20,$B$120:$B$239,G$11)) -> 0.13405522 | H21: =IF(SUMIFS($C$120:$C$239,$A$120:$A$239,$A$20,$B$120:$B$239,H$11)=0,"",SUMIFS($M$120:$M$239,$A$120:$A$239,$A$20,$B$120:$B$239,H$11)) -> 0.17931839 | I21: =IF(SUMIFS($C$120:$C$239,$A$120:$A$239,$A$20,$B$120:$B$239,I$11)=0,"",SUMIFS($M$120:$M$239,$A$120:$A$239,$A$20,$B$120:$B$239,I$11)) -> 0.029416334 | J21: =IF(SUMIFS($C$120:$C$239,$A$120:$A$239,$A$20,$B$120:$B$239,J$11)=0,"",SUMIFS($M$120:$M$239,$A$120:$A$239,$A$20,$B$120:$B$239,J$11)) -> 0.37240412 | K21: =IF(SUMIFS($C$120:$C$239,$A$120:$A$239,$A$20,$B$120:$B$239,K$11)=0,"",SUMIFS($M$120:$M$239,$A$120:$A$239,$A$20,$B$120:$B$239,K$11)) -> 0.045423461 | L21: =V21/O21-1 -> 1.3044004 | M21: =IF($B20=0,"",(V21/O21)^(1/$B20)-1) -> 0.1266629 | O21: 100 | P21: =IF(E21="",O21,O21*(1+E21)) -> 113.23611 | Q21: =IF(F21="",P21,P21*(1+F21)) -> 116.66145 | R21: =IF(G21="",Q21,Q21*(1+G21)) -> 132.30052 | S21: =IF(H21="",R21,R21*(1+H21)) -> 156.02444 | T21: =IF(I21="",S21,S21*(1+I21)) -> 160.61411 | U21: =IF(J21="",T21,T21*(1+J21)) -> 220.42746 | V21: =IF(K21="",U21,U21*(1+K21)) -> 230.44004
D22: Income: | E22: =IF(SUMIFS($C$120:$C$239,$A$120:$A$239,$A$20,$B$120:$B$239,E$11)=0,"",SUMIFS($L$120:$L$239,$A$120:$A$239,$A$20,$B$120:$B$239,E$11)) -> 0.028983463 | F22: =IF(SUMIFS($C$120:$C$239,$A$120:$A$239,$A$20,$B$120:$B$239,F$11)=0,"",SUMIFS($L$120:$L$239,$A$120:$A$239,$A$20,$B$120:$B$239,F$11)) -> 0.029396353 | G22: =IF(SUMIFS($C$120:$C$239,$A$120:$A$239,$A$20,$B$120:$B$239,G$11)=0,"",SUMIFS($L$120:$L$239,$A$120:$A$239,$A$20,$B$120:$B$239,G$11)) -> 0.019052771 | H22: =IF(SUMIFS($C$120:$C$239,$A$120:$A$239,$A$20,$B$120:$B$239,H$11)=0,"",SUMIFS($L$120:$L$239,$A$120:$A$239,$A$20,$B$120:$B$239,H$11)) -> 0.028867965 | I22: =IF(SUMIFS($C$120:$C$239,$A$120:$A$239,$A$20,$B$120:$B$239,I$11)=0,"",SUMIFS($L$120:$L$239,$A$120:$A$239,$A$20,$B$120:$B$239,I$11)) -> 0.023487242 | J22: =IF(SUMIFS($C$120:$C$239,$A$120:$A$239,$A$20,$B$120:$B$239,J$11)=0,"",SUMIFS($L$120:$L$239,$A$120:$A$239,$A$20,$B$120:$B$239,J$11)) -> 0.032661115 | K22: =IF(SUMIFS($C$120:$C$239,$A$120:$A$239,$A$20,$B$120:$B$239,K$11)=0,"",SUMIFS($L$120:$L$239,$A$120:$A$239,$A$20,$B$120:$B$239,K$11)) -> 0.029227978 | L22: =V22/O22-1 -> 0.2080897 | M22: =IF($B20=0,"",(V22/O22)^(1/$B20)-1) -> 0.027373725 | O22: 100 | P22: =IF(E22="",O22,O22*(1+E22)) -> 102.89835 | Q22: =IF(F22="",P22,P22*(1+F22)) -> 105.92318 | R22: =IF(G22="",Q22,Q22*(1+G22)) -> 107.94131 | S22: =IF(H22="",R22,R22*(1+H22)) -> 111.05736 | T22: =IF(I22="",S22,S22*(1+I22)) -> 113.66579 | U22: =IF(J22="",T22,T22*(1+J22)) -> 117.37824 | V22: =IF(K22="",U22,U22*(1+K22)) -> 120.80897
A23: Fazenda Planeste | B23: =COUNT(E23:K23) -> 7 | C23: =SUMIFS($E$120:$E$239,$A$120:$A$239,$A23,$B$120:$B$239,K$11)/1000 -> 234.55 | D23: Total: | E23: =IF(SUMIFS($C$120:$C$239,$A$120:$A$239,$A$23,$B$120:$B$239,E$11)=0,"",SUMIFS($N$120:$N$239,$A$120:$A$239,$A$23,$B$120:$B$239,E$11)) -> 0.1388264 | F23: =IF(SUMIFS($C$120:$C$239,$A$120:$A$239,$A$23,$B$120:$B$239,F$11)=0,"",SUMIFS($N$120:$N$239,$A$120:$A$239,$A$23,$B$120:$B$239,F$11)) -> 0.24151944 | G23: =IF(SUMIFS($C$120:$C$239,$A$120:$A$239,$A$23,$B$120:$B$239,G$11)=0,"",SUMIFS($N$120:$N$239,$A$120:$A$239,$A$23,$B$120:$B$239,G$11)) -> 0.25162281 | H23: =IF(SUMIFS($C$120:$C$239,$A$120:$A$239,$A$23,$B$120:$B$239,H$11)=0,"",SUMIFS($N$120:$N$239,$A$120:$A$239,$A$23,$B$120:$B$239,H$11)) -> 0.20422529 | I23: =IF(SUMIFS($C$120:$C$239,$A$120:$A$239,$A$23,$B$120:$B$239,I$11)=0,"",SUMIFS($N$120:$N$239,$A$120:$A$239,$A$23,$B$120:$B$239,I$11)) -> 0.15534186 | J23: =IF(SUMIFS($C$120:$C$239,$A$120:$A$239,$A$23,$B$120:$B$239,J$11)=0,"",SUMIFS($N$120:$N$239,$A$120:$A$239,$A$23,$B$120:$B$239,J$11)) -> 0.081968693 | K23: =IF(SUMIFS($C$120:$C$239,$A$120:$A$239,$A$23,$B$120:$B$239,K$11)=0,"",SUMIFS($N$120:$N$239,$A$120:$A$239,$A$23,$B$120:$B$239,K$11)) -> 0.058871272 | L23: =V23/O23-1 -> 1.8207243 | M23: =IF($B23=0,"",(V23/O23)^(1/$B23)-1) -> 0.15967751 | O23: 100 | P23: =IF(E23="",O23,O23*(1+E23)) -> 113.88264 | Q23: =IF(F23="",P23,P23*(1+F23)) -> 141.38751 | R23: =IF(G23="",Q23,Q23*(1+G23)) -> 176.96383 | S23: =IF(H23="",R23,R23*(1+H23)) -> 213.10433 | T23: =IF(I23="",S23,S23*(1+I23)) -> 246.20835 | U23: =IF(J23="",T23,T23*(1+J23)) -> 266.38972 | V23: =IF(K23="",U23,U23*(1+K23)) -> 282.07243
D24: Appreciation: | E24: =IF(SUMIFS($C$120:$C$239,$A$120:$A$239,$A$23,$B$120:$B$239,E$11)=0,"",SUMIFS($M$120:$M$239,$A$120:$A$239,$A$23,$B$120:$B$239,E$11)) -> 0.10552482 | F24: =IF(SUMIFS($C$120:$C$239,$A$120:$A$239,$A$23,$B$120:$B$239,F$11)=0,"",SUMIFS($M$120:$M$239,$A$120:$A$239,$A$23,$B$120:$B$239,F$11)) -> 0.20786236 | G24: =IF(SUMIFS($C$120:$C$239,$A$120:$A$239,$A$23,$B$120:$B$239,G$11)=0,"",SUMIFS($M$120:$M$239,$A$120:$A$239,$A$23,$B$120:$B$239,G$11)) -> 0.22006087 | H24: =IF(SUMIFS($C$120:$C$239,$A$120:$A$239,$A$23,$B$120:$B$239,H$11)=0,"",SUMIFS($M$120:$M$239,$A$120:$A$239,$A$23,$B$120:$B$239,H$11)) -> 0.14578765 | I24: =IF(SUMIFS($C$120:$C$239,$A$120:$A$239,$A$23,$B$120:$B$239,I$11)=0,"",SUMIFS($M$120:$M$239,$A$120:$A$239,$A$23,$B$120:$B$239,I$11)) -> 0.11730496 | J24: =IF(SUMIFS($C$120:$C$239,$A$120:$A$239,$A$23,$B$120:$B$239,J$11)=0,"",SUMIFS($M$120:$M$239,$A$120:$A$239,$A$23,$B$120:$B$239,J$11)) -> 0.043830481 | K24: =IF(SUMIFS($C$120:$C$239,$A$120:$A$239,$A$23,$B$120:$B$239,K$11)=0,"",SUMIFS($M$120:$M$239,$A$120:$A$239,$A$23,$B$120:$B$239,K$11)) -> 0.021625457 | L24: =V24/O24-1 -> 1.2241547 | M24: =IF($B23=0,"",(V24/O24)^(1/$B23)-1) -> 0.1209726 | O24: 100 | P24: =IF(E24="",O24,O24*(1+E24)) -> 110.55248 | Q24: =IF(F24="",P24,P24*(1+F24)) -> 133.53218 | R24: =IF(G24="",Q24,Q24*(1+G24)) -> 162.91739 | S24: =IF(H24="",R24,R24*(1+H24)) -> 186.66873 | T24: =IF(I24="",S24,S24*(1+I24)) -> 208.5659 | U24: =IF(J24="",T24,T24*(1+J24)) -> 217.70744 | V24: =IF(K24="",U24,U24*(1+K24)) -> 222.41547
D25: Income: | E25: =IF(SUMIFS($C$120:$C$239,$A$120:$A$239,$A$23,$B$120:$B$239,E$11)=0,"",SUMIFS($L$120:$L$239,$A$120:$A$239,$A$23,$B$120:$B$239,E$11)) -> 0.033301587 | F25: =IF(SUMIFS($C$120:$C$239,$A$120:$A$239,$A$23,$B$120:$B$239,F$11)=0,"",SUMIFS($L$120:$L$239,$A$120:$A$239,$A$23,$B$120:$B$239,F$11)) -> 0.033657084 | G25: =IF(SUMIFS($C$120:$C$239,$A$120:$A$239,$A$23,$B$120:$B$239,G$11)=0,"",SUMIFS($L$120:$L$239,$A$120:$A$239,$A$23,$B$120:$B$239,G$11)) -> 0.031561939 | H25: =IF(SUMIFS($C$120:$C$239,$A$120:$A$239,$A$23,$B$120:$B$239,H$11)=0,"",SUMIFS($L$120:$L$239,$A$120:$A$239,$A$23,$B$120:$B$239,H$11)) -> 0.058437637 | I25: =IF(SUMIFS($C$120:$C$239,$A$120:$A$239,$A$23,$B$120:$B$239,I$11)=0,"",SUMIFS($L$120:$L$239,$A$120:$A$239,$A$23,$B$120:$B$239,I$11)) -> 0.038036902 | J25: =IF(SUMIFS($C$120:$C$239,$A$120:$A$239,$A$23,$B$120:$B$239,J$11)=0,"",SUMIFS($L$120:$L$239,$A$120:$A$239,$A$23,$B$120:$B$239,J$11)) -> 0.038138211 | K25: =IF(SUMIFS($C$120:$C$239,$A$120:$A$239,$A$23,$B$120:$B$239,K$11)=0,"",SUMIFS($L$120:$L$239,$A$120:$A$239,$A$23,$B$120:$B$239,K$11)) -> 0.037245814 | L25: =V25/O25-1 -> 0.30350838 | M25: =IF($B23=0,"",(V25/O25)^(1/$B23)-1) -> 0.038591663 | O25: 100 | P25: =IF(E25="",O25,O25*(1+E25)) -> 103.33016 | Q25: =IF(F25="",P25,P25*(1+F25)) -> 106.80795 | R25: =IF(G25="",Q25,Q25*(1+G25)) -> 110.17902 | S25: =IF(H25="",R25,R25*(1+H25)) -> 116.61762 | T25: =IF(I25="",S25,S25*(1+I25)) -> 121.05339 | U25: =IF(J25="",T25,T25*(1+J25)) -> 125.67015 | V25: =IF(K25="",U25,U25*(1+K25)) -> 130.35084
A26: Fazenda Panorama | B26: =COUNT(E26:K26) -> 7 | C26: =SUMIFS($E$120:$E$239,$A$120:$A$239,$A26,$B$120:$B$239,K$11)/1000 -> 166.43 | D26: Total: | E26: =IF(SUMIFS($C$120:$C$239,$A$120:$A$239,$A$26,$B$120:$B$239,E$11)=0,"",SUMIFS($N$120:$N$239,$A$120:$A$239,$A$26,$B$120:$B$239,E$11)) -> 0.17983968 | F26: =IF(SUMIFS($C$120:$C$239,$A$120:$A$239,$A$26,$B$120:$B$239,F$11)=0,"",SUMIFS($N$120:$N$239,$A$120:$A$239,$A$26,$B$120:$B$239,F$11)) -> 0.22785267 | G26: =IF(SUMIFS($C$120:$C$239,$A$120:$A$239,$A$26,$B$120:$B$239,G$11)=0,"",SUMIFS($N$120:$N$239,$A$120:$A$239,$A$26,$B$120:$B$239,G$11)) -> 0.47422951 | H26: =IF(SUMIFS($C$120:$C$239,$A$120:$A$239,$A$26,$B$120:$B$239,H$11)=0,"",SUMIFS($N$120:$N$239,$A$120:$A$239,$A$26,$B$120:$B$239,H$11)) -> 0.20144273 | I26: =IF(SUMIFS($C$120:$C$239,$A$120:$A$239,$A$26,$B$120:$B$239,I$11)=0,"",SUMIFS($N$120:$N$239,$A$120:$A$239,$A$26,$B$120:$B$239,I$11)) -> -0.10099281 | J26: =IF(SUMIFS($C$120:$C$239,$A$120:$A$239,$A$26,$B$120:$B$239,J$11)=0,"",SUMIFS($N$120:$N$239,$A$120:$A$239,$A$26,$B$120:$B$239,J$11)) -> 0.11704545 | K26: =IF(SUMIFS($C$120:$C$239,$A$120:$A$239,$A$26,$B$120:$B$239,K$11)=0,"",SUMIFS($N$120:$N$239,$A$120:$A$239,$A$26,$B$120:$B$239,K$11)) -> 0.10567517 | L26: =V26/O26-1 -> 1.8490429 | M26: =IF($B26=0,"",(V26/O26)^(1/$B26)-1) -> 0.16133362 | O26: 100 | P26: =IF(E26="",O26,O26*(1+E26)) -> 117.98397 | Q26: =IF(F26="",P26,P26*(1+F26)) -> 144.86693 | R26: =IF(G26="",Q26,Q26*(1+G26)) -> 213.5671 | S26: =IF(H26="",R26,R26*(1+H26)) -> 256.58864 | T26: =IF(I26="",S26,S26*(1+I26)) -> 230.67503 | U26: =IF(J26="",T26,T26*(1+J26)) -> 257.6745 | V26: =IF(K26="",U26,U26*(1+K26)) -> 284.90429
D27: Appreciation: | E27: =IF(SUMIFS($C$120:$C$239,$A$120:$A$239,$A$26,$B$120:$B$239,E$11)=0,"",SUMIFS($M$120:$M$239,$A$120:$A$239,$A$26,$B$120:$B$239,E$11)) -> 0.15216348 | F27: =IF(SUMIFS($C$120:$C$239,$A$120:$A$239,$A$26,$B$120:$B$239,F$11)=0,"",SUMIFS($M$120:$M$239,$A$120:$A$239,$A$26,$B$120:$B$239,F$11)) -> 0.19373144 | G27: =IF(SUMIFS($C$120:$C$239,$A$120:$A$239,$A$26,$B$120:$B$239,G$11)=0,"",SUMIFS($M$120:$M$239,$A$120:$A$239,$A$26,$B$120:$B$239,G$11)) -> 0.4353105 | H27: =IF(SUMIFS($C$120:$C$239,$A$120:$A$239,$A$26,$B$120:$B$239,H$11)=0,"",SUMIFS($M$120:$M$239,$A$120:$A$239,$A$26,$B$120:$B$239,H$11)) -> 0.14546423 | I27: =IF(SUMIFS($C$120:$C$239,$A$120:$A$239,$A$26,$B$120:$B$239,I$11)=0,"",SUMIFS($M$120:$M$239,$A$120:$A$239,$A$26,$B$120:$B$239,I$11)) -> -0.13359307 | J27: =IF(SUMIFS($C$120:$C$239,$A$120:$A$239,$A$26,$B$120:$B$239,J$11)=0,"",SUMIFS($M$120:$M$239,$A$120:$A$239,$A$26,$B$120:$B$239,J$11)) -> 0.076416947 | K27: =IF(SUMIFS($C$120:$C$239,$A$120:$A$239,$A$26,$B$120:$B$239,K$11)=0,"",SUMIFS($M$120:$M$239,$A$120:$A$239,$A$26,$B$120:$B$239,K$11)) -> 0.0657575 | L27: =V27/O27-1 -> 1.247548 | M27: =IF($B26=0,"",(V27/O27)^(1/$B26)-1) -> 0.12264937 | O27: 100 | P27: =IF(E27="",O27,O27*(1+E27)) -> 115.21635 | Q27: =IF(F27="",P27,P27*(1+F27)) -> 137.53738 | R27: =IF(G27="",Q27,Q27*(1+G27)) -> 197.40884 | S27: =IF(H27="",R27,R27*(1+H27)) -> 226.12476 | T27: =IF(I27="",S27,S27*(1+I27)) -> 195.91606 | U27: =IF(J27="",T27,T27*(1+J27)) -> 210.88737 | V27: =IF(K27="",U27,U27*(1+K27)) -> 224.7548
D28: Income: | E28: =IF(SUMIFS($C$120:$C$239,$A$120:$A$239,$A$26,$B$120:$B$239,E$11)=0,"",SUMIFS($L$120:$L$239,$A$120:$A$239,$A$26,$B$120:$B$239,E$11)) -> 0.0276762 | F28: =IF(SUMIFS($C$120:$C$239,$A$120:$A$239,$A$26,$B$120:$B$239,F$11)=0,"",SUMIFS($L$120:$L$239,$A$120:$A$239,$A$26,$B$120:$B$239,F$11)) -> 0.034121229 | G28: =IF(SUMIFS($C$120:$C$239,$A$120:$A$239,$A$26,$B$120:$B$239,G$11)=0,"",SUMIFS($L$120:$L$239,$A$120:$A$239,$A$26,$B$120:$B$239,G$11)) -> 0.038919008 | H28: =IF(SUMIFS($C$120:$C$239,$A$120:$A$239,$A$26,$B$120:$B$239,H$11)=0,"",SUMIFS($L$120:$L$239,$A$120:$A$239,$A$26,$B$120:$B$239,H$11)) -> 0.055978503 | I28: =IF(SUMIFS($C$120:$C$239,$A$120:$A$239,$A$26,$B$120:$B$239,I$11)=0,"",SUMIFS($L$120:$L$239,$A$120:$A$239,$A$26,$B$120:$B$239,I$11)) -> 0.032600252 | J28: =IF(SUMIFS($C$120:$C$239,$A$120:$A$239,$A$26,$B$120:$B$239,J$11)=0,"",SUMIFS($L$120:$L$239,$A$120:$A$239,$A$26,$B$120:$B$239,J$11)) -> 0.040628507 | K28: =IF(SUMIFS($C$120:$C$239,$A$120:$A$239,$A$26,$B$120:$B$239,K$11)=0,"",SUMIFS($L$120:$L$239,$A$120:$A$239,$A$26,$B$120:$B$239,K$11)) -> 0.039917673 | L28: =V28/O28-1 -> 0.30284103 | M28: =IF($B26=0,"",(V28/O28)^(1/$B26)-1) -> 0.038515687 | O28: 100 | P28: =IF(E28="",O28,O28*(1+E28)) -> 102.76762 | Q28: =IF(F28="",P28,P28*(1+F28)) -> 106.27418 | R28: =IF(G28="",Q28,Q28*(1+G28)) -> 110.41026 | S28: =IF(H28="",R28,R28*(1+H28)) -> 116.59086 | T28: =IF(I28="",S28,S28*(1+I28)) -> 120.39176 | U28: =IF(J28="",T28,T28*(1+J28)) -> 125.28309 | V28: =IF(K28="",U28,U28*(1+K28)) -> 130.2841
A29: Fazenda Piratini | B29: =COUNT(E29:K29) -> 7 | C29: =SUMIFS($E$120:$E$239,$A$120:$A$239,$A29,$B$120:$B$239,K$11)/1000 -> 222.86 | D29: Total: | E29: =IF(SUMIFS($C$120:$C$239,$A$120:$A$239,$A$29,$B$120:$B$239,E$11)=0,"",SUMIFS($N$120:$N$239,$A$120:$A$239,$A$29,$B$120:$B$239,E$11)) -> 0.60964019 | F29: =IF(SUMIFS($C$120:$C$239,$A$120:$A$239,$A$29,$B$120:$B$239,F$11)=0,"",SUMIFS($N$120:$N$239,$A$120:$A$239,$A$29,$B$120:$B$239,F$11)) -> -0.13291056 | G29: =IF(SUMIFS($C$120:$C$239,$A$120:$A$239,$A$29,$B$120:$B$239,G$11)=0,"",SUMIFS($N$120:$N$239,$A$120:$A$239,$A$29,$B$120:$B$239,G$11)) -> 0.46341093 | H29: =IF(SUMIFS($C$120:$C$239,$A$120:$A$239,$A$29,$B$120:$B$239,H$11)=0,"",SUMIFS($N$120:$N$239,$A$120:$A$239,$A$29,$B$120:$B$239,H$11)) -> 0.17373164 | I29: =IF(SUMIFS($C$120:$C$239,$A$120:$A$239,$A$29,$B$120:$B$239,I$11)=0,"",SUMIFS($N$120:$N$239,$A$120:$A$239,$A$29,$B$120:$B$239,I$11)) -> 0.34529484 | J29: =IF(SUMIFS($C$120:$C$239,$A$120:$A$239,$A$29,$B$120:$B$239,J$11)=0,"",SUMIFS($N$120:$N$239,$A$120:$A$239,$A$29,$B$120:$B$239,J$11)) -> 0.14326621 | K29: =IF(SUMIFS($C$120:$C$239,$A$120:$A$239,$A$29,$B$120:$B$239,K$11)=0,"",SUMIFS($N$120:$N$239,$A$120:$A$239,$A$29,$B$120:$B$239,K$11)) -> 0.1438427 | L29: =V29/O29-1 -> 3.2175376 | M29: =IF($B29=0,"",(V29/O29)^(1/$B29)-1) -> 0.22827083 | O29: 100 | P29: =IF(E29="",O29,O29*(1+E29)) -> 160.96402 | Q29: =IF(F29="",P29,P29*(1+F29)) -> 139.5702 | R29: =IF(G29="",Q29,Q29*(1+G29)) -> 204.24856 | S29: =IF(H29="",R29,R29*(1+H29)) -> 239.733 | T29: =IF(I29="",S29,S29*(1+I29)) -> 322.51156 | U29: =IF(J29="",T29,T29*(1+J29)) -> 368.71657 | V29: =IF(K29="",U29,U29*(1+K29)) -> 421.75376
D30: Appreciation: | E30: =IF(SUMIFS($C$120:$C$239,$A$120:$A$239,$A$29,$B$120:$B$239,E$11)=0,"",SUMIFS($M$120:$M$239,$A$120:$A$239,$A$29,$B$120:$B$239,E$11)) -> 0.60964019 | F30: =IF(SUMIFS($C$120:$C$239,$A$120:$A$239,$A$29,$B$120:$B$239,F$11)=0,"",SUMIFS($M$120:$M$239,$A$120:$A$239,$A$29,$B$120:$B$239,F$11)) -> -0.13771965 | G30: =IF(SUMIFS($C$120:$C$239,$A$120:$A$239,$A$29,$B$120:$B$239,G$11)=0,"",SUMIFS($M$120:$M$239,$A$120:$A$239,$A$29,$B$120:$B$239,G$11)) -> 0.43623547 | H30: =IF(SUMIFS($C$120:$C$239,$A$120:$A$239,$A$29,$B$120:$B$239,H$11)=0,"",SUMIFS($M$120:$M$239,$A$120:$A$239,$A$29,$B$120:$B$239,H$11)) -> 0.14366754 | I30: =IF(SUMIFS($C$120:$C$239,$A$120:$A$239,$A$29,$B$120:$B$239,I$11)=0,"",SUMIFS($M$120:$M$239,$A$120:$A$239,$A$29,$B$120:$B$239,I$11)) -> 0.32397446 | J30: =IF(SUMIFS($C$120:$C$239,$A$120:$A$239,$A$29,$B$120:$B$239,J$11)=0,"",SUMIFS($M$120:$M$239,$A$120:$A$239,$A$29,$B$120:$B$239,J$11)) -> 0.12475792 | K30: =IF(SUMIFS($C$120:$C$239,$A$120:$A$239,$A$29,$B$120:$B$239,K$11)=0,"",SUMIFS($M$120:$M$239,$A$120:$A$239,$A$29,$B$120:$B$239,K$11)) -> 0.12550341 | L30: =V30/O30-1 -> 2.8210984 | M30: =IF($B29=0,"",(V30/O30)^(1/$B29)-1) -> 0.2110714 | O30: 100 | P30: =IF(E30="",O30,O30*(1+E30)) -> 160.96402 | Q30: =IF(F30="",P30,P30*(1+F30)) -> 138.79611 | R30: =IF(G30="",Q30,Q30*(1+G30)) -> 199.3439 | S30: =IF(H30="",R30,R30*(1+H30)) -> 227.98315 | T30: =IF(I30="",S30,S30*(1+I30)) -> 301.84386 | U30: =IF(J30="",T30,T30*(1+J30)) -> 339.50127 | V30: =IF(K30="",U30,U30*(1+K30)) -> 382.10984
D31: Income: | E31: =IF(SUMIFS($C$120:$C$239,$A$120:$A$239,$A$29,$B$120:$B$239,E$11)=0,"",SUMIFS($L$120:$L$239,$A$120:$A$239,$A$29,$B$120:$B$239,E$11)) -> 0 | F31: =IF(SUMIFS($C$120:$C$239,$A$120:$A$239,$A$29,$B$120:$B$239,F$11)=0,"",SUMIFS($L$120:$L$239,$A$120:$A$239,$A$29,$B$120:$B$239,F$11)) -> 0.0048090897 | G31: =IF(SUMIFS($C$120:$C$239,$A$120:$A$239,$A$29,$B$120:$B$239,G$11)=0,"",SUMIFS($L$120:$L$239,$A$120:$A$239,$A$29,$B$120:$B$239,G$11)) -> 0.027175456 | H31: =IF(SUMIFS($C$120:$C$239,$A$120:$A$239,$A$29,$B$120:$B$239,H$11)=0,"",SUMIFS($L$120:$L$239,$A$120:$A$239,$A$29,$B$120:$B$239,H$11)) -> 0.030064101 | I31: =IF(SUMIFS($C$120:$C$239,$A$120:$A$239,$A$29,$B$120:$B$239,I$11)=0,"",SUMIFS($L$120:$L$239,$A$120:$A$239,$A$29,$B$120:$B$239,I$11)) -> 0.021320381 | J31: =IF(SUMIFS($C$120:$C$239,$A$120:$A$239,$A$29,$B$120:$B$239,J$11)=0,"",SUMIFS($L$120:$L$239,$A$120:$A$239,$A$29,$B$120:$B$239,J$11)) -> 0.018508294 | K31: =IF(SUMIFS($C$120:$C$239,$A$120:$A$239,$A$29,$B$120:$B$239,K$11)=0,"",SUMIFS($L$120:$L$239,$A$120:$A$239,$A$29,$B$120:$B$239,K$11)) -> 0.018339282 | L31: =V31/O31-1 -> 0.12618958 | M31: =IF($B29=0,"",(V31/O31)^(1/$B29)-1) -> 0.017122057 | O31: 100 | P31: =IF(E31="",O31,O31*(1+E31)) -> 100 | Q31: =IF(F31="",P31,P31*(1+F31)) -> 100.48091 | R31: =IF(G31="",Q31,Q31*(1+G31)) -> 103.21152 | S31: =IF(H31="",R31,R31*(1+H31)) -> 106.31449 | T31: =IF(I31="",S31,S31*(1+I31)) -> 108.58115 | U31: =IF(J31="",T31,T31*(1+J31)) -> 110.5908 | V31: =IF(K31="",U31,U31*(1+K31)) -> 112.61896
A32: Fazenda Palmares | B32: =COUNT(E32:K32) -> 6 | C32: =SUMIFS($E$120:$E$239,$A$120:$A$239,$A32,$B$120:$B$239,K$11)/1000 -> 187.6 | D32: Total: | E32: =IF(SUMIFS($C$120:$C$239,$A$120:$A$239,$A$32,$B$120:$B$239,E$11)=0,"",SUMIFS($N$120:$N$239,$A$120:$A$239,$A$32,$B$120:$B$239,E$11)) | F32: =IF(SUMIFS($C$120:$C$239,$A$120:$A$239,$A$32,$B$120:$B$239,F$11)=0,"",SUMIFS($N$120:$N$239,$A$120:$A$239,$A$32,$B$120:$B$239,F$11)) -> 1.2146166 | G32: =IF(SUMIFS($C$120:$C$239,$A$120:$A$239,$A$32,$B$120:$B$239,G$11)=0,"",SUMIFS($N$120:$N$239,$A$120:$A$239,$A$32,$B$120:$B$239,G$11)) -> 0.96345292 | H32: =IF(SUMIFS($C$120:$C$239,$A$120:$A$239,$A$32,$B$120:$B$239,H$11)=0,"",SUMIFS($N$120:$N$239,$A$120:$A$239,$A$32,$B$120:$B$239,H$11)) -> 0.32699059 | I32: =IF(SUMIFS($C$120:$C$239,$A$120:$A$239,$A$32,$B$120:$B$239,I$11)=0,"",SUMIFS($N$120:$N$239,$A$120:$A$239,$A$32,$B$120:$B$239,I$11)) -> 0.79348901 | J32: =IF(SUMIFS($C$120:$C$239,$A$120:$A$239,$A$32,$B$120:$B$239,J$11)=0,"",SUMIFS($N$120:$N$239,$A$120:$A$239,$A$32,$B$120:$B$239,J$11)) -> 0.10342955 | K32: =IF(SUMIFS($C$120:$C$239,$A$120:$A$239,$A$32,$B$120:$B$239,K$11)=0,"",SUMIFS($N$120:$N$239,$A$120:$A$239,$A$32,$B$120:$B$239,K$11)) -> 0.082199168 | L32: =V32/O32-1 -> 11.357693 | M32: =IF($B32=0,"",(V32/O32)^(1/$B32)-1) -> 0.52051101 | O32: 100 | P32: =IF(E32="",O32,O32*(1+E32)) -> 100 | Q32: =IF(F32="",P32,P32*(1+F32)) -> 221.46166 | R32: =IF(G32="",Q32,Q32*(1+G32)) -> 434.82954 | S32: =IF(H32="",R32,R32*(1+H32)) -> 577.01471 | T32: =IF(I32="",S32,S32*(1+I32)) -> 1034.8695 | U32: =IF(J32="",T32,T32*(1+J32)) -> 1141.9056 | V32: =IF(K32="",U32,U32*(1+K32)) -> 1235.7693
D33: Appreciation: | E33: =IF(SUMIFS($C$120:$C$239,$A$120:$A$239,$A$32,$B$120:$B$239,E$11)=0,"",SUMIFS($M$120:$M$239,$A$120:$A$239,$A$32,$B$120:$B$239,E$11)) | F33: =IF(SUMIFS($C$120:$C$239,$A$120:$A$239,$A$32,$B$120:$B$239,F$11)=0,"",SUMIFS($M$120:$M$239,$A$120:$A$239,$A$32,$B$120:$B$239,F$11)) -> 1.0951096 | G33: =IF(SUMIFS($C$120:$C$239,$A$120:$A$239,$A$32,$B$120:$B$239,G$11)=0,"",SUMIFS($M$120:$M$239,$A$120:$A$239,$A$32,$B$120:$B$239,G$11)) -> 0.85667463 | H33: =IF(SUMIFS($C$120:$C$239,$A$120:$A$239,$A$32,$B$120:$B$239,H$11)=0,"",SUMIFS($M$120:$M$239,$A$120:$A$239,$A$32,$B$120:$B$239,H$11)) -> 0.22826372 | I33: =IF(SUMIFS($C$120:$C$239,$A$120:$A$239,$A$32,$B$120:$B$239,I$11)=0,"",SUMIFS($M$120:$M$239,$A$120:$A$239,$A$32,$B$120:$B$239,I$11)) -> 0.71930225 | J33: =IF(SUMIFS($C$120:$C$239,$A$120:$A$239,$A$32,$B$120:$B$239,J$11)=0,"",SUMIFS($M$120:$M$239,$A$120:$A$239,$A$32,$B$120:$B$239,J$11)) -> 0.058513056 | K33: =IF(SUMIFS($C$120:$C$239,$A$120:$A$239,$A$32,$B$120:$B$239,K$11)=0,"",SUMIFS($M$120:$M$239,$A$120:$A$239,$A$32,$B$120:$B$239,K$11)) -> 0.025298965 | L33: =V33/O33-1 -> 7.9152422 | M33: =IF($B32=0,"",(V33/O33)^(1/$B32)-1) -> 0.4399769 | O33: 100 | P33: =IF(E33="",O33,O33*(1+E33)) -> 100 | Q33: =IF(F33="",P33,P33*(1+F33)) -> 209.51096 | R33: =IF(G33="",Q33,Q33*(1+G33)) -> 388.99369 | S33: =IF(H33="",R33,R33*(1+H33)) -> 477.78684 | T33: =IF(I33="",S33,S33*(1+I33)) -> 821.45998 | U33: =IF(J33="",T33,T33*(1+J33)) -> 869.52611 | V33: =IF(K33="",U33,U33*(1+K33)) -> 891.52422
D34: Income: | E34: =IF(SUMIFS($C$120:$C$239,$A$120:$A$239,$A$32,$B$120:$B$239,E$11)=0,"",SUMIFS($L$120:$L$239,$A$120:$A$239,$A$32,$B$120:$B$239,E$11)) | F34: =IF(SUMIFS($C$120:$C$239,$A$120:$A$239,$A$32,$B$120:$B$239,F$11)=0,"",SUMIFS($L$120:$L$239,$A$120:$A$239,$A$32,$B$120:$B$239,F$11)) -> 0.11950698 | G34: =IF(SUMIFS($C$120:$C$239,$A$120:$A$239,$A$32,$B$120:$B$239,G$11)=0,"",SUMIFS($L$120:$L$239,$A$120:$A$239,$A$32,$B$120:$B$239,G$11)) -> 0.10677828 | H34: =IF(SUMIFS($C$120:$C$239,$A$120:$A$239,$A$32,$B$120:$B$239,H$11)=0,"",SUMIFS($L$120:$L$239,$A$120:$A$239,$A$32,$B$120:$B$239,H$11)) -> 0.098726871 | I34: =IF(SUMIFS($C$120:$C$239,$A$120:$A$239,$A$32,$B$120:$B$239,I$11)=0,"",SUMIFS($L$120:$L$239,$A$120:$A$239,$A$32,$B$120:$B$239,I$11)) -> 0.07418676 | J34: =IF(SUMIFS($C$120:$C$239,$A$120:$A$239,$A$32,$B$120:$B$239,J$11)=0,"",SUMIFS($L$120:$L$239,$A$120:$A$239,$A$32,$B$120:$B$239,J$11)) -> 0.04491649 | K34: =IF(SUMIFS($C$120:$C$239,$A$120:$A$239,$A$32,$B$120:$B$239,K$11)=0,"",SUMIFS($L$120:$L$239,$A$120:$A$239,$A$32,$B$120:$B$239,K$11)) -> 0.056900203 | L34: =V34/O34-1 -> 0.61500005 | M34: =IF($B32=0,"",(V34/O34)^(1/$B32)-1) -> 0.083167007 | O34: 100 | P34: =IF(E34="",O34,O34*(1+E34)) -> 100 | Q34: =IF(F34="",P34,P34*(1+F34)) -> 111.9507 | R34: =IF(G34="",Q34,Q34*(1+G34)) -> 123.9046 | S34: =IF(H34="",R34,R34*(1+H34)) -> 136.13731 | T34: =IF(I34="",S34,S34*(1+I34)) -> 146.2369 | U34: =IF(J34="",T34,T34*(1+J34)) -> 152.80535 | V34: =IF(K34="",U34,U34*(1+K34)) -> 161.5
A35: Fazenda Parnaíba | B35: =COUNT(E35:K35) -> 7 | C35: =SUMIFS($E$120:$E$239,$A$120:$A$239,$A35,$B$120:$B$239,K$11)/1000 -> 412.09 | D35: Total: | E35: =IF(SUMIFS($C$120:$C$239,$A$120:$A$239,$A$35,$B$120:$B$239,E$11)=0,"",SUMIFS($N$120:$N$239,$A$120:$A$239,$A$35,$B$120:$B$239,E$11)) -> 0.32356696 | F35: =IF(SUMIFS($C$120:$C$239,$A$120:$A$239,$A$35,$B$120:$B$239,F$11)=0,"",SUMIFS($N$120:$N$239,$A$120:$A$239,$A$35,$B$120:$B$239,F$11)) -> -0.036170726 | G35: =IF(SUMIFS($C$120:$C$239,$A$120:$A$239,$A$35,$B$120:$B$239,G$11)=0,"",SUMIFS($N$120:$N$239,$A$120:$A$239,$A$35,$B$120:$B$239,G$11)) -> 0.11368526 | H35: =IF(SUMIFS($C$120:$C$239,$A$120:$A$239,$A$35,$B$120:$B$239,H$11)=0,"",SUMIFS($N$120:$N$239,$A$120:$A$239,$A$35,$B$120:$B$239,H$11)) -> 0.17778676 | I35: =IF(SUMIFS($C$120:$C$239,$A$120:$A$239,$A$35,$B$120:$B$239,I$11)=0,"",SUMIFS($N$120:$N$239,$A$120:$A$239,$A$35,$B$120:$B$239,I$11)) -> 0.16488899 | J35: =IF(SUMIFS($C$120:$C$239,$A$120:$A$239,$A$35,$B$120:$B$239,J$11)=0,"",SUMIFS($N$120:$N$239,$A$120:$A$239,$A$35,$B$120:$B$239,J$11)) -> 0.13684433 | K35: =IF(SUMIFS($C$120:$C$239,$A$120:$A$239,$A$35,$B$120:$B$239,K$11)=0,"",SUMIFS($N$120:$N$239,$A$120:$A$239,$A$35,$B$120:$B$239,K$11)) -> 0.1881148 | L35: =V35/O35-1 -> 1.6328076 | M35: =IF($B35=0,"",(V35/O35)^(1/$B35)-1) -> 0.14831192 | O35: 100 | P35: =IF(E35="",O35,O35*(1+E35)) -> 132.3567 | Q35: =IF(F35="",P35,P35*(1+F35)) -> 127.56926 | R35: =IF(G35="",Q35,Q35*(1+G35)) -> 142.072 | S35: =IF(H35="",R35,R35*(1+H35)) -> 167.33052 | T35: =IF(I35="",S35,S35*(1+I35)) -> 194.92149 | U35: =IF(J35="",T35,T35*(1+J35)) -> 221.59539 | V35: =IF(K35="",U35,U35*(1+K35)) -> 263.28076
D36: Appreciation: | E36: =IF(SUMIFS($C$120:$C$239,$A$120:$A$239,$A$35,$B$120:$B$239,E$11)=0,"",SUMIFS($M$120:$M$239,$A$120:$A$239,$A$35,$B$120:$B$239,E$11)) -> 0.32356696 | F36: =IF(SUMIFS($C$120:$C$239,$A$120:$A$239,$A$35,$B$120:$B$239,F$11)=0,"",SUMIFS($M$120:$M$239,$A$120:$A$239,$A$35,$B$120:$B$239,F$11)) -> -0.036170726 | G36: =IF(SUMIFS($C$120:$C$239,$A$120:$A$239,$A$35,$B$120:$B$239,G$11)=0,"",SUMIFS($M$120:$M$239,$A$120:$A$239,$A$35,$B$120:$B$239,G$11)) -> 0.11368526 | H36: =IF(SUMIFS($C$120:$C$239,$A$120:$A$239,$A$35,$B$120:$B$239,H$11)=0,"",SUMIFS($M$120:$M$239,$A$120:$A$239,$A$35,$B$120:$B$239,H$11)) -> 0.17778676 | I36: =IF(SUMIFS($C$120:$C$239,$A$120:$A$239,$A$35,$B$120:$B$239,I$11)=0,"",SUMIFS($M$120:$M$239,$A$120:$A$239,$A$35,$B$120:$B$239,I$11)) -> 0.16488899 | J36: =IF(SUMIFS($C$120:$C$239,$A$120:$A$239,$A$35,$B$120:$B$239,J$11)=0,"",SUMIFS($M$120:$M$239,$A$120:$A$239,$A$35,$B$120:$B$239,J$11)) -> 0.13634972 | K36: =IF(SUMIFS($C$120:$C$239,$A$120:$A$239,$A$35,$B$120:$B$239,K$11)=0,"",SUMIFS($M$120:$M$239,$A$120:$A$239,$A$35,$B$120:$B$239,K$11)) -> 0.18765647 | L36: =V36/O36-1 -> 1.6306469 | M36: =IF($B35=0,"",(V36/O36)^(1/$B35)-1) -> 0.14817725 | O36: 100 | P36: =IF(E36="",O36,O36*(1+E36)) -> 132.3567 | Q36: =IF(F36="",P36,P36*(1+F36)) -> 127.56926 | R36: =IF(G36="",Q36,Q36*(1+G36)) -> 142.072 | S36: =IF(H36="",R36,R36*(1+H36)) -> 167.33052 | T36: =IF(I36="",S36,S36*(1+I36)) -> 194.92149 | U36: =IF(J36="",T36,T36*(1+J36)) -> 221.49898 | V36: =IF(K36="",U36,U36*(1+K36)) -> 263.06469
D37: Income: | E37: =IF(SUMIFS($C$120:$C$239,$A$120:$A$239,$A$35,$B$120:$B$239,E$11)=0,"",SUMIFS($L$120:$L$239,$A$120:$A$239,$A$35,$B$120:$B$239,E$11)) -> 0 | F37: =IF(SUMIFS($C$120:$C$239,$A$120:$A$239,$A$35,$B$120:$B$239,F$11)=0,"",SUMIFS($L$120:$L$239,$A$120:$A$239,$A$35,$B$120:$B$239,F$11)) -> 0 | G37: =IF(SUMIFS($C$120:$C$239,$A$120:$A$239,$A$35,$B$120:$B$239,G$11)=0,"",SUMIFS($L$120:$L$239,$A$120:$A$239,$A$35,$B$120:$B$239,G$11)) -> 0 | H37: =IF(SUMIFS($C$120:$C$239,$A$120:$A$239,$A$35,$B$120:$B$239,H$11)=0,"",SUMIFS($L$120:$L$239,$A$120:$A$239,$A$35,$B$120:$B$239,H$11)) -> 0 | I37: =IF(SUMIFS($C$120:$C$239,$A$120:$A$239,$A$35,$B$120:$B$239,I$11)=0,"",SUMIFS($L$120:$L$239,$A$120:$A$239,$A$35,$B$120:$B$239,I$11)) -> 0 | J37: =IF(SUMIFS($C$120:$C$239,$A$120:$A$239,$A$35,$B$120:$B$239,J$11)=0,"",SUMIFS($L$120:$L$239,$A$120:$A$239,$A$35,$B$120:$B$239,J$11)) -> 0.00049461411 | K37: =IF(SUMIFS($C$120:$C$239,$A$120:$A$239,$A$35,$B$120:$B$239,K$11)=0,"",SUMIFS($L$120:$L$239,$A$120:$A$239,$A$35,$B$120:$B$239,K$11)) -> 0.00045833147 | L37: =V37/O37-1 -> 0.00095317228 | M37: =IF($B35=0,"",(V37/O37)^(1/$B35)-1) -> 0.00013611188 | O37: 100 | P37: =IF(E37="",O37,O37*(1+E37)) -> 100 | Q37: =IF(F37="",P37,P37*(1+F37)) -> 100 | R37: =IF(G37="",Q37,Q37*(1+G37)) -> 100 | S37: =IF(H37="",R37,R37*(1+H37)) -> 100 | T37: =IF(I37="",S37,S37*(1+I37)) -> 100 | U37: =IF(J37="",T37,T37*(1+J37)) -> 100.04946 | V37: =IF(K37="",U37,U37*(1+K37)) -> 100.09532
A38: Fazenda Paiaguás | B38: =COUNT(E38:K38) -> 7 | C38: =SUMIFS($E$120:$E$239,$A$120:$A$239,$A38,$B$120:$B$239,K$11)/1000 -> 450.91 | D38: Total: | E38: =IF(SUMIFS($C$120:$C$239,$A$120:$A$239,$A$38,$B$120:$B$239,E$11)=0,"",SUMIFS($N$120:$N$239,$A$120:$A$239,$A$38,$B$120:$B$239,E$11)) -> 0.24713733 | F38: =IF(SUMIFS($C$120:$C$239,$A$120:$A$239,$A$38,$B$120:$B$239,F$11)=0,"",SUMIFS($N$120:$N$239,$A$120:$A$239,$A$38,$B$120:$B$239,F$11)) -> -0.047032534 | G38: =IF(SUMIFS($C$120:$C$239,$A$120:$A$239,$A$38,$B$120:$B$239,G$11)=0,"",SUMIFS($N$120:$N$239,$A$120:$A$239,$A$38,$B$120:$B$239,G$11)) -> 0.16812871 | H38: =IF(SUMIFS($C$120:$C$239,$A$120:$A$239,$A$38,$B$120:$B$239,H$11)=0,"",SUMIFS($N$120:$N$239,$A$120:$A$239,$A$38,$B$120:$B$239,H$11)) -> 0.073691236 | I38: =IF(SUMIFS($C$120:$C$239,$A$120:$A$239,$A$38,$B$120:$B$239,I$11)=0,"",SUMIFS($N$120:$N$239,$A$120:$A$239,$A$38,$B$120:$B$239,I$11)) -> 0.058349331 | J38: =IF(SUMIFS($C$120:$C$239,$A$120:$A$239,$A$38,$B$120:$B$239,J$11)=0,"",SUMIFS($N$120:$N$239,$A$120:$A$239,$A$38,$B$120:$B$239,J$11)) -> 0.47106847 | K38: =IF(SUMIFS($C$120:$C$239,$A$120:$A$239,$A$38,$B$120:$B$239,K$11)=0,"",SUMIFS($N$120:$N$239,$A$120:$A$239,$A$38,$B$120:$B$239,K$11)) -> 0.11680676 | L38: =V38/O38-1 -> 1.5918056 | M38: =IF($B38=0,"",(V38/O38)^(1/$B38)-1) -> 0.14573996 | O38: 100 | P38: =IF(E38="",O38,O38*(1+E38)) -> 124.71373 | Q38: =IF(F38="",P38,P38*(1+F38)) -> 118.84813 | R38: =IF(G38="",Q38,Q38*(1+G38)) -> 138.82991 | S38: =IF(H38="",R38,R38*(1+H38)) -> 149.06046 | T38: =IF(I38="",S38,S38*(1+I38)) -> 157.75804 | U38: =IF(J38="",T38,T38*(1+J38)) -> 232.07288 | V38: =IF(K38="",U38,U38*(1+K38)) -> 259.18056
D39: Appreciation: | E39: =IF(SUMIFS($C$120:$C$239,$A$120:$A$239,$A$38,$B$120:$B$239,E$11)=0,"",SUMIFS($M$120:$M$239,$A$120:$A$239,$A$38,$B$120:$B$239,E$11)) -> 0.21459467 | F39: =IF(SUMIFS($C$120:$C$239,$A$120:$A$239,$A$38,$B$120:$B$239,F$11)=0,"",SUMIFS($M$120:$M$239,$A$120:$A$239,$A$38,$B$120:$B$239,F$11)) -> -0.080957983 | G39: =IF(SUMIFS($C$120:$C$239,$A$120:$A$239,$A$38,$B$120:$B$239,G$11)=0,"",SUMIFS($M$120:$M$239,$A$120:$A$239,$A$38,$B$120:$B$239,G$11)) -> 0.14751823 | H39: =IF(SUMIFS($C$120:$C$239,$A$120:$A$239,$A$38,$B$120:$B$239,H$11)=0,"",SUMIFS($M$120:$M$239,$A$120:$A$239,$A$38,$B$120:$B$239,H$11)) -> 0.040044445 | I39: =IF(SUMIFS($C$120:$C$239,$A$120:$A$239,$A$38,$B$120:$B$239,I$11)=0,"",SUMIFS($M$120:$M$239,$A$120:$A$239,$A$38,$B$120:$B$239,I$11)) -> 0.028035767 | J39: =IF(SUMIFS($C$120:$C$239,$A$120:$A$239,$A$38,$B$120:$B$239,J$11)=0,"",SUMIFS($M$120:$M$239,$A$120:$A$239,$A$38,$B$120:$B$239,J$11)) -> 0.41902609 | K39: =IF(SUMIFS($C$120:$C$239,$A$120:$A$239,$A$38,$B$120:$B$239,K$11)=0,"",SUMIFS($M$120:$M$239,$A$120:$A$239,$A$38,$B$120:$B$239,K$11)) -> 0.073732932 | L39: =V39/O39-1 -> 1.0867629 | M39: =IF($B38=0,"",(V39/O39)^(1/$B38)-1) -> 0.11080804 | O39: 100 | P39: =IF(E39="",O39,O39*(1+E39)) -> 121.45947 | Q39: =IF(F39="",P39,P39*(1+F39)) -> 111.62635 | R39: =IF(G39="",Q39,Q39*(1+G39)) -> 128.09328 | S39: =IF(H39="",R39,R39*(1+H39)) -> 133.2227 | T39: =IF(I39="",S39,S39*(1+I39)) -> 136.9577 | U39: =IF(J39="",T39,T39*(1+J39)) -> 194.34655 | V39: =IF(K39="",U39,U39*(1+K39)) -> 208.67629
D40: Income: | E40: =IF(SUMIFS($C$120:$C$239,$A$120:$A$239,$A$38,$B$120:$B$239,E$11)=0,"",SUMIFS($L$120:$L$239,$A$120:$A$239,$A$38,$B$120:$B$239,E$11)) -> 0.032542654 | F40: =IF(SUMIFS($C$120:$C$239,$A$120:$A$239,$A$38,$B$120:$B$239,F$11)=0,"",SUMIFS($L$120:$L$239,$A$120:$A$239,$A$38,$B$120:$B$239,F$11)) -> 0.033925449 | G40: =IF(SUMIFS($C$120:$C$239,$A$120:$A$239,$A$38,$B$120:$B$239,G$11)=0,"",SUMIFS($L$120:$L$239,$A$120:$A$239,$A$38,$B$120:$B$239,G$11)) -> 0.020610483 | H40: =IF(SUMIFS($C$120:$C$239,$A$120:$A$239,$A$38,$B$120:$B$239,H$11)=0,"",SUMIFS($L$120:$L$239,$A$120:$A$239,$A$38,$B$120:$B$239,H$11)) -> 0.033646791 | I40: =IF(SUMIFS($C$120:$C$239,$A$120:$A$239,$A$38,$B$120:$B$239,I$11)=0,"",SUMIFS($L$120:$L$239,$A$120:$A$239,$A$38,$B$120:$B$239,I$11)) -> 0.030313564 | J40: =IF(SUMIFS($C$120:$C$239,$A$120:$A$239,$A$38,$B$120:$B$239,J$11)=0,"",SUMIFS($L$120:$L$239,$A$120:$A$239,$A$38,$B$120:$B$239,J$11)) -> 0.052042387 | K40: =IF(SUMIFS($C$120:$C$239,$A$120:$A$239,$A$38,$B$120:$B$239,K$11)=0,"",SUMIFS($L$120:$L$239,$A$120:$A$239,$A$38,$B$120:$B$239,K$11)) -> 0.043073829 | L40: =V40/O40-1 -> 0.27334802 | M40: =IF($B38=0,"",(V40/O40)^(1/$B38)-1) -> 0.03512416 | O40: 100 | P40: =IF(E40="",O40,O40*(1+E40)) -> 103.25427 | Q40: =IF(F40="",P40,P40*(1+F40)) -> 106.75721 | R40: =IF(G40="",Q40,Q40*(1+G40)) -> 108.95753 | S40: =IF(H40="",R40,R40*(1+H40)) -> 112.6236 | T40: =IF(I40="",S40,S40*(1+I40)) -> 116.03762 | U40: =IF(J40="",T40,T40*(1+J40)) -> 122.0765 | V40: =IF(K40="",U40,U40*(1+K40)) -> 127.3348
A41: Fazenda Pejuçara | B41: =COUNT(E41:K41) -> 2 | C41: =SUMIFS($E$120:$E$239,$A$120:$A$239,$A41,$B$120:$B$239,K$11)/1000 -> 0 | D41: Total: | E41: =IF(SUMIFS($C$120:$C$239,$A$120:$A$239,$A$41,$B$120:$B$239,E$11)=0,"",SUMIFS($N$120:$N$239,$A$120:$A$239,$A$41,$B$120:$B$239,E$11)) | F41: =IF(SUMIFS($C$120:$C$239,$A$120:$A$239,$A$41,$B$120:$B$239,F$11)=0,"",SUMIFS($N$120:$N$239,$A$120:$A$239,$A$41,$B$120:$B$239,F$11)) | G41: =IF(SUMIFS($C$120:$C$239,$A$120:$A$239,$A$41,$B$120:$B$239,G$11)=0,"",SUMIFS($N$120:$N$239,$A$120:$A$239,$A$41,$B$120:$B$239,G$11)) | H41: =IF(SUMIFS($C$120:$C$239,$A$120:$A$239,$A$41,$B$120:$B$239,H$11)=0,"",SUMIFS($N$120:$N$239,$A$120:$A$239,$A$41,$B$120:$B$239,H$11)) | I41: =IF(SUMIFS($C$120:$C$239,$A$120:$A$239,$A$41,$B$120:$B$239,I$11)=0,"",SUMIFS($N$120:$N$239,$A$120:$A$239,$A$41,$B$120:$B$239,I$11)) -> 0.054492457 | J41: =IF(SUMIFS($C$120:$C$239,$A$120:$A$239,$A$41,$B$120:$B$239,J$11)=0,"",SUMIFS($N$120:$N$239,$A$120:$A$239,$A$41,$B$120:$B$239,J$11)) -> -1 | K41: =IF(SUMIFS($C$120:$C$239,$A$120:$A$239,$A$41,$B$120:$B$239,K$11)=0,"",SUMIFS($N$120:$N$239,$A$120:$A$239,$A$41,$B$120:$B$239,K$11)) | L41: =V41/O41-1 -> -1 | M41: =IF($B41=0,"",(V41/O41)^(1/$B41)-1) -> -1 | O41: 100 | P41: =IF(E41="",O41,O41*(1+E41)) -> 100 | Q41: =IF(F41="",P41,P41*(1+F41)) -> 100 | R41: =IF(G41="",Q41,Q41*(1+G41)) -> 100 | S41: =IF(H41="",R41,R41*(1+H41)) -> 100 | T41: =IF(I41="",S41,S41*(1+I41)) -> 105.44925 | U41: =IF(J41="",T41,T41*(1+J41)) -> 0 | V41: =IF(K41="",U41,U41*(1+K41)) -> 0
D42: Appreciation: | E42: =IF(SUMIFS($C$120:$C$239,$A$120:$A$239,$A$41,$B$120:$B$239,E$11)=0,"",SUMIFS($M$120:$M$239,$A$120:$A$239,$A$41,$B$120:$B$239,E$11)) | F42: =IF(SUMIFS($C$120:$C$239,$A$120:$A$239,$A$41,$B$120:$B$239,F$11)=0,"",SUMIFS($M$120:$M$239,$A$120:$A$239,$A$41,$B$120:$B$239,F$11)) | G42: =IF(SUMIFS($C$120:$C$239,$A$120:$A$239,$A$41,$B$120:$B$239,G$11)=0,"",SUMIFS($M$120:$M$239,$A$120:$A$239,$A$41,$B$120:$B$239,G$11)) | H42: =IF(SUMIFS($C$120:$C$239,$A$120:$A$239,$A$41,$B$120:$B$239,H$11)=0,"",SUMIFS($M$120:$M$239,$A$120:$A$239,$A$41,$B$120:$B$239,H$11)) | I42: =IF(SUMIFS($C$120:$C$239,$A$120:$A$239,$A$41,$B$120:$B$239,I$11)=0,"",SUMIFS($M$120:$M$239,$A$120:$A$239,$A$41,$B$120:$B$239,I$11)) -> 0.025050919 | J42: =IF(SUMIFS($C$120:$C$239,$A$120:$A$239,$A$41,$B$120:$B$239,J$11)=0,"",SUMIFS($M$120:$M$239,$A$120:$A$239,$A$41,$B$120:$B$239,J$11)) -> -1 | K42: =IF(SUMIFS($C$120:$C$239,$A$120:$A$239,$A$41,$B$120:$B$239,K$11)=0,"",SUMIFS($M$120:$M$239,$A$120:$A$239,$A$41,$B$120:$B$239,K$11)) | L42: =V42/O42-1 -> -1 | M42: =IF($B41=0,"",(V42/O42)^(1/$B41)-1) -> -1 | O42: 100 | P42: =IF(E42="",O42,O42*(1+E42)) -> 100 | Q42: =IF(F42="",P42,P42*(1+F42)) -> 100 | R42: =IF(G42="",Q42,Q42*(1+G42)) -> 100 | S42: =IF(H42="",R42,R42*(1+H42)) -> 100 | T42: =IF(I42="",S42,S42*(1+I42)) -> 102.50509 | U42: =IF(J42="",T42,T42*(1+J42)) -> 0 | V42: =IF(K42="",U42,U42*(1+K42)) -> 0
D43: Income: | E43: =IF(SUMIFS($C$120:$C$239,$A$120:$A$239,$A$41,$B$120:$B$239,E$11)=0,"",SUMIFS($L$120:$L$239,$A$120:$A$239,$A$41,$B$120:$B$239,E$11)) | F43: =IF(SUMIFS($C$120:$C$239,$A$120:$A$239,$A$41,$B$120:$B$239,F$11)=0,"",SUMIFS($L$120:$L$239,$A$120:$A$239,$A$41,$B$120:$B$239,F$11)) | G43: =IF(SUMIFS($C$120:$C$239,$A$120:$A$239,$A$41,$B$120:$B$239,G$11)=0,"",SUMIFS($L$120:$L$239,$A$120:$A$239,$A$41,$B$120:$B$239,G$11)) | H43: =IF(SUMIFS($C$120:$C$239,$A$120:$A$239,$A$41,$B$120:$B$239,H$11)=0,"",SUMIFS($L$120:$L$239,$A$120:$A$239,$A$41,$B$120:$B$239,H$11)) | I43: =IF(SUMIFS($C$120:$C$239,$A$120:$A$239,$A$41,$B$120:$B$239,I$11)=0,"",SUMIFS($L$120:$L$239,$A$120:$A$239,$A$41,$B$120:$B$239,I$11)) -> 0.029441538 | J43: =IF(SUMIFS($C$120:$C$239,$A$120:$A$239,$A$41,$B$120:$B$239,J$11)=0,"",SUMIFS($L$120:$L$239,$A$120:$A$239,$A$41,$B$120:$B$239,J$11)) -> 0 | K43: =IF(SUMIFS($C$120:$C$239,$A$120:$A$239,$A$41,$B$120:$B$239,K$11)=0,"",SUMIFS($L$120:$L$239,$A$120:$A$239,$A$41,$B$120:$B$239,K$11)) | L43: =V43/O43-1 -> 0.029441538 | M43: =IF($B41=0,"",(V43/O43)^(1/$B41)-1) -> 0.014613985 | O43: 100 | P43: =IF(E43="",O43,O43*(1+E43)) -> 100 | Q43: =IF(F43="",P43,P43*(1+F43)) -> 100 | R43: =IF(G43="",Q43,Q43*(1+G43)) -> 100 | S43: =IF(H43="",R43,R43*(1+H43)) -> 100 | T43: =IF(I43="",S43,S43*(1+I43)) -> 102.94415 | U43: =IF(J43="",T43,T43*(1+J43)) -> 102.94415 | V43: =IF(K43="",U43,U43*(1+K43)) -> 102.94415
A44: Fazenda Parceiro | B44: =COUNT(E44:K44) -> 3 | C44: =SUMIFS($E$120:$E$239,$A$120:$A$239,$A44,$B$120:$B$239,K$11)/1000 -> 234.99 | D44: Total: | E44: =IF(SUMIFS($C$120:$C$239,$A$120:$A$239,$A$44,$B$120:$B$239,E$11)=0,"",SUMIFS($N$120:$N$239,$A$120:$A$239,$A$44,$B$120:$B$239,E$11)) | F44: =IF(SUMIFS($C$120:$C$239,$A$120:$A$239,$A$44,$B$120:$B$239,F$11)=0,"",SUMIFS($N$120:$N$239,$A$120:$A$239,$A$44,$B$120:$B$239,F$11)) | G44: =IF(SUMIFS($C$120:$C$239,$A$120:$A$239,$A$44,$B$120:$B$239,G$11)=0,"",SUMIFS($N$120:$N$239,$A$120:$A$239,$A$44,$B$120:$B$239,G$11)) | H44: =IF(SUMIFS($C$120:$C$239,$A$120:$A$239,$A$44,$B$120:$B$239,H$11)=0,"",SUMIFS($N$120:$N$239,$A$120:$A$239,$A$44,$B$120:$B$239,H$11)) | I44: =IF(SUMIFS($C$120:$C$239,$A$120:$A$239,$A$44,$B$120:$B$239,I$11)=0,"",SUMIFS($N$120:$N$239,$A$120:$A$239,$A$44,$B$120:$B$239,I$11)) -> 0.49413874 | J44: =IF(SUMIFS($C$120:$C$239,$A$120:$A$239,$A$44,$B$120:$B$239,J$11)=0,"",SUMIFS($N$120:$N$239,$A$120:$A$239,$A$44,$B$120:$B$239,J$11)) -> 0.35316139 | K44: =IF(SUMIFS($C$120:$C$239,$A$120:$A$239,$A$44,$B$120:$B$239,K$11)=0,"",SUMIFS($N$120:$N$239,$A$120:$A$239,$A$44,$B$120:$B$239,K$11)) -> 0.042210686 | L44: =V44/O44-1 -> 1.1071529 | M44: =IF($B44=0,"",(V44/O44)^(1/$B44)-1) -> 0.28203146 | O44: 100 | P44: =IF(E44="",O44,O44*(1+E44)) -> 100 | Q44: =IF(F44="",P44,P44*(1+F44)) -> 100 | R44: =IF(G44="",Q44,Q44*(1+G44)) -> 100 | S44: =IF(H44="",R44,R44*(1+H44)) -> 100 | T44: =IF(I44="",S44,S44*(1+I44)) -> 149.41387 | U44: =IF(J44="",T44,T44*(1+J44)) -> 202.18109 | V44: =IF(K44="",U44,U44*(1+K44)) -> 210.71529
D45: Appreciation: | E45: =IF(SUMIFS($C$120:$C$239,$A$120:$A$239,$A$44,$B$120:$B$239,E$11)=0,"",SUMIFS($M$120:$M$239,$A$120:$A$239,$A$44,$B$120:$B$239,E$11)) | F45: =IF(SUMIFS($C$120:$C$239,$A$120:$A$239,$A$44,$B$120:$B$239,F$11)=0,"",SUMIFS($M$120:$M$239,$A$120:$A$239,$A$44,$B$120:$B$239,F$11)) | G45: =IF(SUMIFS($C$120:$C$239,$A$120:$A$239,$A$44,$B$120:$B$239,G$11)=0,"",SUMIFS($M$120:$M$239,$A$120:$A$239,$A$44,$B$120:$B$239,G$11)) | H45: =IF(SUMIFS($C$120:$C$239,$A$120:$A$239,$A$44,$B$120:$B$239,H$11)=0,"",SUMIFS($M$120:$M$239,$A$120:$A$239,$A$44,$B$120:$B$239,H$11)) | I45: =IF(SUMIFS($C$120:$C$239,$A$120:$A$239,$A$44,$B$120:$B$239,I$11)=0,"",SUMIFS($M$120:$M$239,$A$120:$A$239,$A$44,$B$120:$B$239,I$11)) -> 0.4743142 | J45: =IF(SUMIFS($C$120:$C$239,$A$120:$A$239,$A$44,$B$120:$B$239,J$11)=0,"",SUMIFS($M$120:$M$239,$A$120:$A$239,$A$44,$B$120:$B$239,J$11)) -> 0.34924486 | K45: =IF(SUMIFS($C$120:$C$239,$A$120:$A$239,$A$44,$B$120:$B$239,K$11)=0,"",SUMIFS($M$120:$M$239,$A$120:$A$239,$A$44,$B$120:$B$239,K$11)) -> 0.036827076 | L45: =V45/O45-1 -> 1.0624677 | M45: =IF($B44=0,"",(V45/O45)^(1/$B44)-1) -> 0.27290419 | O45: 100 | P45: =IF(E45="",O45,O45*(1+E45)) -> 100 | Q45: =IF(F45="",P45,P45*(1+F45)) -> 100 | R45: =IF(G45="",Q45,Q45*(1+G45)) -> 100 | S45: =IF(H45="",R45,R45*(1+H45)) -> 100 | T45: =IF(I45="",S45,S45*(1+I45)) -> 147.43142 | U45: =IF(J45="",T45,T45*(1+J45)) -> 198.92109 | V45: =IF(K45="",U45,U45*(1+K45)) -> 206.24677
D46: Income: | E46: =IF(SUMIFS($C$120:$C$239,$A$120:$A$239,$A$44,$B$120:$B$239,E$11)=0,"",SUMIFS($L$120:$L$239,$A$120:$A$239,$A$44,$B$120:$B$239,E$11)) | F46: =IF(SUMIFS($C$120:$C$239,$A$120:$A$239,$A$44,$B$120:$B$239,F$11)=0,"",SUMIFS($L$120:$L$239,$A$120:$A$239,$A$44,$B$120:$B$239,F$11)) | G46: =IF(SUMIFS($C$120:$C$239,$A$120:$A$239,$A$44,$B$120:$B$239,G$11)=0,"",SUMIFS($L$120:$L$239,$A$120:$A$239,$A$44,$B$120:$B$239,G$11)) | H46: =IF(SUMIFS($C$120:$C$239,$A$120:$A$239,$A$44,$B$120:$B$239,H$11)=0,"",SUMIFS($L$120:$L$239,$A$120:$A$239,$A$44,$B$120:$B$239,H$11)) | I46: =IF(SUMIFS($C$120:$C$239,$A$120:$A$239,$A$44,$B$120:$B$239,I$11)=0,"",SUMIFS($L$120:$L$239,$A$120:$A$239,$A$44,$B$120:$B$239,I$11)) -> 0.019824537 | J46: =IF(SUMIFS($C$120:$C$239,$A$120:$A$239,$A$44,$B$120:$B$239,J$11)=0,"",SUMIFS($L$120:$L$239,$A$120:$A$239,$A$44,$B$120:$B$239,J$11)) -> 0.0039165308 | K46: =IF(SUMIFS($C$120:$C$239,$A$120:$A$239,$A$44,$B$120:$B$239,K$11)=0,"",SUMIFS($L$120:$L$239,$A$120:$A$239,$A$44,$B$120:$B$239,K$11)) -> 0.0053836098 | L46: =V46/O46-1 -> 0.029330552 | M46: =IF($B44=0,"",(V46/O46)^(1/$B44)-1) -> 0.0096827916 | O46: 100 | P46: =IF(E46="",O46,O46*(1+E46)) -> 100 | Q46: =IF(F46="",P46,P46*(1+F46)) -> 100 | R46: =IF(G46="",Q46,Q46*(1+G46)) -> 100 | S46: =IF(H46="",R46,R46*(1+H46)) -> 100 | T46: =IF(I46="",S46,S46*(1+I46)) -> 101.98245 | U46: =IF(J46="",T46,T46*(1+J46)) -> 102.38187 | V46: =IF(K46="",U46,U46*(1+K46)) -> 102.93306
A47: Fazenda Perdizes | B47: =COUNT(E47:K47) -> 3 | C47: =SUMIFS($E$120:$E$239,$A$120:$A$239,$A47,$B$120:$B$239,K$11)/1000 -> 175.03 | D47: Total: | E47: =IF(SUMIFS($C$120:$C$239,$A$120:$A$239,$A$47,$B$120:$B$239,E$11)=0,"",SUMIFS($N$120:$N$239,$A$120:$A$239,$A$47,$B$120:$B$239,E$11)) | F47: =IF(SUMIFS($C$120:$C$239,$A$120:$A$239,$A$47,$B$120:$B$239,F$11)=0,"",SUMIFS($N$120:$N$239,$A$120:$A$239,$A$47,$B$120:$B$239,F$11)) | G47: =IF(SUMIFS($C$120:$C$239,$A$120:$A$239,$A$47,$B$120:$B$239,G$11)=0,"",SUMIFS($N$120:$N$239,$A$120:$A$239,$A$47,$B$120:$B$239,G$11)) | H47: =IF(SUMIFS($C$120:$C$239,$A$120:$A$239,$A$47,$B$120:$B$239,H$11)=0,"",SUMIFS($N$120:$N$239,$A$120:$A$239,$A$47,$B$120:$B$239,H$11)) | I47: =IF(SUMIFS($C$120:$C$239,$A$120:$A$239,$A$47,$B$120:$B$239,I$11)=0,"",SUMIFS($N$120:$N$239,$A$120:$A$239,$A$47,$B$120:$B$239,I$11)) -> 1.0563287 | J47: =IF(SUMIFS($C$120:$C$239,$A$120:$A$239,$A$47,$B$120:$B$239,J$11)=0,"",SUMIFS($N$120:$N$239,$A$120:$A$239,$A$47,$B$120:$B$239,J$11)) -> 0.063575347 | K47: =IF(SUMIFS($C$120:$C$239,$A$120:$A$239,$A$47,$B$120:$B$239,K$11)=0,"",SUMIFS($N$120:$N$239,$A$120:$A$239,$A$47,$B$120:$B$239,K$11)) -> 0.060076458 | L47: =V47/O47-1 -> 1.3184514 | M47: =IF($B47=0,"",(V47/O47)^(1/$B47)-1) -> 0.32352657 | O47: 100 | P47: =IF(E47="",O47,O47*(1+E47)) -> 100 | Q47: =IF(F47="",P47,P47*(1+F47)) -> 100 | R47: =IF(G47="",Q47,Q47*(1+G47)) -> 100 | S47: =IF(H47="",R47,R47*(1+H47)) -> 100 | T47: =IF(I47="",S47,S47*(1+I47)) -> 205.63287 | U47: =IF(J47="",T47,T47*(1+J47)) -> 218.70605 | V47: =IF(K47="",U47,U47*(1+K47)) -> 231.84514
D48: Appreciation: | E48: =IF(SUMIFS($C$120:$C$239,$A$120:$A$239,$A$47,$B$120:$B$239,E$11)=0,"",SUMIFS($M$120:$M$239,$A$120:$A$239,$A$47,$B$120:$B$239,E$11)) | F48: =IF(SUMIFS($C$120:$C$239,$A$120:$A$239,$A$47,$B$120:$B$239,F$11)=0,"",SUMIFS($M$120:$M$239,$A$120:$A$239,$A$47,$B$120:$B$239,F$11)) | G48: =IF(SUMIFS($C$120:$C$239,$A$120:$A$239,$A$47,$B$120:$B$239,G$11)=0,"",SUMIFS($M$120:$M$239,$A$120:$A$239,$A$47,$B$120:$B$239,G$11)) | H48: =IF(SUMIFS($C$120:$C$239,$A$120:$A$239,$A$47,$B$120:$B$239,H$11)=0,"",SUMIFS($M$120:$M$239,$A$120:$A$239,$A$47,$B$120:$B$239,H$11)) | I48: =IF(SUMIFS($C$120:$C$239,$A$120:$A$239,$A$47,$B$120:$B$239,I$11)=0,"",SUMIFS($M$120:$M$239,$A$120:$A$239,$A$47,$B$120:$B$239,I$11)) -> 0.99726061 | J48: =IF(SUMIFS($C$120:$C$239,$A$120:$A$239,$A$47,$B$120:$B$239,J$11)=0,"",SUMIFS($M$120:$M$239,$A$120:$A$239,$A$47,$B$120:$B$239,J$11)) -> 0.031873487 | K48: =IF(SUMIFS($C$120:$C$239,$A$120:$A$239,$A$47,$B$120:$B$239,K$11)=0,"",SUMIFS($M$120:$M$239,$A$120:$A$239,$A$47,$B$120:$B$239,K$11)) -> 0.024408108 | L48: =V48/O48-1 -> 1.1112234 | M48: =IF($B47=0,"",(V48/O48)^(1/$B47)-1) -> 0.28285646 | O48: 100 | P48: =IF(E48="",O48,O48*(1+E48)) -> 100 | Q48: =IF(F48="",P48,P48*(1+F48)) -> 100 | R48: =IF(G48="",Q48,Q48*(1+G48)) -> 100 | S48: =IF(H48="",R48,R48*(1+H48)) -> 100 | T48: =IF(I48="",S48,S48*(1+I48)) -> 199.72606 | U48: =IF(J48="",T48,T48*(1+J48)) -> 206.09203 | V48: =IF(K48="",U48,U48*(1+K48)) -> 211.12234
D49: Income: | E49: =IF(SUMIFS($C$120:$C$239,$A$120:$A$239,$A$47,$B$120:$B$239,E$11)=0,"",SUMIFS($L$120:$L$239,$A$120:$A$239,$A$47,$B$120:$B$239,E$11)) | F49: =IF(SUMIFS($C$120:$C$239,$A$120:$A$239,$A$47,$B$120:$B$239,F$11)=0,"",SUMIFS($L$120:$L$239,$A$120:$A$239,$A$47,$B$120:$B$239,F$11)) | G49: =IF(SUMIFS($C$120:$C$239,$A$120:$A$239,$A$47,$B$120:$B$239,G$11)=0,"",SUMIFS($L$120:$L$239,$A$120:$A$239,$A$47,$B$120:$B$239,G$11)) | H49: =IF(SUMIFS($C$120:$C$239,$A$120:$A$239,$A$47,$B$120:$B$239,H$11)=0,"",SUMIFS($L$120:$L$239,$A$120:$A$239,$A$47,$B$120:$B$239,H$11)) | I49: =IF(SUMIFS($C$120:$C$239,$A$120:$A$239,$A$47,$B$120:$B$239,I$11)=0,"",SUMIFS($L$120:$L$239,$A$120:$A$239,$A$47,$B$120:$B$239,I$11)) -> 0.059068118 | J49: =IF(SUMIFS($C$120:$C$239,$A$120:$A$239,$A$47,$B$120:$B$239,J$11)=0,"",SUMIFS($L$120:$L$239,$A$120:$A$239,$A$47,$B$120:$B$239,J$11)) -> 0.03170186 | K49: =IF(SUMIFS($C$120:$C$239,$A$120:$A$239,$A$47,$B$120:$B$239,K$11)=0,"",SUMIFS($L$120:$L$239,$A$120:$A$239,$A$47,$B$120:$B$239,K$11)) -> 0.03566835 | L49: =V49/O49-1 -> 0.1316153 | M49: =IF($B47=0,"",(V49/O49)^(1/$B47)-1) -> 0.042076505 | O49: 100 | P49: =IF(E49="",O49,O49*(1+E49)) -> 100 | Q49: =IF(F49="",P49,P49*(1+F49)) -> 100 | R49: =IF(G49="",Q49,Q49*(1+G49)) -> 100 | S49: =IF(H49="",R49,R49*(1+H49)) -> 100 | T49: =IF(I49="",S49,S49*(1+I49)) -> 105.90681 | U49: =IF(J49="",T49,T49*(1+J49)) -> 109.26425 | V49: =IF(K49="",U49,U49*(1+K49)) -> 113.16153
A50: Fazenda Planorte | B50: =COUNT(E50:K50) -> 7 | C50: =SUMIFS($E$120:$E$239,$A$120:$A$239,$A50,$B$120:$B$239,K$11)/1000 -> 315.87 | D50: Total: | E50: =IF(SUMIFS($C$120:$C$239,$A$120:$A$239,$A$50,$B$120:$B$239,E$11)=0,"",SUMIFS($N$120:$N$239,$A$120:$A$239,$A$50,$B$120:$B$239,E$11)) -> 1.1477692 | F50: =IF(SUMIFS($C$120:$C$239,$A$120:$A$239,$A$50,$B$120:$B$239,F$11)=0,"",SUMIFS($N$120:$N$239,$A$120:$A$239,$A$50,$B$120:$B$239,F$11)) -> -0.14137946 | G50: =IF(SUMIFS($C$120:$C$239,$A$120:$A$239,$A$50,$B$120:$B$239,G$11)=0,"",SUMIFS($N$120:$N$239,$A$120:$A$239,$A$50,$B$120:$B$239,G$11)) -> 0.096175956 | H50: =IF(SUMIFS($C$120:$C$239,$A$120:$A$239,$A$50,$B$120:$B$239,H$11)=0,"",SUMIFS($N$120:$N$239,$A$120:$A$239,$A$50,$B$120:$B$239,H$11)) -> 0.16293493 | I50: =IF(SUMIFS($C$120:$C$239,$A$120:$A$239,$A$50,$B$120:$B$239,I$11)=0,"",SUMIFS($N$120:$N$239,$A$120:$A$239,$A$50,$B$120:$B$239,I$11)) -> 0.0066975139 | J50: =IF(SUMIFS($C$120:$C$239,$A$120:$A$239,$A$50,$B$120:$B$239,J$11)=0,"",SUMIFS($N$120:$N$239,$A$120:$A$239,$A$50,$B$120:$B$239,J$11)) -> 0.20065984 | K50: =IF(SUMIFS($C$120:$C$239,$A$120:$A$239,$A$50,$B$120:$B$239,K$11)=0,"",SUMIFS($N$120:$N$239,$A$120:$A$239,$A$50,$B$120:$B$239,K$11)) -> 0.024743465 | L50: =V50/O50-1 -> 1.911781 | M50: =IF($B50=0,"",(V50/O50)^(1/$B50)-1) -> 0.16495295 | O50: 100 | P50: =IF(E50="",O50,O50*(1+E50)) -> 214.77692 | Q50: =IF(F50="",P50,P50*(1+F50)) -> 184.41187 | R50: =IF(G50="",Q50,Q50*(1+G50)) -> 202.14786 | S50: =IF(H50="",R50,R50*(1+H50)) -> 235.08481 | T50: =IF(I50="",S50,S50*(1+I50)) -> 236.65929 | U50: =IF(J50="",T50,T50*(1+J50)) -> 284.14731 | V50: =IF(K50="",U50,U50*(1+K50)) -> 291.1781
D51: Appreciation: | E51: =IF(SUMIFS($C$120:$C$239,$A$120:$A$239,$A$50,$B$120:$B$239,E$11)=0,"",SUMIFS($M$120:$M$239,$A$120:$A$239,$A$50,$B$120:$B$239,E$11)) -> 1.1477692 | F51: =IF(SUMIFS($C$120:$C$239,$A$120:$A$239,$A$50,$B$120:$B$239,F$11)=0,"",SUMIFS($M$120:$M$239,$A$120:$A$239,$A$50,$B$120:$B$239,F$11)) -> -0.14137946 | G51: =IF(SUMIFS($C$120:$C$239,$A$120:$A$239,$A$50,$B$120:$B$239,G$11)=0,"",SUMIFS($M$120:$M$239,$A$120:$A$239,$A$50,$B$120:$B$239,G$11)) -> 0.096175956 | H51: =IF(SUMIFS($C$120:$C$239,$A$120:$A$239,$A$50,$B$120:$B$239,H$11)=0,"",SUMIFS($M$120:$M$239,$A$120:$A$239,$A$50,$B$120:$B$239,H$11)) -> 0.16293493 | I51: =IF(SUMIFS($C$120:$C$239,$A$120:$A$239,$A$50,$B$120:$B$239,I$11)=0,"",SUMIFS($M$120:$M$239,$A$120:$A$239,$A$50,$B$120:$B$239,I$11)) -> 0.0066975139 | J51: =IF(SUMIFS($C$120:$C$239,$A$120:$A$239,$A$50,$B$120:$B$239,J$11)=0,"",SUMIFS($M$120:$M$239,$A$120:$A$239,$A$50,$B$120:$B$239,J$11)) -> 0.20065984 | K51: =IF(SUMIFS($C$120:$C$239,$A$120:$A$239,$A$50,$B$120:$B$239,K$11)=0,"",SUMIFS($M$120:$M$239,$A$120:$A$239,$A$50,$B$120:$B$239,K$11)) -> 0.024743465 | L51: =V51/O51-1 -> 1.911781 | M51: =IF($B50=0,"",(V51/O51)^(1/$B50)-1) -> 0.16495295 | O51: 100 | P51: =IF(E51="",O51,O51*(1+E51)) -> 214.77692 | Q51: =IF(F51="",P51,P51*(1+F51)) -> 184.41187 | R51: =IF(G51="",Q51,Q51*(1+G51)) -> 202.14786 | S51: =IF(H51="",R51,R51*(1+H51)) -> 235.08481 | T51: =IF(I51="",S51,S51*(1+I51)) -> 236.65929 | U51: =IF(J51="",T51,T51*(1+J51)) -> 284.14731 | V51: =IF(K51="",U51,U51*(1+K51)) -> 291.1781
D52: Income: | E52: =IF(SUMIFS($C$120:$C$239,$A$120:$A$239,$A$50,$B$120:$B$239,E$11)=0,"",SUMIFS($L$120:$L$239,$A$120:$A$239,$A$50,$B$120:$B$239,E$11)) -> 0 | F52: =IF(SUMIFS($C$120:$C$239,$A$120:$A$239,$A$50,$B$120:$B$239,F$11)=0,"",SUMIFS($L$120:$L$239,$A$120:$A$239,$A$50,$B$120:$B$239,F$11)) -> 0 | G52: =IF(SUMIFS($C$120:$C$239,$A$120:$A$239,$A$50,$B$120:$B$239,G$11)=0,"",SUMIFS($L$120:$L$239,$A$120:$A$239,$A$50,$B$120:$B$239,G$11)) -> 0 | H52: =IF(SUMIFS($C$120:$C$239,$A$120:$A$239,$A$50,$B$120:$B$239,H$11)=0,"",SUMIFS($L$120:$L$239,$A$120:$A$239,$A$50,$B$120:$B$239,H$11)) -> 0 | I52: =IF(SUMIFS($C$120:$C$239,$A$120:$A$239,$A$50,$B$120:$B$239,I$11)=0,"",SUMIFS($L$120:$L$239,$A$120:$A$239,$A$50,$B$120:$B$239,I$11)) -> 0 | J52: =IF(SUMIFS($C$120:$C$239,$A$120:$A$239,$A$50,$B$120:$B$239,J$11)=0,"",SUMIFS($L$120:$L$239,$A$120:$A$239,$A$50,$B$120:$B$239,J$11)) -> 0 | K52: =IF(SUMIFS($C$120:$C$239,$A$120:$A$239,$A$50,$B$120:$B$239,K$11)=0,"",SUMIFS($L$120:$L$239,$A$120:$A$239,$A$50,$B$120:$B$239,K$11)) -> 0 | L52: =V52/O52-1 -> 0 | M52: =IF($B50=0,"",(V52/O52)^(1/$B50)-1) -> 0 | O52: 100 | P52: =IF(E52="",O52,O52*(1+E52)) -> 100 | Q52: =IF(F52="",P52,P52*(1+F52)) -> 100 | R52: =IF(G52="",Q52,Q52*(1+G52)) -> 100 | S52: =IF(H52="",R52,R52*(1+H52)) -> 100 | T52: =IF(I52="",S52,S52*(1+I52)) -> 100 | U52: =IF(J52="",T52,T52*(1+J52)) -> 100 | V52: =IF(K52="",U52,U52*(1+K52)) -> 100
A53: Fazenda Parnaguá | B53: =COUNT(E53:K53) -> 6 | C53: =SUMIFS($E$120:$E$239,$A$120:$A$239,$A53,$B$120:$B$239,K$11)/1000 -> 143.71 | D53: Total: | E53: =IF(SUMIFS($C$120:$C$239,$A$120:$A$239,$A$53,$B$120:$B$239,E$11)=0,"",SUMIFS($N$120:$N$239,$A$120:$A$239,$A$53,$B$120:$B$239,E$11)) | F53: =IF(SUMIFS($C$120:$C$239,$A$120:$A$239,$A$53,$B$120:$B$239,F$11)=0,"",SUMIFS($N$120:$N$239,$A$120:$A$239,$A$53,$B$120:$B$239,F$11)) -> 0.015403081 | G53: =IF(SUMIFS($C$120:$C$239,$A$120:$A$239,$A$53,$B$120:$B$239,G$11)=0,"",SUMIFS($N$120:$N$239,$A$120:$A$239,$A$53,$B$120:$B$239,G$11)) -> 0.19267139 | H53: =IF(SUMIFS($C$120:$C$239,$A$120:$A$239,$A$53,$B$120:$B$239,H$11)=0,"",SUMIFS($N$120:$N$239,$A$120:$A$239,$A$53,$B$120:$B$239,H$11)) -> 0.048562934 | I53: =IF(SUMIFS($C$120:$C$239,$A$120:$A$239,$A$53,$B$120:$B$239,I$11)=0,"",SUMIFS($N$120:$N$239,$A$120:$A$239,$A$53,$B$120:$B$239,I$11)) -> 0.40570239 | J53: =IF(SUMIFS($C$120:$C$239,$A$120:$A$239,$A$53,$B$120:$B$239,J$11)=0,"",SUMIFS($N$120:$N$239,$A$120:$A$239,$A$53,$B$120:$B$239,J$11)) -> 0.58705079 | K53: =IF(SUMIFS($C$120:$C$239,$A$120:$A$239,$A$53,$B$120:$B$239,K$11)=0,"",SUMIFS($N$120:$N$239,$A$120:$A$239,$A$53,$B$120:$B$239,K$11)) -> 0.048690257 | L53: =V53/O53-1 -> 1.9708808 | M53: =IF($B53=0,"",(V53/O53)^(1/$B53)-1) -> 0.19898625 | O53: 100 | P53: =IF(E53="",O53,O53*(1+E53)) -> 100 | Q53: =IF(F53="",P53,P53*(1+F53)) -> 101.54031 | R53: =IF(G53="",Q53,Q53*(1+G53)) -> 121.10422 | S53: =IF(H53="",R53,R53*(1+H53)) -> 126.9854 | T53: =IF(I53="",S53,S53*(1+I53)) -> 178.50368 | U53: =IF(J53="",T53,T53*(1+J53)) -> 283.2944 | V53: =IF(K53="",U53,U53*(1+K53)) -> 297.08808
D54: Appreciation: | E54: =IF(SUMIFS($C$120:$C$239,$A$120:$A$239,$A$53,$B$120:$B$239,E$11)=0,"",SUMIFS($M$120:$M$239,$A$120:$A$239,$A$53,$B$120:$B$239,E$11)) | F54: =IF(SUMIFS($C$120:$C$239,$A$120:$A$239,$A$53,$B$120:$B$239,F$11)=0,"",SUMIFS($M$120:$M$239,$A$120:$A$239,$A$53,$B$120:$B$239,F$11)) -> 0.015403081 | G54: =IF(SUMIFS($C$120:$C$239,$A$120:$A$239,$A$53,$B$120:$B$239,G$11)=0,"",SUMIFS($M$120:$M$239,$A$120:$A$239,$A$53,$B$120:$B$239,G$11)) -> 0.19267139 | H54: =IF(SUMIFS($C$120:$C$239,$A$120:$A$239,$A$53,$B$120:$B$239,H$11)=0,"",SUMIFS($M$120:$M$239,$A$120:$A$239,$A$53,$B$120:$B$239,H$11)) -> 0.048562934 | I54: =IF(SUMIFS($C$120:$C$239,$A$120:$A$239,$A$53,$B$120:$B$239,I$11)=0,"",SUMIFS($M$120:$M$239,$A$120:$A$239,$A$53,$B$120:$B$239,I$11)) -> 0.37206471 | J54: =IF(SUMIFS($C$120:$C$239,$A$120:$A$239,$A$53,$B$120:$B$239,J$11)=0,"",SUMIFS($M$120:$M$239,$A$120:$A$239,$A$53,$B$120:$B$239,J$11)) -> 0.58705079 | K54: =IF(SUMIFS($C$120:$C$239,$A$120:$A$239,$A$53,$B$120:$B$239,K$11)=0,"",SUMIFS($M$120:$M$239,$A$120:$A$239,$A$53,$B$120:$B$239,K$11)) -> 0.044422759 | L54: =V54/O54-1 -> 1.887989 | M54: =IF($B53=0,"",(V54/O54)^(1/$B53)-1) -> 0.19334474 | O54: 100 | P54: =IF(E54="",O54,O54*(1+E54)) -> 100 | Q54: =IF(F54="",P54,P54*(1+F54)) -> 101.54031 | R54: =IF(G54="",Q54,Q54*(1+G54)) -> 121.10422 | S54: =IF(H54="",R54,R54*(1+H54)) -> 126.9854 | T54: =IF(I54="",S54,S54*(1+I54)) -> 174.23218 | U54: =IF(J54="",T54,T54*(1+J54)) -> 276.51532 | V54: =IF(K54="",U54,U54*(1+K54)) -> 288.7989
D55: Income: | E55: =IF(SUMIFS($C$120:$C$239,$A$120:$A$239,$A$53,$B$120:$B$239,E$11)=0,"",SUMIFS($L$120:$L$239,$A$120:$A$239,$A$53,$B$120:$B$239,E$11)) | F55: =IF(SUMIFS($C$120:$C$239,$A$120:$A$239,$A$53,$B$120:$B$239,F$11)=0,"",SUMIFS($L$120:$L$239,$A$120:$A$239,$A$53,$B$120:$B$239,F$11)) -> 0 | G55: =IF(SUMIFS($C$120:$C$239,$A$120:$A$239,$A$53,$B$120:$B$239,G$11)=0,"",SUMIFS($L$120:$L$239,$A$120:$A$239,$A$53,$B$120:$B$239,G$11)) -> 0 | H55: =IF(SUMIFS($C$120:$C$239,$A$120:$A$239,$A$53,$B$120:$B$239,H$11)=0,"",SUMIFS($L$120:$L$239,$A$120:$A$239,$A$53,$B$120:$B$239,H$11)) -> 0 | I55: =IF(SUMIFS($C$120:$C$239,$A$120:$A$239,$A$53,$B$120:$B$239,I$11)=0,"",SUMIFS($L$120:$L$239,$A$120:$A$239,$A$53,$B$120:$B$239,I$11)) -> 0.033637674 | J55: =IF(SUMIFS($C$120:$C$239,$A$120:$A$239,$A$53,$B$120:$B$239,J$11)=0,"",SUMIFS($L$120:$L$239,$A$120:$A$239,$A$53,$B$120:$B$239,J$11)) -> 0 | K55: =IF(SUMIFS($C$120:$C$239,$A$120:$A$239,$A$53,$B$120:$B$239,K$11)=0,"",SUMIFS($L$120:$L$239,$A$120:$A$239,$A$53,$B$120:$B$239,K$11)) -> 0.0042674978 | L55: =V55/O55-1 -> 0.038048721 | M55: =IF($B53=0,"",(V55/O55)^(1/$B53)-1) -> 0.0062431948 | O55: 100 | P55: =IF(E55="",O55,O55*(1+E55)) -> 100 | Q55: =IF(F55="",P55,P55*(1+F55)) -> 100 | R55: =IF(G55="",Q55,Q55*(1+G55)) -> 100 | S55: =IF(H55="",R55,R55*(1+H55)) -> 100 | T55: =IF(I55="",S55,S55*(1+I55)) -> 103.36377 | U55: =IF(J55="",T55,T55*(1+J55)) -> 103.36377 | V55: =IF(K55="",U55,U55*(1+K55)) -> 103.80487
A56: Fazenda Paineira | B56: =COUNT(E56:K56) -> 3 | C56: =SUMIFS($E$120:$E$239,$A$120:$A$239,$A56,$B$120:$B$239,K$11)/1000 -> 93.35 | D56: Total: | E56: =IF(SUMIFS($C$120:$C$239,$A$120:$A$239,$A$56,$B$120:$B$239,E$11)=0,"",SUMIFS($N$120:$N$239,$A$120:$A$239,$A$56,$B$120:$B$239,E$11)) | F56: =IF(SUMIFS($C$120:$C$239,$A$120:$A$239,$A$56,$B$120:$B$239,F$11)=0,"",SUMIFS($N$120:$N$239,$A$120:$A$239,$A$56,$B$120:$B$239,F$11)) | G56: =IF(SUMIFS($C$120:$C$239,$A$120:$A$239,$A$56,$B$120:$B$239,G$11)=0,"",SUMIFS($N$120:$N$239,$A$120:$A$239,$A$56,$B$120:$B$239,G$11)) | H56: =IF(SUMIFS($C$120:$C$239,$A$120:$A$239,$A$56,$B$120:$B$239,H$11)=0,"",SUMIFS($N$120:$N$239,$A$120:$A$239,$A$56,$B$120:$B$239,H$11)) | I56: =IF(SUMIFS($C$120:$C$239,$A$120:$A$239,$A$56,$B$120:$B$239,I$11)=0,"",SUMIFS($N$120:$N$239,$A$120:$A$239,$A$56,$B$120:$B$239,I$11)) -> 0.30950886 | J56: =IF(SUMIFS($C$120:$C$239,$A$120:$A$239,$A$56,$B$120:$B$239,J$11)=0,"",SUMIFS($N$120:$N$239,$A$120:$A$239,$A$56,$B$120:$B$239,J$11)) -> 0.07882913 | K56: =IF(SUMIFS($C$120:$C$239,$A$120:$A$239,$A$56,$B$120:$B$239,K$11)=0,"",SUMIFS($N$120:$N$239,$A$120:$A$239,$A$56,$B$120:$B$239,K$11)) -> 0.069828209 | L56: =V56/O56-1 -> 0.51138515 | M56: =IF($B56=0,"",(V56/O56)^(1/$B56)-1) -> 0.14760311 | O56: 100 | P56: =IF(E56="",O56,O56*(1+E56)) -> 100 | Q56: =IF(F56="",P56,P56*(1+F56)) -> 100 | R56: =IF(G56="",Q56,Q56*(1+G56)) -> 100 | S56: =IF(H56="",R56,R56*(1+H56)) -> 100 | T56: =IF(I56="",S56,S56*(1+I56)) -> 130.95089 | U56: =IF(J56="",T56,T56*(1+J56)) -> 141.27363 | V56: =IF(K56="",U56,U56*(1+K56)) -> 151.13851
D57: Appreciation: | E57: =IF(SUMIFS($C$120:$C$239,$A$120:$A$239,$A$56,$B$120:$B$239,E$11)=0,"",SUMIFS($M$120:$M$239,$A$120:$A$239,$A$56,$B$120:$B$239,E$11)) | F57: =IF(SUMIFS($C$120:$C$239,$A$120:$A$239,$A$56,$B$120:$B$239,F$11)=0,"",SUMIFS($M$120:$M$239,$A$120:$A$239,$A$56,$B$120:$B$239,F$11)) | G57: =IF(SUMIFS($C$120:$C$239,$A$120:$A$239,$A$56,$B$120:$B$239,G$11)=0,"",SUMIFS($M$120:$M$239,$A$120:$A$239,$A$56,$B$120:$B$239,G$11)) | H57: =IF(SUMIFS($C$120:$C$239,$A$120:$A$239,$A$56,$B$120:$B$239,H$11)=0,"",SUMIFS($M$120:$M$239,$A$120:$A$239,$A$56,$B$120:$B$239,H$11)) | I57: =IF(SUMIFS($C$120:$C$239,$A$120:$A$239,$A$56,$B$120:$B$239,I$11)=0,"",SUMIFS($M$120:$M$239,$A$120:$A$239,$A$56,$B$120:$B$239,I$11)) -> 0.2790402 | J57: =IF(SUMIFS($C$120:$C$239,$A$120:$A$239,$A$56,$B$120:$B$239,J$11)=0,"",SUMIFS($M$120:$M$239,$A$120:$A$239,$A$56,$B$120:$B$239,J$11)) -> 0.046099334 | K57: =IF(SUMIFS($C$120:$C$239,$A$120:$A$239,$A$56,$B$120:$B$239,K$11)=0,"",SUMIFS($M$120:$M$239,$A$120:$A$239,$A$56,$B$120:$B$239,K$11)) -> 0.069828209 | L57: =V57/O57-1 -> 0.43143346 | M57: =IF($B56=0,"",(V57/O57)^(1/$B56)-1) -> 0.1269995 | O57: 100 | P57: =IF(E57="",O57,O57*(1+E57)) -> 100 | Q57: =IF(F57="",P57,P57*(1+F57)) -> 100 | R57: =IF(G57="",Q57,Q57*(1+G57)) -> 100 | S57: =IF(H57="",R57,R57*(1+H57)) -> 100 | T57: =IF(I57="",S57,S57*(1+I57)) -> 127.90402 | U57: =IF(J57="",T57,T57*(1+J57)) -> 133.80031 | V57: =IF(K57="",U57,U57*(1+K57)) -> 143.14335
D58: Income: | E58: =IF(SUMIFS($C$120:$C$239,$A$120:$A$239,$A$56,$B$120:$B$239,E$11)=0,"",SUMIFS($L$120:$L$239,$A$120:$A$239,$A$56,$B$120:$B$239,E$11)) | F58: =IF(SUMIFS($C$120:$C$239,$A$120:$A$239,$A$56,$B$120:$B$239,F$11)=0,"",SUMIFS($L$120:$L$239,$A$120:$A$239,$A$56,$B$120:$B$239,F$11)) | G58: =IF(SUMIFS($C$120:$C$239,$A$120:$A$239,$A$56,$B$120:$B$239,G$11)=0,"",SUMIFS($L$120:$L$239,$A$120:$A$239,$A$56,$B$120:$B$239,G$11)) | H58: =IF(SUMIFS($C$120:$C$239,$A$120:$A$239,$A$56,$B$120:$B$239,H$11)=0,"",SUMIFS($L$120:$L$239,$A$120:$A$239,$A$56,$B$120:$B$239,H$11)) | I58: =IF(SUMIFS($C$120:$C$239,$A$120:$A$239,$A$56,$B$120:$B$239,I$11)=0,"",SUMIFS($L$120:$L$239,$A$120:$A$239,$A$56,$B$120:$B$239,I$11)) -> 0.030468659 | J58: =IF(SUMIFS($C$120:$C$239,$A$120:$A$239,$A$56,$B$120:$B$239,J$11)=0,"",SUMIFS($L$120:$L$239,$A$120:$A$239,$A$56,$B$120:$B$239,J$11)) -> 0.032729797 | K58: =IF(SUMIFS($C$120:$C$239,$A$120:$A$239,$A$56,$B$120:$B$239,K$11)=0,"",SUMIFS($L$120:$L$239,$A$120:$A$239,$A$56,$B$120:$B$239,K$11)) -> 0 | L58: =V58/O58-1 -> 0.064195689 | M58: =IF($B56=0,"",(V58/O58)^(1/$B56)-1) -> 0.020956327 | O58: 100 | P58: =IF(E58="",O58,O58*(1+E58)) -> 100 | Q58: =IF(F58="",P58,P58*(1+F58)) -> 100 | R58: =IF(G58="",Q58,Q58*(1+G58)) -> 100 | S58: =IF(H58="",R58,R58*(1+H58)) -> 100 | T58: =IF(I58="",S58,S58*(1+I58)) -> 103.04687 | U58: =IF(J58="",T58,T58*(1+J58)) -> 106.41957 | V58: =IF(K58="",U58,U58*(1+K58)) -> 106.41957
A59: Fazenda Palmeira | B59: =COUNT(E59:K59) -> 2 | C59: =SUMIFS($E$120:$E$239,$A$120:$A$239,$A59,$B$120:$B$239,K$11)/1000 -> 0 | D59: Total: | E59: =IF(SUMIFS($C$120:$C$239,$A$120:$A$239,$A$59,$B$120:$B$239,E$11)=0,"",SUMIFS($N$120:$N$239,$A$120:$A$239,$A$59,$B$120:$B$239,E$11)) -> 0.28375593 | F59: =IF(SUMIFS($C$120:$C$239,$A$120:$A$239,$A$59,$B$120:$B$239,F$11)=0,"",SUMIFS($N$120:$N$239,$A$120:$A$239,$A$59,$B$120:$B$239,F$11)) -> 0.075217736 | G59: =IF(SUMIFS($C$120:$C$239,$A$120:$A$239,$A$59,$B$120:$B$239,G$11)=0,"",SUMIFS($N$120:$N$239,$A$120:$A$239,$A$59,$B$120:$B$239,G$11)) | H59: =IF(SUMIFS($C$120:$C$239,$A$120:$A$239,$A$59,$B$120:$B$239,H$11)=0,"",SUMIFS($N$120:$N$239,$A$120:$A$239,$A$59,$B$120:$B$239,H$11)) | I59: =IF(SUMIFS($C$120:$C$239,$A$120:$A$239,$A$59,$B$120:$B$239,I$11)=0,"",SUMIFS($N$120:$N$239,$A$120:$A$239,$A$59,$B$120:$B$239,I$11)) | J59: =IF(SUMIFS($C$120:$C$239,$A$120:$A$239,$A$59,$B$120:$B$239,J$11)=0,"",SUMIFS($N$120:$N$239,$A$120:$A$239,$A$59,$B$120:$B$239,J$11)) | K59: =IF(SUMIFS($C$120:$C$239,$A$120:$A$239,$A$59,$B$120:$B$239,K$11)=0,"",SUMIFS($N$120:$N$239,$A$120:$A$239,$A$59,$B$120:$B$239,K$11)) | L59: =V59/O59-1 -> 0.38031714 | M59: =IF($B59=0,"",(V59/O59)^(1/$B59)-1) -> 0.17486899 | O59: 100 | P59: =IF(E59="",O59,O59*(1+E59)) -> 128.37559 | Q59: =IF(F59="",P59,P59*(1+F59)) -> 138.03171 | R59: =IF(G59="",Q59,Q59*(1+G59)) -> 138.03171 | S59: =IF(H59="",R59,R59*(1+H59)) -> 138.03171 | T59: =IF(I59="",S59,S59*(1+I59)) -> 138.03171 | U59: =IF(J59="",T59,T59*(1+J59)) -> 138.03171 | V59: =IF(K59="",U59,U59*(1+K59)) -> 138.03171
D60: Appreciation: | E60: =IF(SUMIFS($C$120:$C$239,$A$120:$A$239,$A$59,$B$120:$B$239,E$11)=0,"",SUMIFS($M$120:$M$239,$A$120:$A$239,$A$59,$B$120:$B$239,E$11)) -> 0.23645704 | F60: =IF(SUMIFS($C$120:$C$239,$A$120:$A$239,$A$59,$B$120:$B$239,F$11)=0,"",SUMIFS($M$120:$M$239,$A$120:$A$239,$A$59,$B$120:$B$239,F$11)) -> 0.075217736 | G60: =IF(SUMIFS($C$120:$C$239,$A$120:$A$239,$A$59,$B$120:$B$239,G$11)=0,"",SUMIFS($M$120:$M$239,$A$120:$A$239,$A$59,$B$120:$B$239,G$11)) | H60: =IF(SUMIFS($C$120:$C$239,$A$120:$A$239,$A$59,$B$120:$B$239,H$11)=0,"",SUMIFS($M$120:$M$239,$A$120:$A$239,$A$59,$B$120:$B$239,H$11)) | I60: =IF(SUMIFS($C$120:$C$239,$A$120:$A$239,$A$59,$B$120:$B$239,I$11)=0,"",SUMIFS($M$120:$M$239,$A$120:$A$239,$A$59,$B$120:$B$239,I$11)) | J60: =IF(SUMIFS($C$120:$C$239,$A$120:$A$239,$A$59,$B$120:$B$239,J$11)=0,"",SUMIFS($M$120:$M$239,$A$120:$A$239,$A$59,$B$120:$B$239,J$11)) | K60: =IF(SUMIFS($C$120:$C$239,$A$120:$A$239,$A$59,$B$120:$B$239,K$11)=0,"",SUMIFS($M$120:$M$239,$A$120:$A$239,$A$59,$B$120:$B$239,K$11)) | L60: =V60/O60-1 -> 0.32946053 | M60: =IF($B59=0,"",(V60/O60)^(1/$B59)-1) -> 0.15302235 | O60: 100 | P60: =IF(E60="",O60,O60*(1+E60)) -> 123.6457 | Q60: =IF(F60="",P60,P60*(1+F60)) -> 132.94605 | R60: =IF(G60="",Q60,Q60*(1+G60)) -> 132.94605 | S60: =IF(H60="",R60,R60*(1+H60)) -> 132.94605 | T60: =IF(I60="",S60,S60*(1+I60)) -> 132.94605 | U60: =IF(J60="",T60,T60*(1+J60)) -> 132.94605 | V60: =IF(K60="",U60,U60*(1+K60)) -> 132.94605
D61: Income: | E61: =IF(SUMIFS($C$120:$C$239,$A$120:$A$239,$A$59,$B$120:$B$239,E$11)=0,"",SUMIFS($L$120:$L$239,$A$120:$A$239,$A$59,$B$120:$B$239,E$11)) -> 0.04729889 | F61: =IF(SUMIFS($C$120:$C$239,$A$120:$A$239,$A$59,$B$120:$B$239,F$11)=0,"",SUMIFS($L$120:$L$239,$A$120:$A$239,$A$59,$B$120:$B$239,F$11)) -> 0 | G61: =IF(SUMIFS($C$120:$C$239,$A$120:$A$239,$A$59,$B$120:$B$239,G$11)=0,"",SUMIFS($L$120:$L$239,$A$120:$A$239,$A$59,$B$120:$B$239,G$11)) | H61: =IF(SUMIFS($C$120:$C$239,$A$120:$A$239,$A$59,$B$120:$B$239,H$11)=0,"",SUMIFS($L$120:$L$239,$A$120:$A$239,$A$59,$B$120:$B$239,H$11)) | I61: =IF(SUMIFS($C$120:$C$239,$A$120:$A$239,$A$59,$B$120:$B$239,I$11)=0,"",SUMIFS($L$120:$L$239,$A$120:$A$239,$A$59,$B$120:$B$239,I$11)) | J61: =IF(SUMIFS($C$120:$C$239,$A$120:$A$239,$A$59,$B$120:$B$239,J$11)=0,"",SUMIFS($L$120:$L$239,$A$120:$A$239,$A$59,$B$120:$B$239,J$11)) | K61: =IF(SUMIFS($C$120:$C$239,$A$120:$A$239,$A$59,$B$120:$B$239,K$11)=0,"",SUMIFS($L$120:$L$239,$A$120:$A$239,$A$59,$B$120:$B$239,K$11)) | L61: =V61/O61-1 -> 0.04729889 | M61: =IF($B59=0,"",(V61/O61)^(1/$B59)-1) -> 0.023376221 | O61: 100 | P61: =IF(E61="",O61,O61*(1+E61)) -> 104.72989 | Q61: =IF(F61="",P61,P61*(1+F61)) -> 104.72989 | R61: =IF(G61="",Q61,Q61*(1+G61)) -> 104.72989 | S61: =IF(H61="",R61,R61*(1+H61)) -> 104.72989 | T61: =IF(I61="",S61,S61*(1+I61)) -> 104.72989 | U61: =IF(J61="",T61,T61*(1+J61)) -> 104.72989 | V61: =IF(K61="",U61,U61*(1+K61)) -> 104.72989
A64: FARMLAND INDEX - US$ (NCREIF style) | E64: Returns | O64: Index Values (Dec 2008 = 100)
A65: Farm | B65: Years | C65: Market Value (US$ mm, 2015) | E65: 2009 | F65: =E65+1 -> 2010 | G65: =F65+1 -> 2011 | H65: =G65+1 -> 2012 | I65: =H65+1 -> 2013 | J65: =I65+1 -> 2014 | K65: =J65+1 -> 2015 | L65: Cumulative | M65: Annualized | O65: =E65-1 -> 2008 | P65: =O65+1 -> 2009 | Q65: =P65+1 -> 2010 | R65: =Q65+1 -> 2011 | S65: =R65+1 -> 2012 | T65: =S65+1 -> 2013 | U65: =T65+1 -> 2014 | V65: =U65+1 -> 2015
A66: Total Farmland | B66: =COUNT(E66:K66) -> 7 | C66: =K70 -> 1002.4872 | D66: Total: | E66: =IF(E68="","",E68+E67) -> 0.10973938 | F66: =IF(F68="","",F68+F67) -> 0.1962789 | G66: =IF(G68="","",G68+G67) -> 0.30075043 | H66: =IF(H68="","",H68+H67) -> -0.069603426 | I66: =IF(I68="","",I68+I67) -> 0.055602856 | J66: =IF(J68="","",J68+J67) -> 0.21700209 | K66: =IF(K68="","",K68+K67) -> -0.27553788 | L66: =V66/O66-1 -> 0.49528192 | M66: =IF($B66=0,"",(V66/O66)^(1/$B66)-1) -> 0.059157243 | O66: 100 | P66: =IF(E66="",O66,O66*(1+E66)) -> 110.97394 | Q66: =IF(F66="",P66,P66*(1+F66)) -> 132.75578 | R66: =IF(G66="",Q66,Q66*(1+G66)) -> 172.68214 | S66: =IF(H66="",R66,R66*(1+H66)) -> 160.66287 | T66: =IF(I66="",S66,S66*(1+I66)) -> 169.59618 | U66: =IF(J66="",T66,T66*(1+J66)) -> 206.39891 | V66: =IF(K66="",U66,U66*(1+K66)) -> 149.52819
D67: Appreciation: | E67: =IF(SUMIFS($J$244:$J$363,$B$244:$B$363,E$65)=0,"",SUMIFS($K$244:$K$363,$B$244:$B$363,E$65)/SUMIFS($J$244:$J$363,$B$244:$B$363,E$65)) -> 0.087518189 | F67: =IF(SUMIFS($J$244:$J$363,$B$244:$B$363,F$65)=0,"",SUMIFS($K$244:$K$363,$B$244:$B$363,F$65)/SUMIFS($J$244:$J$363,$B$244:$B$363,F$65)) -> 0.17054002 | G67: =IF(SUMIFS($J$244:$J$363,$B$244:$B$363,G$65)=0,"",SUMIFS($K$244:$K$363,$B$244:$B$363,G$65)/SUMIFS($J$244:$J$363,$B$244:$B$363,G$65)) -> 0.28257707 | H67: =IF(SUMIFS($J$244:$J$363,$B$244:$B$363,H$65)=0,"",SUMIFS($K$244:$K$363,$B$244:$B$363,H$65)/SUMIFS($J$244:$J$363,$B$244:$B$363,H$65)) -> -0.093561903 | I67: =IF(SUMIFS($J$244:$J$363,$B$244:$B$363,I$65)=0,"",SUMIFS($K$244:$K$363,$B$244:$B$363,I$65)/SUMIFS($J$244:$J$363,$B$244:$B$363,I$65)) -> 0.033918779 | J67: =IF(SUMIFS($J$244:$J$363,$B$244:$B$363,J$65)=0,"",SUMIFS($K$244:$K$363,$B$244:$B$363,J$65)/SUMIFS($J$244:$J$363,$B$244:$B$363,J$65)) -> 0.19571567 | K67: =IF(SUMIFS($J$244:$J$363,$B$244:$B$363,K$65)=0,"",SUMIFS($K$244:$K$363,$B$244:$B$363,K$65)/SUMIFS($J$244:$J$363,$B$244:$B$363,K$65)) -> -0.2893436 | L67: =V67/O67-1 -> 0.30022476 | M67: =IF($B66=0,"",(V67/O67)^(1/$B66)-1) -> 0.038217506 | O67: 100 | P67: =IF(E67="",O67,O67*(1+E67)) -> 108.75182 | Q67: =IF(F67="",P67,P67*(1+F67)) -> 127.29836 | R67: =IF(G67="",Q67,Q67*(1+G67)) -> 163.26995 | S67: =IF(H67="",R67,R67*(1+H67)) -> 147.99411 | T67: =IF(I67="",S67,S67*(1+I67)) -> 153.01388 | U67: =IF(J67="",T67,T67*(1+J67)) -> 182.9611 | V67: =IF(K67="",U67,U67*(1+K67)) -> 130.02248
D68: Income: | E68: =IF(SUMIFS($J$244:$J$363,$B$244:$B$363,E$65)=0,"",SUMIFS($F$244:$F$363,$B$244:$B$363,E$65,$C$244:$C$363,1)/SUMIFS($J$244:$J$363,$B$244:$B$363,E$65)) -> 0.02222119 | F68: =IF(SUMIFS($J$244:$J$363,$B$244:$B$363,F$65)=0,"",SUMIFS($F$244:$F$363,$B$244:$B$363,F$65,$C$244:$C$363,1)/SUMIFS($J$244:$J$363,$B$244:$B$363,F$65)) -> 0.025738871 | G68: =IF(SUMIFS($J$244:$J$363,$B$244:$B$363,G$65)=0,"",SUMIFS($F$244:$F$363,$B$244:$B$363,G$65,$C$244:$C$363,1)/SUMIFS($J$244:$J$363,$B$244:$B$363,G$65)) -> 0.018173366 | H68: =IF(SUMIFS($J$244:$J$363,$B$244:$B$363,H$65)=0,"",SUMIFS($F$244:$F$363,$B$244:$B$363,H$65,$C$244:$C$363,1)/SUMIFS($J$244:$J$363,$B$244:$B$363,H$65)) -> 0.023958477 | I68: =IF(SUMIFS($J$244:$J$363,$B$244:$B$363,I$65)=0,"",SUMIFS($F$244:$F$363,$B$244:$B$363,I$65,$C$244:$C$363,1)/SUMIFS($J$244:$J$363,$B$244:$B$363,I$65)) -> 0.021684077 | J68: =IF(SUMIFS($J$244:$J$363,$B$244:$B$363,J$65)=0,"",SUMIFS($F$244:$F$363,$B$244:$B$363,J$65,$C$244:$C$363,1)/SUMIFS($J$244:$J$363,$B$244:$B$363,J$65)) -> 0.021286422 | K68: =IF(SUMIFS($J$244:$J$363,$B$244:$B$363,K$65)=0,"",SUMIFS($F$244:$F$363,$B$244:$B$363,K$65,$C$244:$C$363,1)/SUMIFS($J$244:$J$363,$B$244:$B$363,K$65)) -> 0.013805723 | L68: =V68/O68-1 -> 0.15639097 | M68: =IF($B66=0,"",(V68/O68)^(1/$B66)-1) -> 0.020974643 | O68: 100 | P68: =IF(E68="",O68,O68*(1+E68)) -> 102.22212 | Q68: =IF(F68="",P68,P68*(1+F68)) -> 104.8532 | R68: =IF(G68="",Q68,Q68*(1+G68)) -> 106.75874 | S68: =IF(H68="",R68,R68*(1+H68)) -> 109.31651 | T68: =IF(I68="",S68,S68*(1+I68)) -> 111.68694 | U68: =IF(J68="",T68,T68*(1+J68)) -> 114.06436 | V68: =IF(K68="",U68,U68*(1+K68)) -> 115.6391
D69: Props: | E69: =COUNTIFS($B$244:$B$363,E$65,$E$244:$E$363,">0") -> 11 | F69: =COUNTIFS($B$244:$B$363,F$65,$E$244:$E$363,">0") -> 11 | G69: =COUNTIFS($B$244:$B$363,G$65,$E$244:$E$363,">0") -> 10 | H69: =COUNTIFS($B$244:$B$363,H$65,$E$244:$E$363,">0") -> 14 | I69: =COUNTIFS($B$244:$B$363,I$65,$E$244:$E$363,">0") -> 14 | J69: =COUNTIFS($B$244:$B$363,J$65,$E$244:$E$363,">0") -> 13 | K69: =COUNTIFS($B$244:$B$363,K$65,$E$244:$E$363,">0") -> 13
D70: MV (US$ mm): | E70: =SUMIFS($E$244:$E$363,$B$244:$B$363,E$65)/1000 -> 742.794 | F70: =SUMIFS($E$244:$E$363,$B$244:$B$363,F$65)/1000 -> 867.86057 | G70: =SUMIFS($E$244:$E$363,$B$244:$B$363,G$65)/1000 -> 1090.5732 | H70: =SUMIFS($E$244:$E$363,$B$244:$B$363,H$65)/1000 -> 1140.2403 | I70: =SUMIFS($E$244:$E$363,$B$244:$B$363,I$65)/1000 -> 1178.501 | J70: =SUMIFS($E$244:$E$363,$B$244:$B$363,J$65)/1000 -> 1406.7231 | K70: =SUMIFS($E$244:$E$363,$B$244:$B$363,K$65)/1000 -> 1002.4872
A71: Fazenda Pamplona | B71: =COUNT(E71:K71) -> 7 | C71: =SUMIFS($E$244:$E$363,$A$244:$A$363,$A71,$B$244:$B$363,K$65)/1000 -> 85.725231 | D71: Total: | E71: =IF(SUMIFS($C$244:$C$363,$A$244:$A$363,$A$71,$B$244:$B$363,E$65)=0,"",SUMIFS($N$244:$N$363,$A$244:$A$363,$A$71,$B$244:$B$363,E$65)) -> -0.041394341 | F71: =IF(SUMIFS($C$244:$C$363,$A$244:$A$363,$A$71,$B$244:$B$363,F$65)=0,"",SUMIFS($N$244:$N$363,$A$244:$A$363,$A$71,$B$244:$B$363,F$65)) -> 0.25984289 | G71: =IF(SUMIFS($C$244:$C$363,$A$244:$A$363,$A$71,$B$244:$B$363,G$65)=0,"",SUMIFS($N$244:$N$363,$A$244:$A$363,$A$71,$B$244:$B$363,G$65)) -> 0.1991823 | H71: =IF(SUMIFS($C$244:$C$363,$A$244:$A$363,$A$71,$B$244:$B$363,H$65)=0,"",SUMIFS($N$244:$N$363,$A$244:$A$363,$A$71,$B$244:$B$363,H$65)) -> -0.019478599 | I71: =IF(SUMIFS($C$244:$C$363,$A$244:$A$363,$A$71,$B$244:$B$363,I$65)=0,"",SUMIFS($N$244:$N$363,$A$244:$A$363,$A$71,$B$244:$B$363,I$65)) -> -0.047243551 | J71: =IF(SUMIFS($C$244:$C$363,$A$244:$A$363,$A$71,$B$244:$B$363,J$65)=0,"",SUMIFS($N$244:$N$363,$A$244:$A$363,$A$71,$B$244:$B$363,J$65)) -> 0.23439531 | K71: =IF(SUMIFS($C$244:$C$363,$A$244:$A$363,$A$71,$B$244:$B$363,K$65)=0,"",SUMIFS($N$244:$N$363,$A$244:$A$363,$A$71,$B$244:$B$363,K$65)) -> -0.26456424 | L71: =V71/O71-1 -> 0.22822962 | M71: =IF($B71=0,"",(V71/O71)^(1/$B71)-1) -> 0.029803169 | O71: 100 | P71: =IF(E71="",O71,O71*(1+E71)) -> 95.860566 | Q71: =IF(F71="",P71,P71*(1+F71)) -> 120.76925 | R71: =IF(G71="",Q71,Q71*(1+G71)) -> 144.82435 | S71: =IF(H71="",R71,R71*(1+H71)) -> 142.00337 | T71: =IF(I71="",S71,S71*(1+I71)) -> 135.29463 | U71: =IF(J71="",T71,T71*(1+J71)) -> 167.00706 | V71: =IF(K71="",U71,U71*(1+K71)) -> 122.82296
D72: Appreciation: | E72: =IF(SUMIFS($C$244:$C$363,$A$244:$A$363,$A$71,$B$244:$B$363,E$65)=0,"",SUMIFS($M$244:$M$363,$A$244:$A$363,$A$71,$B$244:$B$363,E$65)) -> -0.078735513 | F72: =IF(SUMIFS($C$244:$C$363,$A$244:$A$363,$A$71,$B$244:$B$363,F$65)=0,"",SUMIFS($M$244:$M$363,$A$244:$A$363,$A$71,$B$244:$B$363,F$65)) -> 0.21321364 | G72: =IF(SUMIFS($C$244:$C$363,$A$244:$A$363,$A$71,$B$244:$B$363,G$65)=0,"",SUMIFS($M$244:$M$363,$A$244:$A$363,$A$71,$B$244:$B$363,G$65)) -> 0.17645788 | H72: =IF(SUMIFS($C$244:$C$363,$A$244:$A$363,$A$71,$B$244:$B$363,H$65)=0,"",SUMIFS($M$244:$M$363,$A$244:$A$363,$A$71,$B$244:$B$363,H$65)) -> -0.048523395 | I72: =IF(SUMIFS($C$244:$C$363,$A$244:$A$363,$A$71,$B$244:$B$363,I$65)=0,"",SUMIFS($M$244:$M$363,$A$244:$A$363,$A$71,$B$244:$B$363,I$65)) -> -0.071262548 | J72: =IF(SUMIFS($C$244:$C$363,$A$244:$A$363,$A$71,$B$244:$B$363,J$65)=0,"",SUMIFS($M$244:$M$363,$A$244:$A$363,$A$71,$B$244:$B$363,J$65)) -> 0.20902365 | K72: =IF(SUMIFS($C$244:$C$363,$A$244:$A$363,$A$71,$B$244:$B$363,K$65)=0,"",SUMIFS($M$244:$M$363,$A$244:$A$363,$A$71,$B$244:$B$363,K$65)) -> -0.2826048 | L72: =V72/O72-1 -> 0.0078185215 | M72: =IF($B71=0,"",(V72/O72)^(1/$B71)-1) -> 0.0011132071 | O72: 100 | P72: =IF(E72="",O72,O72*(1+E72)) -> 92.126449 | Q72: =IF(F72="",P72,P72*(1+F72)) -> 111.76906 | R72: =IF(G72="",Q72,Q72*(1+G72)) -> 131.4916 | S72: =IF(H72="",R72,R72*(1+H72)) -> 125.11118 | T72: =IF(I72="",S72,S72*(1+I72)) -> 116.19544 | U72: =IF(J72="",T72,T72*(1+J72)) -> 140.48303 | V72: =IF(K72="",U72,U72*(1+K72)) -> 100.78185
D73: Income: | E73: =IF(SUMIFS($C$244:$C$363,$A$244:$A$363,$A$71,$B$244:$B$363,E$65)=0,"",SUMIFS($L$244:$L$363,$A$244:$A$363,$A$71,$B$244:$B$363,E$65)) -> 0.037341173 | F73: =IF(SUMIFS($C$244:$C$363,$A$244:$A$363,$A$71,$B$244:$B$363,F$65)=0,"",SUMIFS($L$244:$L$363,$A$244:$A$363,$A$71,$B$244:$B$363,F$65)) -> 0.046629252 | G73: =IF(SUMIFS($C$244:$C$363,$A$244:$A$363,$A$71,$B$244:$B$363,G$65)=0,"",SUMIFS($L$244:$L$363,$A$244:$A$363,$A$71,$B$244:$B$363,G$65)) -> 0.022724419 | H73: =IF(SUMIFS($C$244:$C$363,$A$244:$A$363,$A$71,$B$244:$B$363,H$65)=0,"",SUMIFS($L$244:$L$363,$A$244:$A$363,$A$71,$B$244:$B$363,H$65)) -> 0.029044796 | I73: =IF(SUMIFS($C$244:$C$363,$A$244:$A$363,$A$71,$B$244:$B$363,I$65)=0,"",SUMIFS($L$244:$L$363,$A$244:$A$363,$A$71,$B$244:$B$363,I$65)) -> 0.024018997 | J73: =IF(SUMIFS($C$244:$C$363,$A$244:$A$363,$A$71,$B$244:$B$363,J$65)=0,"",SUMIFS($L$244:$L$363,$A$244:$A$363,$A$71,$B$244:$B$363,J$65)) -> 0.025371657 | K73: =IF(SUMIFS($C$244:$C$363,$A$244:$A$363,$A$71,$B$244:$B$363,K$65)=0,"",SUMIFS($L$244:$L$363,$A$244:$A$363,$A$71,$B$244:$B$363,K$65)) -> 0.018040555 | L73: =V73/O73-1 -> 0.2214109 | M73: =IF($B71=0,"",(V73/O73)^(1/$B71)-1) -> 0.028984487 | O73: 100 | P73: =IF(E73="",O73,O73*(1+E73)) -> 103.73412 | Q73: =IF(F73="",P73,P73*(1+F73)) -> 108.57116 | R73: =IF(G73="",Q73,Q73*(1+G73)) -> 111.03838 | S73: =IF(H73="",R73,R73*(1+H73)) -> 114.26347 | T73: =IF(I73="",S73,S73*(1+I73)) -> 117.00796 | U73: =IF(J73="",T73,T73*(1+J73)) -> 119.97664 | V73: =IF(K73="",U73,U73*(1+K73)) -> 122.14109
A74: Fazenda Planalto | B74: =COUNT(E74:K74) -> 7 | C74: =SUMIFS($E$244:$E$363,$A$244:$A$363,$A74,$B$244:$B$363,K$65)/1000 -> 139.5503 | D74: Total: | E74: =IF(SUMIFS($C$244:$C$363,$A$244:$A$363,$A$74,$B$244:$B$363,E$65)=0,"",SUMIFS($N$244:$N$363,$A$244:$A$363,$A$74,$B$244:$B$363,E$65)) -> -0.025900953 | F74: =IF(SUMIFS($C$244:$C$363,$A$244:$A$363,$A$74,$B$244:$B$363,F$65)=0,"",SUMIFS($N$244:$N$363,$A$244:$A$363,$A$74,$B$244:$B$363,F$65)) -> 0.23796286 | G74: =IF(SUMIFS($C$244:$C$363,$A$244:$A$363,$A$74,$B$244:$B$363,G$65)=0,"",SUMIFS($N$244:$N$363,$A$244:$A$363,$A$74,$B$244:$B$363,G$65)) -> 0.23632209 | H74: =IF(SUMIFS($C$244:$C$363,$A$244:$A$363,$A$74,$B$244:$B$363,H$65)=0,"",SUMIFS($N$244:$N$363,$A$244:$A$363,$A$74,$B$244:$B$363,H$65)) -> -0.04496908 | I74: =IF(SUMIFS($C$244:$C$363,$A$244:$A$363,$A$74,$B$244:$B$363,I$65)=0,"",SUMIFS($N$244:$N$363,$A$244:$A$363,$A$74,$B$244:$B$363,I$65)) -> -0.06102223 | J74: =IF(SUMIFS($C$244:$C$363,$A$244:$A$363,$A$74,$B$244:$B$363,J$65)=0,"",SUMIFS($N$244:$N$363,$A$244:$A$363,$A$74,$B$244:$B$363,J$65)) -> 0.40314676 | K74: =IF(SUMIFS($C$244:$C$363,$A$244:$A$363,$A$74,$B$244:$B$363,K$65)=0,"",SUMIFS($N$244:$N$363,$A$244:$A$363,$A$74,$B$244:$B$363,K$65)) -> -0.28777253 | L74: =V74/O74-1 -> 0.33609371 | M74: =IF($B74=0,"",(V74/O74)^(1/$B74)-1) -> 0.042261517 | O74: 100 | P74: =IF(E74="",O74,O74*(1+E74)) -> 97.409905 | Q74: =IF(F74="",P74,P74*(1+F74)) -> 120.58984 | R74: =IF(G74="",Q74,Q74*(1+G74)) -> 149.08789 | S74: =IF(H74="",R74,R74*(1+H74)) -> 142.38354 | T74: =IF(I74="",S74,S74*(1+I74)) -> 133.69498 | U74: =IF(J74="",T74,T74*(1+J74)) -> 187.59368 | V74: =IF(K74="",U74,U74*(1+K74)) -> 133.60937
D75: Appreciation: | E75: =IF(SUMIFS($C$244:$C$363,$A$244:$A$363,$A$74,$B$244:$B$363,E$65)=0,"",SUMIFS($M$244:$M$363,$A$244:$A$363,$A$74,$B$244:$B$363,E$65)) -> -0.053972514 | F75: =IF(SUMIFS($C$244:$C$363,$A$244:$A$363,$A$74,$B$244:$B$363,F$65)=0,"",SUMIFS($M$244:$M$363,$A$244:$A$363,$A$74,$B$244:$B$363,F$65)) -> 0.20231079 | G75: =IF(SUMIFS($C$244:$C$363,$A$244:$A$363,$A$74,$B$244:$B$363,G$65)=0,"",SUMIFS($M$244:$M$363,$A$244:$A$363,$A$74,$B$244:$B$363,G$65)) -> 0.21875866 | H75: =IF(SUMIFS($C$244:$C$363,$A$244:$A$363,$A$74,$B$244:$B$363,H$65)=0,"",SUMIFS($M$244:$M$363,$A$244:$A$363,$A$74,$B$244:$B$363,H$65)) -> -0.067654689 | I75: =IF(SUMIFS($C$244:$C$363,$A$244:$A$363,$A$74,$B$244:$B$363,I$65)=0,"",SUMIFS($M$244:$M$363,$A$244:$A$363,$A$74,$B$244:$B$363,I$65)) -> -0.081356806 | J75: =IF(SUMIFS($C$244:$C$363,$A$244:$A$363,$A$74,$B$244:$B$363,J$65)=0,"",SUMIFS($M$244:$M$363,$A$244:$A$363,$A$74,$B$244:$B$363,J$65)) -> 0.37525809 | K75: =IF(SUMIFS($C$244:$C$363,$A$244:$A$363,$A$74,$B$244:$B$363,K$65)=0,"",SUMIFS($M$244:$M$363,$A$244:$A$363,$A$74,$B$244:$B$363,K$65)) -> -0.30463908 | L75: =V75/O75-1 -> 0.13541951 | M75: =IF($B74=0,"",(V75/O75)^(1/$B74)-1) -> 0.018308758 | O75: 100 | P75: =IF(E75="",O75,O75*(1+E75)) -> 94.602749 | Q75: =IF(F75="",P75,P75*(1+F75)) -> 113.74191 | R75: =IF(G75="",Q75,Q75*(1+G75)) -> 138.62393 | S75: =IF(H75="",R75,R75*(1+H75)) -> 129.24537 | T75: =IF(I75="",S75,S75*(1+I75)) -> 118.73038 | U75: =IF(J75="",T75,T75*(1+J75)) -> 163.28492 | V75: =IF(K75="",U75,U75*(1+K75)) -> 113.54195
D76: Income: | E76: =IF(SUMIFS($C$244:$C$363,$A$244:$A$363,$A$74,$B$244:$B$363,E$65)=0,"",SUMIFS($L$244:$L$363,$A$244:$A$363,$A$74,$B$244:$B$363,E$65)) -> 0.02807156 | F76: =IF(SUMIFS($C$244:$C$363,$A$244:$A$363,$A$74,$B$244:$B$363,F$65)=0,"",SUMIFS($L$244:$L$363,$A$244:$A$363,$A$74,$B$244:$B$363,F$65)) -> 0.035652072 | G76: =IF(SUMIFS($C$244:$C$363,$A$244:$A$363,$A$74,$B$244:$B$363,G$65)=0,"",SUMIFS($L$244:$L$363,$A$244:$A$363,$A$74,$B$244:$B$363,G$65)) -> 0.017563422 | H76: =IF(SUMIFS($C$244:$C$363,$A$244:$A$363,$A$74,$B$244:$B$363,H$65)=0,"",SUMIFS($L$244:$L$363,$A$244:$A$363,$A$74,$B$244:$B$363,H$65)) -> 0.022685609 | I76: =IF(SUMIFS($C$244:$C$363,$A$244:$A$363,$A$74,$B$244:$B$363,I$65)=0,"",SUMIFS($L$244:$L$363,$A$244:$A$363,$A$74,$B$244:$B$363,I$65)) -> 0.020334575 | J76: =IF(SUMIFS($C$244:$C$363,$A$244:$A$363,$A$74,$B$244:$B$363,J$65)=0,"",SUMIFS($L$244:$L$363,$A$244:$A$363,$A$74,$B$244:$B$363,J$65)) -> 0.02788867 | K76: =IF(SUMIFS($C$244:$C$363,$A$244:$A$363,$A$74,$B$244:$B$363,K$65)=0,"",SUMIFS($L$244:$L$363,$A$244:$A$363,$A$74,$B$244:$B$363,K$65)) -> 0.016866549 | L76: =V76/O76-1 -> 0.18166262 | M76: =IF($B74=0,"",(V76/O76)^(1/$B74)-1) -> 0.024132655 | O76: 100 | P76: =IF(E76="",O76,O76*(1+E76)) -> 102.80716 | Q76: =IF(F76="",P76,P76*(1+F76)) -> 106.47244 | R76: =IF(G76="",Q76,Q76*(1+G76)) -> 108.34246 | S76: =IF(H76="",R76,R76*(1+H76)) -> 110.80028 | T76: =IF(I76="",S76,S76*(1+I76)) -> 113.05336 | U76: =IF(J76="",T76,T76*(1+J76)) -> 116.20626 | V76: =IF(K76="",U76,U76*(1+K76)) -> 118.16626
A77: Fazenda Planeste | B77: =COUNT(E77:K77) -> 7 | C77: =SUMIFS($E$244:$E$363,$A$244:$A$363,$A77,$B$244:$B$363,K$65)/1000 -> 69.119467 | D77: Total: | E77: =IF(SUMIFS($C$244:$C$363,$A$244:$A$363,$A$77,$B$244:$B$363,E$65)=0,"",SUMIFS($N$244:$N$363,$A$244:$A$363,$A$77,$B$244:$B$363,E$65)) -> -0.044531814 | F77: =IF(SUMIFS($C$244:$C$363,$A$244:$A$363,$A$77,$B$244:$B$363,F$65)=0,"",SUMIFS($N$244:$N$363,$A$244:$A$363,$A$77,$B$244:$B$363,F$65)) -> 0.45107269 | G77: =IF(SUMIFS($C$244:$C$363,$A$244:$A$363,$A$77,$B$244:$B$363,G$65)=0,"",SUMIFS($N$244:$N$363,$A$244:$A$363,$A$77,$B$244:$B$363,G$65)) -> 0.3404723 | H77: =IF(SUMIFS($C$244:$C$363,$A$244:$A$363,$A$77,$B$244:$B$363,H$65)=0,"",SUMIFS($N$244:$N$363,$A$244:$A$363,$A$77,$B$244:$B$363,H$65)) -> -0.051131287 | I77: =IF(SUMIFS($C$244:$C$363,$A$244:$A$363,$A$77,$B$244:$B$363,I$65)=0,"",SUMIFS($N$244:$N$363,$A$244:$A$363,$A$77,$B$244:$B$363,I$65)) -> 0.029177346 | J77: =IF(SUMIFS($C$244:$C$363,$A$244:$A$363,$A$77,$B$244:$B$363,J$65)=0,"",SUMIFS($N$244:$N$363,$A$244:$A$363,$A$77,$B$244:$B$363,J$65)) -> 0.079115442 | K77: =IF(SUMIFS($C$244:$C$363,$A$244:$A$363,$A$77,$B$244:$B$363,K$65)=0,"",SUMIFS($N$244:$N$363,$A$244:$A$363,$A$77,$B$244:$B$363,K$65)) -> -0.29976789 | L77: =V77/O77-1 -> 0.37141697 | M77: =IF($B77=0,"",(V77/O77)^(1/$B77)-1) -> 0.046154062 | O77: 100 | P77: =IF(E77="",O77,O77*(1+E77)) -> 95.546819 | Q77: =IF(F77="",P77,P77*(1+F77)) -> 138.64538 | R77: =IF(G77="",Q77,Q77*(1+G77)) -> 185.85029 | S77: =IF(H77="",R77,R77*(1+H77)) -> 176.34753 | T77: =IF(I77="",S77,S77*(1+I77)) -> 181.49288 | U77: =IF(J77="",T77,T77*(1+J77)) -> 195.85177 | V77: =IF(K77="",U77,U77*(1+K77)) -> 137.1417
D78: Appreciation: | E78: =IF(SUMIFS($C$244:$C$363,$A$244:$A$363,$A$77,$B$244:$B$363,E$65)=0,"",SUMIFS($M$244:$M$363,$A$244:$A$363,$A$77,$B$244:$B$363,E$65)) -> -0.076783479 | F78: =IF(SUMIFS($C$244:$C$363,$A$244:$A$363,$A$77,$B$244:$B$363,F$65)=0,"",SUMIFS($M$244:$M$363,$A$244:$A$363,$A$77,$B$244:$B$363,F$65)) -> 0.41023494 | G78: =IF(SUMIFS($C$244:$C$363,$A$244:$A$363,$A$77,$B$244:$B$363,G$65)=0,"",SUMIFS($M$244:$M$363,$A$244:$A$363,$A$77,$B$244:$B$363,G$65)) -> 0.31139163 | H78: =IF(SUMIFS($C$244:$C$363,$A$244:$A$363,$A$77,$B$244:$B$363,H$65)=0,"",SUMIFS($M$244:$M$363,$A$244:$A$363,$A$77,$B$244:$B$363,H$65)) -> -0.096911045 | I78: =IF(SUMIFS($C$244:$C$363,$A$244:$A$363,$A$77,$B$244:$B$363,I$65)=0,"",SUMIFS($M$244:$M$363,$A$244:$A$363,$A$77,$B$244:$B$363,I$65)) -> -0.0037221514 | J78: =IF(SUMIFS($C$244:$C$363,$A$244:$A$363,$A$77,$B$244:$B$363,J$65)=0,"",SUMIFS($M$244:$M$363,$A$244:$A$363,$A$77,$B$244:$B$363,J$65)) -> 0.046562806 | K78: =IF(SUMIFS($C$244:$C$363,$A$244:$A$363,$A$77,$B$244:$B$363,K$65)=0,"",SUMIFS($M$244:$M$363,$A$244:$A$363,$A$77,$B$244:$B$363,K$65)) -> -0.32122542 | L78: =V78/O78-1 -> 0.091262708 | M78: =IF($B77=0,"",(V78/O78)^(1/$B77)-1) -> 0.012554652 | O78: 100 | P78: =IF(E78="",O78,O78*(1+E78)) -> 92.321652 | Q78: =IF(F78="",P78,P78*(1+F78)) -> 130.19522 | R78: =IF(G78="",Q78,Q78*(1+G78)) -> 170.73692 | S78: =IF(H78="",R78,R78*(1+H78)) -> 154.19063 | T78: =IF(I78="",S78,S78*(1+I78)) -> 153.61671 | U78: =IF(J78="",T78,T78*(1+J78)) -> 160.76953 | V78: =IF(K78="",U78,U78*(1+K78)) -> 109.12627
D79: Income: | E79: =IF(SUMIFS($C$244:$C$363,$A$244:$A$363,$A$77,$B$244:$B$363,E$65)=0,"",SUMIFS($L$244:$L$363,$A$244:$A$363,$A$77,$B$244:$B$363,E$65)) -> 0.032251665 | F79: =IF(SUMIFS($C$244:$C$363,$A$244:$A$363,$A$77,$B$244:$B$363,F$65)=0,"",SUMIFS($L$244:$L$363,$A$244:$A$363,$A$77,$B$244:$B$363,F$65)) -> 0.040837757 | G79: =IF(SUMIFS($C$244:$C$363,$A$244:$A$363,$A$77,$B$244:$B$363,G$65)=0,"",SUMIFS($L$244:$L$363,$A$244:$A$363,$A$77,$B$244:$B$363,G$65)) -> 0.029080668 | H79: =IF(SUMIFS($C$244:$C$363,$A$244:$A$363,$A$77,$B$244:$B$363,H$65)=0,"",SUMIFS($L$244:$L$363,$A$244:$A$363,$A$77,$B$244:$B$363,H$65)) -> 0.045779758 | I79: =IF(SUMIFS($C$244:$C$363,$A$244:$A$363,$A$77,$B$244:$B$363,I$65)=0,"",SUMIFS($L$244:$L$363,$A$244:$A$363,$A$77,$B$244:$B$363,I$65)) -> 0.032899497 | J79: =IF(SUMIFS($C$244:$C$363,$A$244:$A$363,$A$77,$B$244:$B$363,J$65)=0,"",SUMIFS($L$244:$L$363,$A$244:$A$363,$A$77,$B$244:$B$363,J$65)) -> 0.032552636 | K79: =IF(SUMIFS($C$244:$C$363,$A$244:$A$363,$A$77,$B$244:$B$363,K$65)=0,"",SUMIFS($L$244:$L$363,$A$244:$A$363,$A$77,$B$244:$B$363,K$65)) -> 0.021457534 | L79: =V79/O79-1 -> 0.25964702 | M79: =IF($B77=0,"",(V79/O79)^(1/$B77)-1) -> 0.033525666 | O79: 100 | P79: =IF(E79="",O79,O79*(1+E79)) -> 103.22517 | Q79: =IF(F79="",P79,P79*(1+F79)) -> 107.44065 | R79: =IF(G79="",Q79,Q79*(1+G79)) -> 110.5651 | S79: =IF(H79="",R79,R79*(1+H79)) -> 115.62674 | T79: =IF(I79="",S79,S79*(1+I79)) -> 119.4308 | U79: =IF(J79="",T79,T79*(1+J79)) -> 123.31859 | V79: =IF(K79="",U79,U79*(1+K79)) -> 125.9647
A80: Fazenda Panorama | B80: =COUNT(E80:K80) -> 7 | C80: =SUMIFS($E$244:$E$363,$A$244:$A$363,$A80,$B$244:$B$363,K$65)/1000 -> 49.045205 | D80: Total: | E80: =IF(SUMIFS($C$244:$C$363,$A$244:$A$363,$A$80,$B$244:$B$363,E$65)=0,"",SUMIFS($N$244:$N$363,$A$244:$A$363,$A$80,$B$244:$B$363,E$65)) -> -0.010484007 | F80: =IF(SUMIFS($C$244:$C$363,$A$244:$A$363,$A$80,$B$244:$B$363,F$65)=0,"",SUMIFS($N$244:$N$363,$A$244:$A$363,$A$80,$B$244:$B$363,F$65)) -> 0.43518787 | G80: =IF(SUMIFS($C$244:$C$363,$A$244:$A$363,$A$80,$B$244:$B$363,G$65)=0,"",SUMIFS($N$244:$N$363,$A$244:$A$363,$A$80,$B$244:$B$363,G$65)) -> 0.57829984 | H80: =IF(SUMIFS($C$244:$C$363,$A$244:$A$363,$A$80,$B$244:$B$363,H$65)=0,"",SUMIFS($N$244:$N$363,$A$244:$A$363,$A$80,$B$244:$B$363,H$65)) -> -0.053073343 | I80: =IF(SUMIFS($C$244:$C$363,$A$244:$A$363,$A$80,$B$244:$B$363,I$65)=0,"",SUMIFS($N$244:$N$363,$A$244:$A$363,$A$80,$B$244:$B$363,I$65)) -> -0.19891617 | J80: =IF(SUMIFS($C$244:$C$363,$A$244:$A$363,$A$80,$B$244:$B$363,J$65)=0,"",SUMIFS($N$244:$N$363,$A$244:$A$363,$A$80,$B$244:$B$363,J$65)) -> 0.11380861 | K80: =IF(SUMIFS($C$244:$C$363,$A$244:$A$363,$A$80,$B$244:$B$363,K$65)=0,"",SUMIFS($N$244:$N$363,$A$244:$A$363,$A$80,$B$244:$B$363,K$65)) -> -0.26926715 | L80: =V80/O80-1 -> 0.3838359 | M80: =IF($B80=0,"",(V80/O80)^(1/$B80)-1) -> 0.047502195 | O80: 100 | P80: =IF(E80="",O80,O80*(1+E80)) -> 98.951599 | Q80: =IF(F80="",P80,P80*(1+F80)) -> 142.01414 | R80: =IF(G80="",Q80,Q80*(1+G80)) -> 224.14089 | S80: =IF(H80="",R80,R80*(1+H80)) -> 212.24498 | T80: =IF(I80="",S80,S80*(1+I80)) -> 170.02602 | U80: =IF(J80="",T80,T80*(1+J80)) -> 189.37645 | V80: =IF(K80="",U80,U80*(1+K80)) -> 138.38359
D81: Appreciation: | E81: =IF(SUMIFS($C$244:$C$363,$A$244:$A$363,$A$80,$B$244:$B$363,E$65)=0,"",SUMIFS($M$244:$M$363,$A$244:$A$363,$A$80,$B$244:$B$363,E$65)) -> -0.037289979 | F81: =IF(SUMIFS($C$244:$C$363,$A$244:$A$363,$A$80,$B$244:$B$363,F$65)=0,"",SUMIFS($M$244:$M$363,$A$244:$A$363,$A$80,$B$244:$B$363,F$65)) -> 0.39378493 | G81: =IF(SUMIFS($C$244:$C$363,$A$244:$A$363,$A$80,$B$244:$B$363,G$65)=0,"",SUMIFS($M$244:$M$363,$A$244:$A$363,$A$80,$B$244:$B$363,G$65)) -> 0.54245069 | H81: =IF(SUMIFS($C$244:$C$363,$A$244:$A$363,$A$80,$B$244:$B$363,H$65)=0,"",SUMIFS($M$244:$M$363,$A$244:$A$363,$A$80,$B$244:$B$363,H$65)) -> -0.096937978 | I81: =IF(SUMIFS($C$244:$C$363,$A$244:$A$363,$A$80,$B$244:$B$363,I$65)=0,"",SUMIFS($M$244:$M$363,$A$244:$A$363,$A$80,$B$244:$B$363,I$65)) -> -0.22712348 | J81: =IF(SUMIFS($C$244:$C$363,$A$244:$A$363,$A$80,$B$244:$B$363,J$65)=0,"",SUMIFS($M$244:$M$363,$A$244:$A$363,$A$80,$B$244:$B$363,J$65)) -> 0.079136599 | K81: =IF(SUMIFS($C$244:$C$363,$A$244:$A$363,$A$80,$B$244:$B$363,K$65)=0,"",SUMIFS($M$244:$M$363,$A$244:$A$363,$A$80,$B$244:$B$363,K$65)) -> -0.29225118 | L81: =V81/O81-1 -> 0.10328017 | M81: =IF($B80=0,"",(V81/O81)^(1/$B80)-1) -> 0.014140142 | O81: 100 | P81: =IF(E81="",O81,O81*(1+E81)) -> 96.271002 | Q81: =IF(F81="",P81,P81*(1+F81)) -> 134.18107 | R81: =IF(G81="",Q81,Q81*(1+G81)) -> 206.96769 | S81: =IF(H81="",R81,R81*(1+H81)) -> 186.90466 | T81: =IF(I81="",S81,S81*(1+I81)) -> 144.45422 | U81: =IF(J81="",T81,T81*(1+J81)) -> 155.88584 | V81: =IF(K81="",U81,U81*(1+K81)) -> 110.32802
D82: Income: | E82: =IF(SUMIFS($C$244:$C$363,$A$244:$A$363,$A$80,$B$244:$B$363,E$65)=0,"",SUMIFS($L$244:$L$363,$A$244:$A$363,$A$80,$B$244:$B$363,E$65)) -> 0.026805972 | F82: =IF(SUMIFS($C$244:$C$363,$A$244:$A$363,$A$80,$B$244:$B$363,F$65)=0,"",SUMIFS($L$244:$L$363,$A$244:$A$363,$A$80,$B$244:$B$363,F$65)) -> 0.041402944 | G82: =IF(SUMIFS($C$244:$C$363,$A$244:$A$363,$A$80,$B$244:$B$363,G$65)=0,"",SUMIFS($L$244:$L$363,$A$244:$A$363,$A$80,$B$244:$B$363,G$65)) -> 0.035849148 | H82: =IF(SUMIFS($C$244:$C$363,$A$244:$A$363,$A$80,$B$244:$B$363,H$65)=0,"",SUMIFS($L$244:$L$363,$A$244:$A$363,$A$80,$B$244:$B$363,H$65)) -> 0.043864635 | I82: =IF(SUMIFS($C$244:$C$363,$A$244:$A$363,$A$80,$B$244:$B$363,I$65)=0,"",SUMIFS($L$244:$L$363,$A$244:$A$363,$A$80,$B$244:$B$363,I$65)) -> 0.028207305 | J82: =IF(SUMIFS($C$244:$C$363,$A$244:$A$363,$A$80,$B$244:$B$363,J$65)=0,"",SUMIFS($L$244:$L$363,$A$244:$A$363,$A$80,$B$244:$B$363,J$65)) -> 0.034672008 | K82: =IF(SUMIFS($C$244:$C$363,$A$244:$A$363,$A$80,$B$244:$B$363,K$65)=0,"",SUMIFS($L$244:$L$363,$A$244:$A$363,$A$80,$B$244:$B$363,K$65)) -> 0.02298403 | L82: =V82/O82-1 -> 0.25834615 | M82: =IF($B80=0,"",(V82/O82)^(1/$B80)-1) -> 0.03337312 | O82: 100 | P82: =IF(E82="",O82,O82*(1+E82)) -> 102.6806 | Q82: =IF(F82="",P82,P82*(1+F82)) -> 106.93188 | R82: =IF(G82="",Q82,Q82*(1+G82)) -> 110.76529 | S82: =IF(H82="",R82,R82*(1+H82)) -> 115.62397 | T82: =IF(I82="",S82,S82*(1+I82)) -> 118.88541 | U82: =IF(J82="",T82,T82*(1+J82)) -> 123.00741 | V82: =IF(K82="",U82,U82*(1+K82)) -> 125.83461
A83: Fazenda Piratini | B83: =COUNT(E83:K83) -> 7 | C83: =SUMIFS($E$244:$E$363,$A$244:$A$363,$A83,$B$244:$B$363,K$65)/1000 -> 65.674545 | D83: Total: | E83: =IF(SUMIFS($C$244:$C$363,$A$244:$A$363,$A$83,$B$244:$B$363,E$65)=0,"",SUMIFS($N$244:$N$363,$A$244:$A$363,$A$83,$B$244:$B$363,E$65)) -> 0.34808165 | F83: =IF(SUMIFS($C$244:$C$363,$A$244:$A$363,$A$83,$B$244:$B$363,F$65)=0,"",SUMIFS($N$244:$N$363,$A$244:$A$363,$A$83,$B$244:$B$363,F$65)) -> 0.009964642 | G83: =IF(SUMIFS($C$244:$C$363,$A$244:$A$363,$A$83,$B$244:$B$363,G$65)=0,"",SUMIFS($N$244:$N$363,$A$244:$A$363,$A$83,$B$244:$B$363,G$65)) -> 0.56829781 | H83: =IF(SUMIFS($C$244:$C$363,$A$244:$A$363,$A$83,$B$244:$B$363,H$65)=0,"",SUMIFS($N$244:$N$363,$A$244:$A$363,$A$83,$B$244:$B$363,H$65)) -> -0.072326232 | I83: =IF(SUMIFS($C$244:$C$363,$A$244:$A$363,$A$83,$B$244:$B$363,I$65)=0,"",SUMIFS($N$244:$N$363,$A$244:$A$363,$A$83,$B$244:$B$363,I$65)) -> 0.20001869 | J83: =IF(SUMIFS($C$244:$C$363,$A$244:$A$363,$A$83,$B$244:$B$363,J$65)=0,"",SUMIFS($N$244:$N$363,$A$244:$A$363,$A$83,$B$244:$B$363,J$65)) -> 0.1434593 | K83: =IF(SUMIFS($C$244:$C$363,$A$244:$A$363,$A$83,$B$244:$B$363,K$65)=0,"",SUMIFS($N$244:$N$363,$A$244:$A$363,$A$83,$B$244:$B$363,K$65)) -> -0.23963564 | L83: =V83/O83-1 -> 1.0666962 | M83: =IF($B83=0,"",(V83/O83)^(1/$B83)-1) -> 0.10927576 | O83: 100 | P83: =IF(E83="",O83,O83*(1+E83)) -> 134.80817 | Q83: =IF(F83="",P83,P83*(1+F83)) -> 136.15148 | R83: =IF(G83="",Q83,Q83*(1+G83)) -> 213.52607 | S83: =IF(H83="",R83,R83*(1+H83)) -> 198.08253 | T83: =IF(I83="",S83,S83*(1+I83)) -> 237.70274 | U83: =IF(J83="",T83,T83*(1+J83)) -> 271.80341 | V83: =IF(K83="",U83,U83*(1+K83)) -> 206.66962
D84: Appreciation: | E84: =IF(SUMIFS($C$244:$C$363,$A$244:$A$363,$A$83,$B$244:$B$363,E$65)=0,"",SUMIFS($M$244:$M$363,$A$244:$A$363,$A$83,$B$244:$B$363,E$65)) -> 0.34808165 | F84: =IF(SUMIFS($C$244:$C$363,$A$244:$A$363,$A$83,$B$244:$B$363,F$65)=0,"",SUMIFS($M$244:$M$363,$A$244:$A$363,$A$83,$B$244:$B$363,F$65)) -> 0.0041471484 | G84: =IF(SUMIFS($C$244:$C$363,$A$244:$A$363,$A$83,$B$244:$B$363,G$65)=0,"",SUMIFS($M$244:$M$363,$A$244:$A$363,$A$83,$B$244:$B$363,G$65)) -> 0.54325453 | H84: =IF(SUMIFS($C$244:$C$363,$A$244:$A$363,$A$83,$B$244:$B$363,H$65)=0,"",SUMIFS($M$244:$M$363,$A$244:$A$363,$A$83,$B$244:$B$363,H$65)) -> -0.095948831 | I84: =IF(SUMIFS($C$244:$C$363,$A$244:$A$363,$A$83,$B$244:$B$363,I$65)=0,"",SUMIFS($M$244:$M$363,$A$244:$A$363,$A$83,$B$244:$B$363,I$65)) -> 0.18155746 | J84: =IF(SUMIFS($C$244:$C$363,$A$244:$A$363,$A$83,$B$244:$B$363,J$65)=0,"",SUMIFS($M$244:$M$363,$A$244:$A$363,$A$83,$B$244:$B$363,J$65)) -> 0.12763934 | K84: =IF(SUMIFS($C$244:$C$363,$A$244:$A$363,$A$83,$B$244:$B$363,K$65)=0,"",SUMIFS($M$244:$M$363,$A$244:$A$363,$A$83,$B$244:$B$363,K$65)) -> -0.25024274 | L84: =V84/O84-1 -> 0.88664365 | M84: =IF($B83=0,"",(V84/O84)^(1/$B83)-1) -> 0.094924739 | O84: 100 | P84: =IF(E84="",O84,O84*(1+E84)) -> 134.80817 | Q84: =IF(F84="",P84,P84*(1+F84)) -> 135.36723 | R84: =IF(G84="",Q84,Q84*(1+G84)) -> 208.9061 | S84: =IF(H84="",R84,R84*(1+H84)) -> 188.8618 | T84: =IF(I84="",S84,S84*(1+I84)) -> 223.15107 | U84: =IF(J84="",T84,T84*(1+J84)) -> 251.63393 | V84: =IF(K84="",U84,U84*(1+K84)) -> 188.66436
